Workbook
Name Asset_Code: [2]Code_Dictionary!$B$12:$B$14
Name DATA1: WBS.structure!$A$2:$A$525
Name DATA10: WBS.structure!$J$2:$J$525
Name DATA11: WBS.structure!$K$2:$K$525
Name DATA12: WBS.structure!$L$2:$L$525
Name DATA13: WBS.structure!$M$2:$M$525
Name DATA14: WBS.structure!$N$2:$N$525
Name DATA15: WBS.structure!$O$2:$O$525
Name DATA16: WBS.structure!$P$2:$P$525
Name DATA17: WBS.structure!$Q$2:$Q$525
Name DATA18: WBS.structure!$R$2:$R$525
Name DATA19: WBS.structure!$S$2:$S$525
Name DATA2: WBS.structure!$B$2:$B$525
Name DATA20: WBS.structure!#REF!
Name DATA21: WBS.structure!$T$2:$T$525
Name DATA3: WBS.structure!$C$2:$C$525
Name DATA4: WBS.structure!$D$2:$D$525
Name DATA5: WBS.structure!$E$2:$E$525
Name DATA6: WBS.structure!$F$2:$F$525
Name DATA7: WBS.structure!$G$2:$G$525
Name DATA8: WBS.structure!$H$2:$H$525
Name DATA9: WBS.structure!$I$2:$I$525
Name L0_list: [2]Code_Dictionary!$C$17:$C$20
Name L1_List: [2]Code_Dictionary!$D$17:$D$20
Name L2_Code: [2]Code_Dictionary!$B$30:$B$33
Name L3_AFE_code: [2]Code_Dictionary!$F$49:$F$145
Name L3_asset_code: [2]Code_Dictionary!$E$49:$E$145
Name L3_Code: [2]Code_Dictionary!$C$49:$C$145
Name L3_Code_Desc: [2]Code_Dictionary!$H$49:$H$145
Name L3_WBS_list: [2]Code_Dictionary!$G$49:$G$145
Name Level_WBS_code: WBS.structure!$B$1:$B$2426
Name SERVICE_ITEMS: [2]Code_Dictionary!$C$1265:$C$1287
Name TEST1: WBS.structure!$A$2:$T$525
Name TESTHKEY: WBS.structure!$D$1:$T$1
Name TESTKEYS: WBS.structure!$A$2:$C$525
Name TESTVKEY: WBS.structure!$A$1:$C$1
Name WBS_ACT_USD: WBS.structure!$N$2:$N$2426
Name WBS_BUD_USD: WBS.structure!$F$2:$F$2426
Name WBS_Desc: WBS.structure!$C$2:$C$2426
Name WBS_ID: WBS.structure!$D$2:$D$2426

Sheet WBS_Dictionary
A1: # | B1: LEVEL | C1: LABEL | D1: WBS CODE | E1: LVL 1 | F1: LVL 2 | G1: LVL 3 | H1: LVL 4 | I1: LVL 5 | J1: Tag_Level_2 | K1: Tag_Level_3 | L1: Tag_Level_4 | M1: Tag_LVL5 | N1: Tag_Well_Pad | O1: Tag_Well_or_Pad | P1: Middle Number
A2: 1 | B2: 01 | C2: DRJ Drilling MUW 2023 | D2: E530-30-D235301 | E2: E530-30-D235301 | P2: =_xlfn.TEXTBEFORE(_xlfn.TEXTAFTER(Table26[[#This Row],[WBS CODE]], "-"), "-") -> 30
A3: 2 | B3: 02 | C3: Surface Facilities Cost | D3: E530-30203-D235301 | E3: E530-30-D235301 | F3: E530-30203-D235301 | J3: Surface Facilities Cost | P3: =_xlfn.TEXTBEFORE(_xlfn.TEXTAFTER(Table26[[#This Row],[WBS CODE]], "-"), "-") -> 30203
A4: 3 | B4: 03 | C4: Tie-in Pad 20 | D4: E530-3020390-D235301 | E4: E530-30-D235301 | F4: E530-30203-D235301 | G4: E530-3020390-D235301 | J4: Surface Facilities Cost | K4: Tie-in | N4: Pad 20 | O4: Pad | P4: =_xlfn.TEXTBEFORE(_xlfn.TEXTAFTER(Table26[[#This Row],[WBS CODE]], "-"), "-") -> 3020390
A5: 4 | B5: 04 | C5: Tie In - Const Pad 20 | D5: E530-302039009-D235301 | E5: E530-30-D235301 | F5: E530-30203-D235301 | G5: E530-3020390-D235301 | H5: E530-302039009-D235301 | J5: Surface Facilities Cost | K5: Tie-in | L5: Construction | N5: Pad 20 | O5: Pad | P5: =_xlfn.TEXTBEFORE(_xlfn.TEXTAFTER(Table26[[#This Row],[WBS CODE]], "-"), "-") -> 302039009
A6: 5 | B6: 05 | C6: Tie In-Inst,HookUp&Pre-Comm Pad 20 | D6: E530-30203900963-D235301 | E6: E530-30-D235301 | F6: E530-30203-D235301 | G6: E530-3020390-D235301 | H6: E530-302039009-D235301 | I6: E530-30203900963-D235301 | J6: Surface Facilities Cost | K6: Tie-in | L6: Construction | M6: Installation, Hook Up & Pre-Commisioning | N6: Pad 20 | O6: Pad | P6: =_xlfn.TEXTBEFORE(_xlfn.TEXTAFTER(Table26[[#This Row],[WBS CODE]], "-"), "-") -> 30203900963
A7: 6 | B7: 04 | C7: Tie In - Proc Pad 20 | D7: E530-302039008-D235301 | E7: E530-30-D235301 | F7: E530-30203-D235301 | G7: E530-3020390-D235301 | H7: E530-302039008-D235301 | J7: Surface Facilities Cost | K7: Tie-in | L7: Procurement | N7: Pad 20 | O7: Pad | P7: =_xlfn.TEXTBEFORE(_xlfn.TEXTAFTER(Table26[[#This Row],[WBS CODE]], "-"), "-") -> 302039008
A8: 7 | B8: 05 | C8: Tie In-Material Non LL Pad 20 | D8: E530-30203900821-D235301 | E8: E530-30-D235301 | F8: E530-30203-D235301 | G8: E530-3020390-D235301 | H8: E530-302039008-D235301 | I8: E530-30203900821-D235301 | J8: Surface Facilities Cost | K8: Tie-in | L8: Procurement | M8: Material - Non LL | N8: Pad 20 | O8: Pad | P8: =_xlfn.TEXTBEFORE(_xlfn.TEXTAFTER(Table26[[#This Row],[WBS CODE]], "-"), "-") -> 30203900821
A9: 8 | B9: 05 | C9: Tie In-Material LL Pad 20 | D9: E530-30203900860-D235301 | E9: E530-30-D235301 | F9: E530-30203-D235301 | G9: E530-3020390-D235301 | H9: E530-302039008-D235301 | I9: E530-30203900860-D235301 | J9: Surface Facilities Cost | K9: Tie-in | L9: Procurement | M9: Material - LL | N9: Pad 20 | O9: Pad | P9: =_xlfn.TEXTBEFORE(_xlfn.TEXTAFTER(Table26[[#This Row],[WBS CODE]], "-"), "-") -> 30203900860
A10: 9 | B10: 04 | C10: Tie In - Eng Pad 20 | D10: E530-302039007-D235301 | E10: E530-30-D235301 | F10: E530-30203-D235301 | G10: E530-3020390-D235301 | H10: E530-302039007-D235301 | J10: Surface Facilities Cost | K10: Tie-in | L10: Engineering | N10: Pad 20 | O10: Pad | P10: =_xlfn.TEXTBEFORE(_xlfn.TEXTAFTER(Table26[[#This Row],[WBS CODE]], "-"), "-") -> 302039007
A11: 10 | B11: 05 | C11: Tie In-Eng Pad 20 | D11: E530-30203900759-D235301 | E11: E530-30-D235301 | F11: E530-30203-D235301 | G11: E530-3020390-D235301 | H11: E530-302039007-D235301 | I11: E530-30203900759-D235301 | J11: Surface Facilities Cost | K11: Tie-in | L11: Engineering | M11: Engineering | N11: Pad 20 | O11: Pad | P11: =_xlfn.TEXTBEFORE(_xlfn.TEXTAFTER(Table26[[#This Row],[WBS CODE]], "-"), "-") -> 30203900759
A12: 11 | B12: 03 | C12: Tie-in Pad 14 | D12: E530-3020389-D235301 | E12: E530-30-D235301 | F12: E530-30203-D235301 | G12: E530-3020389-D235301 | J12: Surface Facilities Cost | K12: Tie-in | N12: Pad 14 | O12: Pad | P12: =_xlfn.TEXTBEFORE(_xlfn.TEXTAFTER(Table26[[#This Row],[WBS CODE]], "-"), "-") -> 3020389
A13: 12 | B13: 04 | C13: Tie In - Const Pad 14 | D13: E530-302038909-D235301 | E13: E530-30-D235301 | F13: E530-30203-D235301 | G13: E530-3020389-D235301 | H13: E530-302038909-D235301 | J13: Surface Facilities Cost | K13: Tie-in | L13: Construction | N13: Pad 14 | O13: Pad | P13: =_xlfn.TEXTBEFORE(_xlfn.TEXTAFTER(Table26[[#This Row],[WBS CODE]], "-"), "-") -> 302038909
A14: 13 | B14: 05 | C14: Tie In-Inst,HookUp&Pre-Comm Pad 14 | D14: E530-30203890963-D235301 | E14: E530-30-D235301 | F14: E530-30203-D235301 | G14: E530-3020389-D235301 | H14: E530-302038909-D235301 | I14: E530-30203890963-D235301 | J14: Surface Facilities Cost | K14: Tie-in | L14: Construction | M14: Installation, Hook Up & Pre-Commisioning | N14: Pad 14 | O14: Pad | P14: =_xlfn.TEXTBEFORE(_xlfn.TEXTAFTER(Table26[[#This Row],[WBS CODE]], "-"), "-") -> 30203890963
A15: 14 | B15: 04 | C15: Tie In - Proc Pad 14 | D15: E530-302038908-D235301 | E15: E530-30-D235301 | F15: E530-30203-D235301 | G15: E530-3020389-D235301 | H15: E530-302038908-D235301 | J15: Surface Facilities Cost | K15: Tie-in | L15: Procurement | N15: Pad 14 | O15: Pad | P15: =_xlfn.TEXTBEFORE(_xlfn.TEXTAFTER(Table26[[#This Row],[WBS CODE]], "-"), "-") -> 302038908
A16: 15 | B16: 05 | C16: Tie In-Material Non LL Pad 14 | D16: E530-30203890821-D235301 | E16: E530-30-D235301 | F16: E530-30203-D235301 | G16: E530-3020389-D235301 | H16: E530-302038908-D235301 | I16: E530-30203890821-D235301 | J16: Surface Facilities Cost | K16: Tie-in | L16: Procurement | M16: Material - Non LL | N16: Pad 14 | O16: Pad | P16: =_xlfn.TEXTBEFORE(_xlfn.TEXTAFTER(Table26[[#This Row],[WBS CODE]], "-"), "-") -> 30203890821
A17: 16 | B17: 05 | C17: Tie In-Material LL Pad 14 | D17: E530-30203890860-D235301 | E17: E530-30-D235301 | F17: E530-30203-D235301 | G17: E530-3020389-D235301 | H17: E530-302038908-D235301 | I17: E530-30203890860-D235301 | J17: Surface Facilities Cost | K17: Tie-in | L17: Procurement | M17: Material - LL | N17: Pad 14 | O17: Pad | P17: =_xlfn.TEXTBEFORE(_xlfn.TEXTAFTER(Table26[[#This Row],[WBS CODE]], "-"), "-") -> 30203890860
A18: 17 | B18: 04 | C18: Tie In - Eng Pad 14 | D18: E530-302038907-D235301 | E18: E530-30-D235301 | F18: E530-30203-D235301 | G18: E530-3020389-D235301 | H18: E530-302038907-D235301 | J18: Surface Facilities Cost | K18: Tie-in | L18: Engineering | N18: Pad 14 | O18: Pad | P18: =_xlfn.TEXTBEFORE(_xlfn.TEXTAFTER(Table26[[#This Row],[WBS CODE]], "-"), "-") -> 302038907
A19: 18 | B19: 05 | C19: Tie In-Eng Pad 14 | D19: E530-30203890759-D235301 | E19: E530-30-D235301 | F19: E530-30203-D235301 | G19: E530-3020389-D235301 | H19: E530-302038907-D235301 | I19: E530-30203890759-D235301 | J19: Surface Facilities Cost | K19: Tie-in | L19: Engineering | M19: Engineering | N19: Pad 14 | O19: Pad | P19: =_xlfn.TEXTBEFORE(_xlfn.TEXTAFTER(Table26[[#This Row],[WBS CODE]], "-"), "-") -> 30203890759
A20: 19 | B20: 03 | C20: Tie-in Pad 18 | D20: E530-3020388-D235301 | E20: E530-30-D235301 | F20: E530-30203-D235301 | G20: E530-3020388-D235301 | J20: Surface Facilities Cost | K20: Tie-in | N20: Pad 18 | O20: Pad | P20: =_xlfn.TEXTBEFORE(_xlfn.TEXTAFTER(Table26[[#This Row],[WBS CODE]], "-"), "-") -> 3020388
A21: 20 | B21: 04 | C21: Tie In - Const Pad 18 | D21: E530-302038809-D235301 | E21: E530-30-D235301 | F21: E530-30203-D235301 | G21: E530-3020388-D235301 | H21: E530-302038809-D235301 | J21: Surface Facilities Cost | K21: Tie-in | L21: Construction | N21: Pad 18 | O21: Pad | P21: =_xlfn.TEXTBEFORE(_xlfn.TEXTAFTER(Table26[[#This Row],[WBS CODE]], "-"), "-") -> 302038809
A22: 21 | B22: 05 | C22: Tie In-Inst,HookUp&Pre-Comm Pad 18 | D22: E530-30203880963-D235301 | E22: E530-30-D235301 | F22: E530-30203-D235301 | G22: E530-3020388-D235301 | H22: E530-302038809-D235301 | I22: E530-30203880963-D235301 | J22: Surface Facilities Cost | K22: Tie-in | L22: Construction | M22: Installation, Hook Up & Pre-Commisioning | N22: Pad 18 | O22: Pad | P22: =_xlfn.TEXTBEFORE(_xlfn.TEXTAFTER(Table26[[#This Row],[WBS CODE]], "-"), "-") -> 30203880963
A23: 22 | B23: 04 | C23: Tie In - Proc Pad 18 | D23: E530-302038808-D235301 | E23: E530-30-D235301 | F23: E530-30203-D235301 | G23: E530-3020388-D235301 | H23: E530-302038808-D235301 | J23: Surface Facilities Cost | K23: Tie-in | L23: Procurement | N23: Pad 18 | O23: Pad | P23: =_xlfn.TEXTBEFORE(_xlfn.TEXTAFTER(Table26[[#This Row],[WBS CODE]], "-"), "-") -> 302038808
A24: 23 | B24: 05 | C24: Tie In-Material Non LL Pad 18 | D24: E530-30203880821-D235301 | E24: E530-30-D235301 | F24: E530-30203-D235301 | G24: E530-3020388-D235301 | H24: E530-302038808-D235301 | I24: E530-30203880821-D235301 | J24: Surface Facilities Cost | K24: Tie-in | L24: Procurement | M24: Material - Non LL | N24: Pad 18 | O24: Pad | P24: =_xlfn.TEXTBEFORE(_xlfn.TEXTAFTER(Table26[[#This Row],[WBS CODE]], "-"), "-") -> 30203880821
A25: 24 | B25: 05 | C25: Tie In-Material LL Pad 18 | D25: E530-30203880860-D235301 | E25: E530-30-D235301 | F25: E530-30203-D235301 | G25: E530-3020388-D235301 | H25: E530-302038808-D235301 | I25: E530-30203880860-D235301 | J25: Surface Facilities Cost | K25: Tie-in | L25: Procurement | M25: Material - LL | N25: Pad 18 | O25: Pad | P25: =_xlfn.TEXTBEFORE(_xlfn.TEXTAFTER(Table26[[#This Row],[WBS CODE]], "-"), "-") -> 30203880860
A26: 25 | B26: 04 | C26: Tie In - Eng Pad 18 | D26: E530-302038807-D235301 | E26: E530-30-D235301 | F26: E530-30203-D235301 | G26: E530-3020388-D235301 | H26: E530-302038807-D235301 | J26: Surface Facilities Cost | K26: Tie-in | L26: Engineering | N26: Pad 18 | O26: Pad | P26: =_xlfn.TEXTBEFORE(_xlfn.TEXTAFTER(Table26[[#This Row],[WBS CODE]], "-"), "-") -> 302038807
A27: 26 | B27: 05 | C27: Tie In-Eng Pad 18 | D27: E530-30203880759-D235301 | E27: E530-30-D235301 | F27: E530-30203-D235301 | G27: E530-3020388-D235301 | H27: E530-302038807-D235301 | I27: E530-30203880759-D235301 | J27: Surface Facilities Cost | K27: Tie-in | L27: Engineering | M27: Engineering | N27: Pad 18 | O27: Pad | P27: =_xlfn.TEXTBEFORE(_xlfn.TEXTAFTER(Table26[[#This Row],[WBS CODE]], "-"), "-") -> 30203880759
A28: 27 | B28: 03 | C28: Tie-in Pad 15 | D28: E530-3020387-D235301 | E28: E530-30-D235301 | F28: E530-30203-D235301 | G28: E530-3020387-D235301 | J28: Surface Facilities Cost | K28: Tie-in | N28: Pad 15 | O28: Pad | P28: =_xlfn.TEXTBEFORE(_xlfn.TEXTAFTER(Table26[[#This Row],[WBS CODE]], "-"), "-") -> 3020387
A29: 28 | B29: 04 | C29: Tie In - Const Pad 15 | D29: E530-302038709-D235301 | E29: E530-30-D235301 | F29: E530-30203-D235301 | G29: E530-3020387-D235301 | H29: E530-302038709-D235301 | J29: Surface Facilities Cost | K29: Tie-in | L29: Construction | N29: Pad 15 | O29: Pad | P29: =_xlfn.TEXTBEFORE(_xlfn.TEXTAFTER(Table26[[#This Row],[WBS CODE]], "-"), "-") -> 302038709
A30: 29 | B30: 05 | C30: Tie In-Inst,HookUp&Pre-Comm Pad 15 | D30: E530-30203870963-D235301 | E30: E530-30-D235301 | F30: E530-30203-D235301 | G30: E530-3020387-D235301 | H30: E530-302038709-D235301 | I30: E530-30203870963-D235301 | J30: Surface Facilities Cost | K30: Tie-in | L30: Construction | M30: Installation, Hook Up & Pre-Commisioning | N30: Pad 15 | O30: Pad | P30: =_xlfn.TEXTBEFORE(_xlfn.TEXTAFTER(Table26[[#This Row],[WBS CODE]], "-"), "-") -> 30203870963
A31: 30 | B31: 04 | C31: Tie In - Proc Pad 15 | D31: E530-302038708-D235301 | E31: E530-30-D235301 | F31: E530-30203-D235301 | G31: E530-3020387-D235301 | H31: E530-302038708-D235301 | J31: Surface Facilities Cost | K31: Tie-in | L31: Procurement | N31: Pad 15 | O31: Pad | P31: =_xlfn.TEXTBEFORE(_xlfn.TEXTAFTER(Table26[[#This Row],[WBS CODE]], "-"), "-") -> 302038708
A32: 31 | B32: 05 | C32: Tie In-Material Non LL Pad 15 | D32: E530-30203870821-D235301 | E32: E530-30-D235301 | F32: E530-30203-D235301 | G32: E530-3020387-D235301 | H32: E530-302038708-D235301 | I32: E530-30203870821-D235301 | J32: Surface Facilities Cost | K32: Tie-in | L32: Procurement | M32: Material - Non LL | N32: Pad 15 | O32: Pad | P32: =_xlfn.TEXTBEFORE(_xlfn.TEXTAFTER(Table26[[#This Row],[WBS CODE]], "-"), "-") -> 30203870821
A33: 32 | B33: 05 | C33: Tie In-Material LL Pad 15 | D33: E530-30203870860-D235301 | E33: E530-30-D235301 | F33: E530-30203-D235301 | G33: E530-3020387-D235301 | H33: E530-302038708-D235301 | I33: E530-30203870860-D235301 | J33: Surface Facilities Cost | K33: Tie-in | L33: Procurement | M33: Material - LL | N33: Pad 15 | O33: Pad | P33: =_xlfn.TEXTBEFORE(_xlfn.TEXTAFTER(Table26[[#This Row],[WBS CODE]], "-"), "-") -> 30203870860
A34: 33 | B34: 04 | C34: Tie In - Eng Pad 15 | D34: E530-302038707-D235301 | E34: E530-30-D235301 | F34: E530-30203-D235301 | G34: E530-3020387-D235301 | H34: E530-302038707-D235301 | J34: Surface Facilities Cost | K34: Tie-in | L34: Engineering | N34: Pad 15 | O34: Pad | P34: =_xlfn.TEXTBEFORE(_xlfn.TEXTAFTER(Table26[[#This Row],[WBS CODE]], "-"), "-") -> 302038707
A35: 34 | B35: 05 | C35: Tie In-Eng Pad 15 | D35: E530-30203870759-D235301 | E35: E530-30-D235301 | F35: E530-30203-D235301 | G35: E530-3020387-D235301 | H35: E530-302038707-D235301 | I35: E530-30203870759-D235301 | J35: Surface Facilities Cost | K35: Tie-in | L35: Engineering | M35: Engineering | N35: Pad 15 | O35: Pad | P35: =_xlfn.TEXTBEFORE(_xlfn.TEXTAFTER(Table26[[#This Row],[WBS CODE]], "-"), "-") -> 30203870759
A36: 35 | B36: 03 | C36: Special Requirement Existing - Pad 20 | D36: E530-3020394-D235301 | E36: E530-30-D235301 | F36: E530-30203-D235301 | G36: E530-3020394-D235301 | J36: Surface Facilities Cost | K36: Special Requirement Existing Pad | N36: Pad 20 | O36: Pad | P36: =_xlfn.TEXTBEFORE(_xlfn.TEXTAFTER(Table26[[#This Row],[WBS CODE]], "-"), "-") -> 3020394
A37: 36 | B37: 04 | C37: Spec Req - Const Pad 20 | D37: E530-302039409-D235301 | E37: E530-30-D235301 | F37: E530-30203-D235301 | G37: E530-3020394-D235301 | H37: E530-302039409-D235301 | J37: Surface Facilities Cost | K37: Special Requirement Existing Pad | L37: Construction | N37: Pad 20 | O37: Pad | P37: =_xlfn.TEXTBEFORE(_xlfn.TEXTAFTER(Table26[[#This Row],[WBS CODE]], "-"), "-") -> 302039409
A38: 37 | B38: 05 | C38: Spec Req Const Pad 20 | D38: E530-30203940962-D235301 | E38: E530-30-D235301 | F38: E530-30203-D235301 | G38: E530-3020394-D235301 | H38: E530-302039409-D235301 | I38: E530-30203940962-D235301 | J38: Surface Facilities Cost | K38: Special Requirement Existing Pad | L38: Construction | M38: Construction | N38: Pad 20 | O38: Pad | P38: =_xlfn.TEXTBEFORE(_xlfn.TEXTAFTER(Table26[[#This Row],[WBS CODE]], "-"), "-") -> 30203940962
A39: 38 | B39: 04 | C39: Spec Req - Proc Pad 20 | D39: E530-302039408-D235301 | E39: E530-30-D235301 | F39: E530-30203-D235301 | G39: E530-3020394-D235301 | H39: E530-302039408-D235301 | J39: Surface Facilities Cost | K39: Special Requirement Existing Pad | L39: Procurement | N39: Pad 20 | O39: Pad | P39: =_xlfn.TEXTBEFORE(_xlfn.TEXTAFTER(Table26[[#This Row],[WBS CODE]], "-"), "-") -> 302039408
A40: 39 | B40: 05 | C40: Spec Req Material Non LL Pad 20 | D40: E530-30203940821-D235301 | E40: E530-30-D235301 | F40: E530-30203-D235301 | G40: E530-3020394-D235301 | H40: E530-302039408-D235301 | I40: E530-30203940821-D235301 | J40: Surface Facilities Cost | K40: Special Requirement Existing Pad | L40: Procurement | M40: Material - Non LL | N40: Pad 20 | O40: Pad | P40: =_xlfn.TEXTBEFORE(_xlfn.TEXTAFTER(Table26[[#This Row],[WBS CODE]], "-"), "-") -> 30203940821
A41: 40 | B41: 05 | C41: Spec Req Material LL Pad 20 | D41: E530-30203940860-D235301 | E41: E530-30-D235301 | F41: E530-30203-D235301 | G41: E530-3020394-D235301 | H41: E530-302039408-D235301 | I41: E530-30203940860-D235301 | J41: Surface Facilities Cost | K41: Special Requirement Existing Pad | L41: Procurement | M41: Material - LL | N41: Pad 20 | O41: Pad | P41: =_xlfn.TEXTBEFORE(_xlfn.TEXTAFTER(Table26[[#This Row],[WBS CODE]], "-"), "-") -> 30203940860
A42: 41 | B42: 04 | C42: Spec Req - Eng Pad 20 | D42: E530-302039407-D235301 | E42: E530-30-D235301 | F42: E530-30203-D235301 | G42: E530-3020394-D235301 | H42: E530-302039407-D235301 | J42: Surface Facilities Cost | K42: Special Requirement Existing Pad | L42: Engineering | N42: Pad 20 | O42: Pad | P42: =_xlfn.TEXTBEFORE(_xlfn.TEXTAFTER(Table26[[#This Row],[WBS CODE]], "-"), "-") -> 302039407
A43: 42 | B43: 05 | C43: Spec Req Eng Pad 20 | D43: E530-30203940759-D235301 | E43: E530-30-D235301 | F43: E530-30203-D235301 | G43: E530-3020394-D235301 | H43: E530-302039407-D235301 | I43: E530-30203940759-D235301 | J43: Surface Facilities Cost | K43: Special Requirement Existing Pad | L43: Engineering | M43: Engineering | N43: Pad 20 | O43: Pad | P43: =_xlfn.TEXTBEFORE(_xlfn.TEXTAFTER(Table26[[#This Row],[WBS CODE]], "-"), "-") -> 30203940759
A44: 43 | B44: 03 | C44: Special Requirement Existing - Pad 14 | D44: E530-3020393-D235301 | E44: E530-30-D235301 | F44: E530-30203-D235301 | G44: E530-3020393-D235301 | J44: Surface Facilities Cost | K44: Special Requirement Existing Pad | N44: Pad 14 | O44: Pad | P44: =_xlfn.TEXTBEFORE(_xlfn.TEXTAFTER(Table26[[#This Row],[WBS CODE]], "-"), "-") -> 3020393
A45: 44 | B45: 04 | C45: Spec Req - Const Pad 14 | D45: E530-302039309-D235301 | E45: E530-30-D235301 | F45: E530-30203-D235301 | G45: E530-3020393-D235301 | H45: E530-302039309-D235301 | J45: Surface Facilities Cost | K45: Special Requirement Existing Pad | L45: Construction | N45: Pad 14 | O45: Pad | P45: =_xlfn.TEXTBEFORE(_xlfn.TEXTAFTER(Table26[[#This Row],[WBS CODE]], "-"), "-") -> 302039309
A46: 45 | B46: 05 | C46: Spec Req Const Pad 14 | D46: E530-30203930962-D235301 | E46: E530-30-D235301 | F46: E530-30203-D235301 | G46: E530-3020393-D235301 | H46: E530-302039309-D235301 | I46: E530-30203930962-D235301 | J46: Surface Facilities Cost | K46: Special Requirement Existing Pad | L46: Construction | M46: Construction | N46: Pad 14 | O46: Pad | P46: =_xlfn.TEXTBEFORE(_xlfn.TEXTAFTER(Table26[[#This Row],[WBS CODE]], "-"), "-") -> 30203930962
A47: 46 | B47: 04 | C47: Spec Req - Proc Pad 14 | D47: E530-302039308-D235301 | E47: E530-30-D235301 | F47: E530-30203-D235301 | G47: E530-3020393-D235301 | H47: E530-302039308-D235301 | J47: Surface Facilities Cost | K47: Special Requirement Existing Pad | L47: Procurement | N47: Pad 14 | O47: Pad | P47: =_xlfn.TEXTBEFORE(_xlfn.TEXTAFTER(Table26[[#This Row],[WBS CODE]], "-"), "-") -> 302039308
A48: 47 | B48: 05 | C48: Spec Req Material Non LL Pad 14 | D48: E530-30203930821-D235301 | E48: E530-30-D235301 | F48: E530-30203-D235301 | G48: E530-3020393-D235301 | H48: E530-302039308-D235301 | I48: E530-30203930821-D235301 | J48: Surface Facilities Cost | K48: Special Requirement Existing Pad | L48: Procurement | M48: Material - Non LL | N48: Pad 14 | O48: Pad | P48: =_xlfn.TEXTBEFORE(_xlfn.TEXTAFTER(Table26[[#This Row],[WBS CODE]], "-"), "-") -> 30203930821
A49: 48 | B49: 05 | C49: Spec Req Material LL Pad 14 | D49: E530-30203930860-D235301 | E49: E530-30-D235301 | F49: E530-30203-D235301 | G49: E530-3020393-D235301 | H49: E530-302039308-D235301 | I49: E530-30203930860-D235301 | J49: Surface Facilities Cost | K49: Special Requirement Existing Pad | L49: Procurement | M49: Material - LL | N49: Pad 14 | O49: Pad | P49: =_xlfn.TEXTBEFORE(_xlfn.TEXTAFTER(Table26[[#This Row],[WBS CODE]], "-"), "-") -> 30203930860
A50: 49 | B50: 04 | C50: Spec Req - Eng Pad 14 | D50: E530-302039307-D235301 | E50: E530-30-D235301 | F50: E530-30203-D235301 | G50: E530-3020393-D235301 | H50: E530-302039307-D235301 | J50: Surface Facilities Cost | K50: Special Requirement Existing Pad | L50: Engineering | N50: Pad 14 | O50: Pad | P50: =_xlfn.TEXTBEFORE(_xlfn.TEXTAFTER(Table26[[#This Row],[WBS CODE]], "-"), "-") -> 302039307
A51: 50 | B51: 05 | C51: Spec Req Eng Pad 14 | D51: E530-30203930759-D235301 | E51: E530-30-D235301 | F51: E530-30203-D235301 | G51: E530-3020393-D235301 | H51: E530-302039307-D235301 | I51: E530-30203930759-D235301 | J51: Surface Facilities Cost | K51: Special Requirement Existing Pad | L51: Engineering | M51: Engineering | N51: Pad 14 | O51: Pad | P51: =_xlfn.TEXTBEFORE(_xlfn.TEXTAFTER(Table26[[#This Row],[WBS CODE]], "-"), "-") -> 30203930759
A52: 51 | B52: 03 | C52: Special Requirement Existing - Pad 18 | D52: E530-3020392-D235301 | E52: E530-30-D235301 | F52: E530-30203-D235301 | G52: E530-3020392-D235301 | J52: Surface Facilities Cost | K52: Special Requirement Existing Pad | N52: Pad 18 | O52: Pad | P52: =_xlfn.TEXTBEFORE(_xlfn.TEXTAFTER(Table26[[#This Row],[WBS CODE]], "-"), "-") -> 3020392
A53: 52 | B53: 04 | C53: Spec Req - Const Pad 18 | D53: E530-302039209-D235301 | E53: E530-30-D235301 | F53: E530-30203-D235301 | G53: E530-3020392-D235301 | H53: E530-302039209-D235301 | J53: Surface Facilities Cost | K53: Special Requirement Existing Pad | L53: Construction | N53: Pad 18 | O53: Pad | P53: =_xlfn.TEXTBEFORE(_xlfn.TEXTAFTER(Table26[[#This Row],[WBS CODE]], "-"), "-") -> 302039209
A54: 53 | B54: 05 | C54: Spec Req Const Pad 18 | D54: E530-30203920962-D235301 | E54: E530-30-D235301 | F54: E530-30203-D235301 | G54: E530-3020392-D235301 | H54: E530-302039209-D235301 | I54: E530-30203920962-D235301 | J54: Surface Facilities Cost | K54: Special Requirement Existing Pad | L54: Construction | M54: Construction | N54: Pad 18 | O54: Pad | P54: =_xlfn.TEXTBEFORE(_xlfn.TEXTAFTER(Table26[[#This Row],[WBS CODE]], "-"), "-") -> 30203920962
A55: 54 | B55: 04 | C55: Spec Req - Proc Pad 18 | D55: E530-302039208-D235301 | E55: E530-30-D235301 | F55: E530-30203-D235301 | G55: E530-3020392-D235301 | H55: E530-302039208-D235301 | J55: Surface Facilities Cost | K55: Special Requirement Existing Pad | L55: Procurement | N55: Pad 18 | O55: Pad | P55: =_xlfn.TEXTBEFORE(_xlfn.TEXTAFTER(Table26[[#This Row],[WBS CODE]], "-"), "-") -> 302039208
A56: 55 | B56: 05 | C56: Spec Req Material Non LL Pad 18 | D56: E530-30203920821-D235301 | E56: E530-30-D235301 | F56: E530-30203-D235301 | G56: E530-3020392-D235301 | H56: E530-302039208-D235301 | I56: E530-30203920821-D235301 | J56: Surface Facilities Cost | K56: Special Requirement Existing Pad | L56: Procurement | M56: Material - Non LL | N56: Pad 18 | O56: Pad | P56: =_xlfn.TEXTBEFORE(_xlfn.TEXTAFTER(Table26[[#This Row],[WBS CODE]], "-"), "-") -> 30203920821
A57: 56 | B57: 05 | C57: Spec Req Material LL Pad 18 | D57: E530-30203920860-D235301 | E57: E530-30-D235301 | F57: E530-30203-D235301 | G57: E530-3020392-D235301 | H57: E530-302039208-D235301 | I57: E530-30203920860-D235301 | J57: Surface Facilities Cost | K57: Special Requirement Existing Pad | L57: Procurement | M57: Material - LL | N57: Pad 18 | O57: Pad | P57: =_xlfn.TEXTBEFORE(_xlfn.TEXTAFTER(Table26[[#This Row],[WBS CODE]], "-"), "-") -> 30203920860
A58: 57 | B58: 04 | C58: Spec Req - Eng Pad 18 | D58: E530-302039207-D235301 | E58: E530-30-D235301 | F58: E530-30203-D235301 | G58: E530-3020392-D235301 | H58: E530-302039207-D235301 | J58: Surface Facilities Cost | K58: Special Requirement Existing Pad | L58: Engineering | N58: Pad 18 | O58: Pad | P58: =_xlfn.TEXTBEFORE(_xlfn.TEXTAFTER(Table26[[#This Row],[WBS CODE]], "-"), "-") -> 302039207
A59: 58 | B59: 05 | C59: Spec Req Eng Pad 18 | D59: E530-30203920759-D235301 | E59: E530-30-D235301 | F59: E530-30203-D235301 | G59: E530-3020392-D235301 | H59: E530-302039207-D235301 | I59: E530-30203920759-D235301 | J59: Surface Facilities Cost | K59: Special Requirement Existing Pad | L59: Engineering | M59: Engineering | N59: Pad 18 | O59: Pad | P59: =_xlfn.TEXTBEFORE(_xlfn.TEXTAFTER(Table26[[#This Row],[WBS CODE]], "-"), "-") -> 30203920759
A60: 59 | B60: 03 | C60: Road and Pad - Pad 20 | D60: E530-3020386-D235301 | E60: E530-30-D235301 | F60: E530-30203-D235301 | G60: E530-3020386-D235301 | J60: Surface Facilities Cost | K60: Road & Pad | N60: Pad 20 | O60: Pad | P60: =_xlfn.TEXTBEFORE(_xlfn.TEXTAFTER(Table26[[#This Row],[WBS CODE]], "-"), "-") -> 3020386
A61: 60 | B61: 04 | C61: Road & Pad - Const Pad 20 | D61: E530-302038609-D235301 | E61: E530-30-D235301 | F61: E530-30203-D235301 | G61: E530-3020386-D235301 | H61: E530-302038609-D235301 | J61: Surface Facilities Cost | K61: Road & Pad | L61: Construction | N61: Pad 20 | O61: Pad | P61: =_xlfn.TEXTBEFORE(_xlfn.TEXTAFTER(Table26[[#This Row],[WBS CODE]], "-"), "-") -> 302038609
A62: 61 | B62: 05 | C62: Road & Pad Const Pad 20 | D62: E530-30203860962-D235301 | E62: E530-30-D235301 | F62: E530-30203-D235301 | G62: E530-3020386-D235301 | H62: E530-302038609-D235301 | I62: E530-30203860962-D235301 | J62: Surface Facilities Cost | K62: Road & Pad | L62: Construction | M62: Construction | N62: Pad 20 | O62: Pad | P62: =_xlfn.TEXTBEFORE(_xlfn.TEXTAFTER(Table26[[#This Row],[WBS CODE]], "-"), "-") -> 30203860962
A63: 62 | B63: 04 | C63: Road & Pad - Proc Pad 20 | D63: E530-302038608-D235301 | E63: E530-30-D235301 | F63: E530-30203-D235301 | G63: E530-3020386-D235301 | H63: E530-302038608-D235301 | J63: Surface Facilities Cost | K63: Road & Pad | L63: Procurement | N63: Pad 20 | O63: Pad | P63: =_xlfn.TEXTBEFORE(_xlfn.TEXTAFTER(Table26[[#This Row],[WBS CODE]], "-"), "-") -> 302038608
A64: 63 | B64: 05 | C64: Road & Pad Material Non LL Pad 20 | D64: E530-30203860821-D235301 | E64: E530-30-D235301 | F64: E530-30203-D235301 | G64: E530-3020386-D235301 | H64: E530-302038608-D235301 | I64: E530-30203860821-D235301 | J64: Surface Facilities Cost | K64: Road & Pad | L64: Procurement | M64: Material - Non LL | N64: Pad 20 | O64: Pad | P64: =_xlfn.TEXTBEFORE(_xlfn.TEXTAFTER(Table26[[#This Row],[WBS CODE]], "-"), "-") -> 30203860821
A65: 64 | B65: 05 | C65: Road & Pad Material LL Pad 20 | D65: E530-30203860860-D235301 | E65: E530-30-D235301 | F65: E530-30203-D235301 | G65: E530-3020386-D235301 | H65: E530-302038608-D235301 | I65: E530-30203860860-D235301 | J65: Surface Facilities Cost | K65: Road & Pad | L65: Procurement | M65: Material - LL | N65: Pad 20 | O65: Pad | P65: =_xlfn.TEXTBEFORE(_xlfn.TEXTAFTER(Table26[[#This Row],[WBS CODE]], "-"), "-") -> 30203860860
A66: 65 | B66: 04 | C66: Road & Pad - Eng Pad 20 | D66: E530-302038607-D235301 | E66: E530-30-D235301 | F66: E530-30203-D235301 | G66: E530-3020386-D235301 | H66: E530-302038607-D235301 | J66: Surface Facilities Cost | K66: Road & Pad | L66: Engineering | N66: Pad 20 | O66: Pad | P66: =_xlfn.TEXTBEFORE(_xlfn.TEXTAFTER(Table26[[#This Row],[WBS CODE]], "-"), "-") -> 302038607
A67: 66 | B67: 05 | C67: Road & Pad Eng Pad 20 | D67: E530-30203860759-D235301 | E67: E530-30-D235301 | F67: E530-30203-D235301 | G67: E530-3020386-D235301 | H67: E530-302038607-D235301 | I67: E530-30203860759-D235301 | J67: Surface Facilities Cost | K67: Road & Pad | L67: Engineering | M67: Engineering | N67: Pad 20 | O67: Pad | P67: =_xlfn.TEXTBEFORE(_xlfn.TEXTAFTER(Table26[[#This Row],[WBS CODE]], "-"), "-") -> 30203860759
A68: 67 | B68: 03 | C68: Road and Pad - Pad 14 | D68: E530-3020385-D235301 | E68: E530-30-D235301 | F68: E530-30203-D235301 | G68: E530-3020385-D235301 | J68: Surface Facilities Cost | K68: Road & Pad | N68: Pad 14 | O68: Pad | P68: =_xlfn.TEXTBEFORE(_xlfn.TEXTAFTER(Table26[[#This Row],[WBS CODE]], "-"), "-") -> 3020385
A69: 68 | B69: 04 | C69: Road & Pad - Const Pad 14 | D69: E530-302038509-D235301 | E69: E530-30-D235301 | F69: E530-30203-D235301 | G69: E530-3020385-D235301 | H69: E530-302038509-D235301 | J69: Surface Facilities Cost | K69: Road & Pad | L69: Construction | N69: Pad 14 | O69: Pad | P69: =_xlfn.TEXTBEFORE(_xlfn.TEXTAFTER(Table26[[#This Row],[WBS CODE]], "-"), "-") -> 302038509
A70: 69 | B70: 05 | C70: Road & Pad Const Pad 14 | D70: E530-30203850962-D235301 | E70: E530-30-D235301 | F70: E530-30203-D235301 | G70: E530-3020385-D235301 | H70: E530-302038509-D235301 | I70: E530-30203850962-D235301 | J70: Surface Facilities Cost | K70: Road & Pad | L70: Construction | M70: Construction | N70: Pad 14 | O70: Pad | P70: =_xlfn.TEXTBEFORE(_xlfn.TEXTAFTER(Table26[[#This Row],[WBS CODE]], "-"), "-") -> 30203850962
A71: 70 | B71: 04 | C71: Road & Pad - Proc Pad 14 | D71: E530-302038508-D235301 | E71: E530-30-D235301 | F71: E530-30203-D235301 | G71: E530-3020385-D235301 | H71: E530-302038508-D235301 | J71: Surface Facilities Cost | K71: Road & Pad | L71: Procurement | N71: Pad 14 | O71: Pad | P71: =_xlfn.TEXTBEFORE(_xlfn.TEXTAFTER(Table26[[#This Row],[WBS CODE]], "-"), "-") -> 302038508
A72: 71 | B72: 05 | C72: Road & Pad Material Non LL Pad 14 | D72: E530-30203850821-D235301 | E72: E530-30-D235301 | F72: E530-30203-D235301 | G72: E530-3020385-D235301 | H72: E530-302038508-D235301 | I72: E530-30203850821-D235301 | J72: Surface Facilities Cost | K72: Road & Pad | L72: Procurement | M72: Material - Non LL | N72: Pad 14 | O72: Pad | P72: =_xlfn.TEXTBEFORE(_xlfn.TEXTAFTER(Table26[[#This Row],[WBS CODE]], "-"), "-") -> 30203850821
A73: 72 | B73: 05 | C73: Road & Pad Material LL Pad 14 | D73: E530-30203850860-D235301 | E73: E530-30-D235301 | F73: E530-30203-D235301 | G73: E530-3020385-D235301 | H73: E530-302038508-D235301 | I73: E530-30203850860-D235301 | J73: Surface Facilities Cost | K73: Road & Pad | L73: Procurement | M73: Material - LL | N73: Pad 14 | O73: Pad | P73: =_xlfn.TEXTBEFORE(_xlfn.TEXTAFTER(Table26[[#This Row],[WBS CODE]], "-"), "-") -> 30203850860
A74: 73 | B74: 04 | C74: Road & Pad - Eng Pad 14 | D74: E530-302038507-D235301 | E74: E530-30-D235301 | F74: E530-30203-D235301 | G74: E530-3020385-D235301 | H74: E530-302038507-D235301 | J74: Surface Facilities Cost | K74: Road & Pad | L74: Engineering | N74: Pad 14 | O74: Pad | P74: =_xlfn.TEXTBEFORE(_xlfn.TEXTAFTER(Table26[[#This Row],[WBS CODE]], "-"), "-") -> 302038507
A75: 74 | B75: 05 | C75: Road & Pad Eng Pad 14 | D75: E530-30203850759-D235301 | E75: E530-30-D235301 | F75: E530-30203-D235301 | G75: E530-3020385-D235301 | H75: E530-302038507-D235301 | I75: E530-30203850759-D235301 | J75: Surface Facilities Cost | K75: Road & Pad | L75: Engineering | M75: Engineering | N75: Pad 14 | O75: Pad | P75: =_xlfn.TEXTBEFORE(_xlfn.TEXTAFTER(Table26[[#This Row],[WBS CODE]], "-"), "-") -> 30203850759
A76: 75 | B76: 03 | C76: Road and Pad - Pad 18 | D76: E530-3020384-D235301 | E76: E530-30-D235301 | F76: E530-30203-D235301 | G76: E530-3020384-D235301 | J76: Surface Facilities Cost | K76: Road & Pad | N76: Pad 18 | O76: Pad | P76: =_xlfn.TEXTBEFORE(_xlfn.TEXTAFTER(Table26[[#This Row],[WBS CODE]], "-"), "-") -> 3020384
A77: 76 | B77: 04 | C77: Road & Pad - Const Pad 18 | D77: E530-302038409-D235301 | E77: E530-30-D235301 | F77: E530-30203-D235301 | G77: E530-3020384-D235301 | H77: E530-302038409-D235301 | J77: Surface Facilities Cost | K77: Road & Pad | L77: Construction | N77: Pad 18 | O77: Pad | P77: =_xlfn.TEXTBEFORE(_xlfn.TEXTAFTER(Table26[[#This Row],[WBS CODE]], "-"), "-") -> 302038409
A78: 77 | B78: 05 | C78: Road & Pad Const Pad 18 | D78: E530-30203840962-D235301 | E78: E530-30-D235301 | F78: E530-30203-D235301 | G78: E530-3020384-D235301 | H78: E530-302038409-D235301 | I78: E530-30203840962-D235301 | J78: Surface Facilities Cost | K78: Road & Pad | L78: Construction | M78: Construction | N78: Pad 18 | O78: Pad | P78: =_xlfn.TEXTBEFORE(_xlfn.TEXTAFTER(Table26[[#This Row],[WBS CODE]], "-"), "-") -> 30203840962
A79: 78 | B79: 04 | C79: Road & Pad - Proc Pad 18 | D79: E530-302038408-D235301 | E79: E530-30-D235301 | F79: E530-30203-D235301 | G79: E530-3020384-D235301 | H79: E530-302038408-D235301 | J79: Surface Facilities Cost | K79: Road & Pad | L79: Procurement | N79: Pad 18 | O79: Pad | P79: =_xlfn.TEXTBEFORE(_xlfn.TEXTAFTER(Table26[[#This Row],[WBS CODE]], "-"), "-") -> 302038408
A80: 79 | B80: 05 | C80: Road & Pad Material Non LL Pad 18 | D80: E530-30203840821-D235301 | E80: E530-30-D235301 | F80: E530-30203-D235301 | G80: E530-3020384-D235301 | H80: E530-302038408-D235301 | I80: E530-30203840821-D235301 | J80: Surface Facilities Cost | K80: Road & Pad | L80: Procurement | M80: Material - Non LL | N80: Pad 18 | O80: Pad | P80: =_xlfn.TEXTBEFORE(_xlfn.TEXTAFTER(Table26[[#This Row],[WBS CODE]], "-"), "-") -> 30203840821
A81: 80 | B81: 05 | C81: Road & Pad Material LL Pad 18 | D81: E530-30203840860-D235301 | E81: E530-30-D235301 | F81: E530-30203-D235301 | G81: E530-3020384-D235301 | H81: E530-302038408-D235301 | I81: E530-30203840860-D235301 | J81: Surface Facilities Cost | K81: Road & Pad | L81: Procurement | M81: Material - LL | N81: Pad 18 | O81: Pad | P81: =_xlfn.TEXTBEFORE(_xlfn.TEXTAFTER(Table26[[#This Row],[WBS CODE]], "-"), "-") -> 30203840860
A82: 81 | B82: 04 | C82: Road & Pad - Eng Pad 18 | D82: E530-302038407-D235301 | E82: E530-30-D235301 | F82: E530-30203-D235301 | G82: E530-3020384-D235301 | H82: E530-302038407-D235301 | J82: Surface Facilities Cost | K82: Road & Pad | L82: Engineering | N82: Pad 18 | O82: Pad | P82: =_xlfn.TEXTBEFORE(_xlfn.TEXTAFTER(Table26[[#This Row],[WBS CODE]], "-"), "-") -> 302038407
A83: 82 | B83: 05 | C83: Road & Pad Eng Pad 18 | D83: E530-30203840759-D235301 | E83: E530-30-D235301 | F83: E530-30203-D235301 | G83: E530-3020384-D235301 | H83: E530-302038407-D235301 | I83: E530-30203840759-D235301 | J83: Surface Facilities Cost | K83: Road & Pad | L83: Engineering | M83: Engineering | N83: Pad 18 | O83: Pad | P83: =_xlfn.TEXTBEFORE(_xlfn.TEXTAFTER(Table26[[#This Row],[WBS CODE]], "-"), "-") -> 30203840759
A84: 83 | B84: 03 | C84: Road and Pad - Pad 15 | D84: E530-3020383-D235301 | E84: E530-30-D235301 | F84: E530-30203-D235301 | G84: E530-3020383-D235301 | J84: Surface Facilities Cost | K84: Road & Pad | N84: Pad 15 | O84: Pad | P84: =_xlfn.TEXTBEFORE(_xlfn.TEXTAFTER(Table26[[#This Row],[WBS CODE]], "-"), "-") -> 3020383
A85: 84 | B85: 04 | C85: Road & Pad - Const Pad 15 | D85: E530-302038309-D235301 | E85: E530-30-D235301 | F85: E530-30203-D235301 | G85: E530-3020383-D235301 | H85: E530-302038309-D235301 | J85: Surface Facilities Cost | K85: Road & Pad | L85: Construction | N85: Pad 15 | O85: Pad | P85: =_xlfn.TEXTBEFORE(_xlfn.TEXTAFTER(Table26[[#This Row],[WBS CODE]], "-"), "-") -> 302038309
A86: 85 | B86: 05 | C86: Road & Pad Const Pad 15 | D86: E530-30203830962-D235301 | E86: E530-30-D235301 | F86: E530-30203-D235301 | G86: E530-3020383-D235301 | H86: E530-302038309-D235301 | I86: E530-30203830962-D235301 | J86: Surface Facilities Cost | K86: Road & Pad | L86: Construction | M86: Construction | N86: Pad 15 | O86: Pad | P86: =_xlfn.TEXTBEFORE(_xlfn.TEXTAFTER(Table26[[#This Row],[WBS CODE]], "-"), "-") -> 30203830962
A87: 86 | B87: 04 | C87: Road & Pad - Proc Pad 15 | D87: E530-302038308-D235301 | E87: E530-30-D235301 | F87: E530-30203-D235301 | G87: E530-3020383-D235301 | H87: E530-302038308-D235301 | J87: Surface Facilities Cost | K87: Road & Pad | L87: Procurement | N87: Pad 15 | O87: Pad | P87: =_xlfn.TEXTBEFORE(_xlfn.TEXTAFTER(Table26[[#This Row],[WBS CODE]], "-"), "-") -> 302038308
A88: 87 | B88: 05 | C88: Road & Pad Material Non LL Pad 15 | D88: E530-30203830821-D235301 | E88: E530-30-D235301 | F88: E530-30203-D235301 | G88: E530-3020383-D235301 | H88: E530-302038308-D235301 | I88: E530-30203830821-D235301 | J88: Surface Facilities Cost | K88: Road & Pad | L88: Procurement | M88: Material - Non LL | N88: Pad 15 | O88: Pad | P88: =_xlfn.TEXTBEFORE(_xlfn.TEXTAFTER(Table26[[#This Row],[WBS CODE]], "-"), "-") -> 30203830821
A89: 88 | B89: 05 | C89: Road & Pad Material LL Pad 15 | D89: E530-30203830860-D235301 | E89: E530-30-D235301 | F89: E530-30203-D235301 | G89: E530-3020383-D235301 | H89: E530-302038308-D235301 | I89: E530-30203830860-D235301 | J89: Surface Facilities Cost | K89: Road & Pad | L89: Procurement | M89: Material - LL | N89: Pad 15 | O89: Pad | P89: =_xlfn.TEXTBEFORE(_xlfn.TEXTAFTER(Table26[[#This Row],[WBS CODE]], "-"), "-") -> 30203830860
A90: 89 | B90: 04 | C90: Road & Pad - Eng Pad 15 | D90: E530-302038307-D235301 | E90: E530-30-D235301 | F90: E530-30203-D235301 | G90: E530-3020383-D235301 | H90: E530-302038307-D235301 | J90: Surface Facilities Cost | K90: Road & Pad | L90: Engineering | N90: Pad 15 | O90: Pad | P90: =_xlfn.TEXTBEFORE(_xlfn.TEXTAFTER(Table26[[#This Row],[WBS CODE]], "-"), "-") -> 302038307
A91: 90 | B91: 05 | C91: Road & Pad Eng Pad 15 | D91: E530-30203830759-D235301 | E91: E530-30-D235301 | F91: E530-30203-D235301 | G91: E530-3020383-D235301 | H91: E530-302038307-D235301 | I91: E530-30203830759-D235301 | J91: Surface Facilities Cost | K91: Road & Pad | L91: Engineering | M91: Engineering | N91: Pad 15 | O91: Pad | P91: =_xlfn.TEXTBEFORE(_xlfn.TEXTAFTER(Table26[[#This Row],[WBS CODE]], "-"), "-") -> 30203830759
A92: 91 | B92: 03 | C92: Conductor casing installation and materi | D92: E530-3020374-D235301 | E92: E530-30-D235301 | F92: E530-30203-D235301 | G92: E530-3020374-D235301 | J92: Surface Facilities Cost | K92: Conductor Casing Installation & Material | P92: =_xlfn.TEXTBEFORE(_xlfn.TEXTAFTER(Table26[[#This Row],[WBS CODE]], "-"), "-") -> 3020374
A93: 92 | B93: 04 | C93: Conductor Casing Inst & Mat DRJ-Steam 6 | D93: E530-302037406-D235301 | E93: E530-30-D235301 | F93: E530-30203-D235301 | G93: E530-3020374-D235301 | H93: E530-302037406-D235301 | J93: Surface Facilities Cost | K93: Conductor Casing Installation & Material | L93: Conductor Casing Installation & Material | N93: DRJ-Steam 6 | O93: Well | P93: =_xlfn.TEXTBEFORE(_xlfn.TEXTAFTER(Table26[[#This Row],[WBS CODE]], "-"), "-") -> 302037406
A94: 93 | B94: 05 | C94: Cdtr Csg Material DRJ-Steam 6 (Pad 20) | D94: E530-30203740660-D235301 | E94: E530-30-D235301 | F94: E530-30203-D235301 | G94: E530-3020374-D235301 | H94: E530-302037406-D235301 | I94: E530-30203740660-D235301 | J94: Surface Facilities Cost | K94: Conductor Casing Installation & Material | L94: Conductor Casing Installation & Material | M94: Material | N94: DRJ-Steam 6 | O94: Well | P94: =_xlfn.TEXTBEFORE(_xlfn.TEXTAFTER(Table26[[#This Row],[WBS CODE]], "-"), "-") -> 30203740660
A95: 94 | B95: 05 | C95: Cdtr Csg Service DRJ-Steam 6 (Pad 20) | D95: E530-30203740603-D235301 | E95: E530-30-D235301 | F95: E530-30203-D235301 | G95: E530-3020374-D235301 | H95: E530-302037406-D235301 | I95: E530-30203740603-D235301 | J95: Surface Facilities Cost | K95: Conductor Casing Installation & Material | L95: Conductor Casing Installation & Material | M95: Service | N95: DRJ-Steam 6 | O95: Well | P95: =_xlfn.TEXTBEFORE(_xlfn.TEXTAFTER(Table26[[#This Row],[WBS CODE]], "-"), "-") -> 30203740603
A96: 95 | B96: 04 | C96: Conductor Casing Inst & Mat DRJ-Steam 5 | D96: E530-302037405-D235301 | E96: E530-30-D235301 | F96: E530-30203-D235301 | G96: E530-3020374-D235301 | H96: E530-302037405-D235301 | J96: Surface Facilities Cost | K96: Conductor Casing Installation & Material | L96: Conductor Casing Installation & Material | N96: DRJ-Steam 5 | O96: Well | P96: =_xlfn.TEXTBEFORE(_xlfn.TEXTAFTER(Table26[[#This Row],[WBS CODE]], "-"), "-") -> 302037405
A97: 96 | B97: 05 | C97: Cdtr Csg Material DRJ-Steam 5 (Pad 20) | D97: E530-30203740560-D235301 | E97: E530-30-D235301 | F97: E530-30203-D235301 | G97: E530-3020374-D235301 | H97: E530-302037405-D235301 | I97: E530-30203740560-D235301 | J97: Surface Facilities Cost | K97: Conductor Casing Installation & Material | L97: Conductor Casing Installation & Material | M97: Material | N97: DRJ-Steam 5 | O97: Well | P97: =_xlfn.TEXTBEFORE(_xlfn.TEXTAFTER(Table26[[#This Row],[WBS CODE]], "-"), "-") -> 30203740560
A98: 97 | B98: 05 | C98: Cdtr Csg Service DRJ-Steam 5 (Pad 20) | D98: E530-30203740503-D235301 | E98: E530-30-D235301 | F98: E530-30203-D235301 | G98: E530-3020374-D235301 | H98: E530-302037405-D235301 | I98: E530-30203740503-D235301 | J98: Surface Facilities Cost | K98: Conductor Casing Installation & Material | L98: Conductor Casing Installation & Material | M98: Service | N98: DRJ-Steam 5 | O98: Well | P98: =_xlfn.TEXTBEFORE(_xlfn.TEXTAFTER(Table26[[#This Row],[WBS CODE]], "-"), "-") -> 30203740503
A99: 98 | B99: 04 | C99: Conductor Casing Inst & Mat DRJ-Steam 4 | D99: E530-302037404-D235301 | E99: E530-30-D235301 | F99: E530-30203-D235301 | G99: E530-3020374-D235301 | H99: E530-302037404-D235301 | J99: Surface Facilities Cost | K99: Conductor Casing Installation & Material | L99: Conductor Casing Installation & Material | N99: DRJ-Steam 4 | O99: Well | P99: =_xlfn.TEXTBEFORE(_xlfn.TEXTAFTER(Table26[[#This Row],[WBS CODE]], "-"), "-") -> 302037404
A100: 99 | B100: 05 | C100: Cdtr Csg Material DRJ-Steam 4 (Pad 20) | D100: E530-30203740460-D235301 | E100: E530-30-D235301 | F100: E530-30203-D235301 | G100: E530-3020374-D235301 | H100: E530-302037404-D235301 | I100: E530-30203740460-D235301 | J100: Surface Facilities Cost | K100: Conductor Casing Installation & Material | L100: Conductor Casing Installation & Material | M100: Material | N100: DRJ-Steam 4 | O100: Well | P100: =_xlfn.TEXTBEFORE(_xlfn.TEXTAFTER(Table26[[#This Row],[WBS CODE]], "-"), "-") -> 30203740460
...

Sheet WBS.structure
A1: No | B1: Level | C1: WBS_Desc | D1: WBS_ID | E1: AFE/Projec | F1: Budget | G1: Budget2 | H1: Release | I1: Release3 | J1: ProCstPlan | K1: ProCstPlan4 | L1: Tot.cst.cm | M1: Tot.cst.cm5 | N1: Act.costs | O1: Act.costs6 | P1: CAPEX | Q1: OPEX | R1: Resp.persn | S1: Life Cycle | T1: Status | U1: Code_L1 | V1: Code_L2 | W1: Code_L3 | X1: Code_L4 | Y1: LVL 5 | Z1: Tag_L2 | AA1: Tag_L3 | AB1: Tag_L4 | AC1: Tag_L5 | AD1: Tag_Well_Pad_Name | AE1: Tag_Well_or_Pad
A2: 1 | B2: 00 | C2: Salak Projects 2024 | D2: 1E54024 | F2: 76657407 | G2: USD | H2: 68353810 | I2: USD | J2: 0 | K2: USD | L2: 9271400.2 | M2: USD | N2: 38522326 | O2: USD | R2: STAR ENERGY | T2: PREL | U2: =IF(IFERROR(INDEX(WBS_Dictionary!E$2:E$1212, MATCH(Table2[[#This Row],[WBS_ID]], Table26[WBS CODE],0)), "") = "", "null", IFERROR(INDEX(WBS_Dictionary!E$2:E$1212, MATCH(Table2[[#This Row],[WBS_ID]], Table26[WBS CODE],0)), "")) -> null | V2: =IF(IFERROR(INDEX(WBS_Dictionary!F$2:F$1212, MATCH(Table2[[#This Row],[WBS_ID]], Table26[WBS CODE],0)), "") = "", "null", IFERROR(INDEX(WBS_Dictionary!F$2:F$1212, MATCH(Table2[[#This Row],[WBS_ID]], Table26[WBS CODE],0)), "")) -> null | W2: =IF(IFERROR(INDEX(WBS_Dictionary!G$2:G$1212, MATCH(Table2[[#This Row],[WBS_ID]], Table26[WBS CODE],0)), "") = "", "null", IFERROR(INDEX(WBS_Dictionary!G$2:G$1212, MATCH(Table2[[#This Row],[WBS_ID]], Table26[WBS CODE],0)), "")) -> null | X2: =IF(IFERROR(INDEX(WBS_Dictionary!H$2:H$1212, MATCH(Table2[[#This Row],[WBS_ID]], Table26[WBS CODE],0)), "") = "", "null", IFERROR(INDEX(WBS_Dictionary!H$2:H$1212, MATCH(Table2[[#This Row],[WBS_ID]], Table26[WBS CODE],0)), "")) -> null | Y2: =IF(IFERROR(INDEX(WBS_Dictionary!I$2:I$1212, MATCH(Table2[[#This Row],[WBS_ID]], Table26[WBS CODE],0)), "") = "", "null", IFERROR(INDEX(WBS_Dictionary!I$2:I$1212, MATCH(Table2[[#This Row],[WBS_ID]], Table26[WBS CODE],0)), "")) -> null | Z2: =IF(IFERROR(INDEX(WBS_Dictionary!J$2:J$1212, MATCH(Table2[[#This Row],[WBS_ID]], Table26[WBS CODE],0)), "") = "", "null", IFERROR(INDEX(WBS_Dictionary!J$2:J$1212, MATCH(Table2[[#This Row],[WBS_ID]], Table26[WBS CODE],0)), "")) -> null | AA2: =IF(IFERROR(INDEX(WBS_Dictionary!K$2:K$1212, MATCH(Table2[[#This Row],[WBS_ID]], Table26[WBS CODE],0)), "") = "", "null", IFERROR(INDEX(WBS_Dictionary!K$2:K$1212, MATCH(Table2[[#This Row],[WBS_ID]], Table26[WBS CODE],0)), "")) -> null | AB2: =IF(IFERROR(INDEX(WBS_Dictionary!L$2:L$1212, MATCH(Table2[[#This Row],[WBS_ID]], Table26[WBS CODE],0)), "") = "", "null", IFERROR(INDEX(WBS_Dictionary!L$2:L$1212, MATCH(Table2[[#This Row],[WBS_ID]], Table26[WBS CODE],0)), "")) -> null | ... AE2: =IF(IFERROR(INDEX(WBS_Dictionary!O$2:O$1212, MATCH(Table2[[#This Row],[WBS_ID]], Table26[WBS CODE],0)), "") = "", "null", IFERROR(INDEX(WBS_Dictionary!O$2:O$1212, MATCH(Table2[[#This Row],[WBS_ID]], Table26[WBS CODE],0)), "")) -> null
A3: 2 | B3: 01 | C3: SLK Drilling MUW 2025 | D3: E540-30-D245401 | E3: D245401 | F3: 76657407 | G3: USD | H3: 68353810 | I3: USD | J3: 0 | K3: USD | L3: 9271400.2 | M3: USD | N3: 38522326 | O3: USD | Q3: X | R3: STAR ENERGY | S3: Production | T3: REL BUDG AVAC // BUDG | U3: =IF(IFERROR(INDEX(WBS_Dictionary!E$2:E$1212, MATCH(Table2[[#This Row],[WBS_ID]], Table26[WBS CODE],0)), "") = "", "null", IFERROR(INDEX(WBS_Dictionary!E$2:E$1212, MATCH(Table2[[#This Row],[WBS_ID]], Table26[WBS CODE],0)), "")) -> E540-30-D245401 | V3: =IF(IFERROR(INDEX(WBS_Dictionary!F$2:F$1212, MATCH(Table2[[#This Row],[WBS_ID]], Table26[WBS CODE],0)), "") = "", "null", IFERROR(INDEX(WBS_Dictionary!F$2:F$1212, MATCH(Table2[[#This Row],[WBS_ID]], Table26[WBS CODE],0)), "")) -> null | W3: =IF(IFERROR(INDEX(WBS_Dictionary!G$2:G$1212, MATCH(Table2[[#This Row],[WBS_ID]], Table26[WBS CODE],0)), "") = "", "null", IFERROR(INDEX(WBS_Dictionary!G$2:G$1212, MATCH(Table2[[#This Row],[WBS_ID]], Table26[WBS CODE],0)), "")) -> null | X3: =IF(IFERROR(INDEX(WBS_Dictionary!H$2:H$1212, MATCH(Table2[[#This Row],[WBS_ID]], Table26[WBS CODE],0)), "") = "", "null", IFERROR(INDEX(WBS_Dictionary!H$2:H$1212, MATCH(Table2[[#This Row],[WBS_ID]], Table26[WBS CODE],0)), "")) -> null | Y3: =IF(IFERROR(INDEX(WBS_Dictionary!I$2:I$1212, MATCH(Table2[[#This Row],[WBS_ID]], Table26[WBS CODE],0)), "") = "", "null", IFERROR(INDEX(WBS_Dictionary!I$2:I$1212, MATCH(Table2[[#This Row],[WBS_ID]], Table26[WBS CODE],0)), "")) -> null | Z3: =IF(IFERROR(INDEX(WBS_Dictionary!J$2:J$1212, MATCH(Table2[[#This Row],[WBS_ID]], Table26[WBS CODE],0)), "") = "", "null", IFERROR(INDEX(WBS_Dictionary!J$2:J$1212, MATCH(Table2[[#This Row],[WBS_ID]], Table26[WBS CODE],0)), "")) -> null | AA3: =IF(IFERROR(INDEX(WBS_Dictionary!K$2:K$1212, MATCH(Table2[[#This Row],[WBS_ID]], Table26[WBS CODE],0)), "") = "", "null", IFERROR(INDEX(WBS_Dictionary!K$2:K$1212, MATCH(Table2[[#This Row],[WBS_ID]], Table26[WBS CODE],0)), "")) -> null | AB3: =IF(IFERROR(INDEX(WBS_Dictionary!L$2:L$1212, MATCH(Table2[[#This Row],[WBS_ID]], Table26[WBS CODE],0)), "") = "", "null", IFERROR(INDEX(WBS_Dictionary!L$2:L$1212, MATCH(Table2[[#This Row],[WBS_ID]], Table26[WBS CODE],0)), "")) -> null | ... AE3: =IF(IFERROR(INDEX(WBS_Dictionary!O$2:O$1212, MATCH(Table2[[#This Row],[WBS_ID]], Table26[WBS CODE],0)), "") = "", "null", IFERROR(INDEX(WBS_Dictionary!O$2:O$1212, MATCH(Table2[[#This Row],[WBS_ID]], Table26[WBS CODE],0)), "")) -> null
A4: 3 | B4: 02 | C4: Contingency | D4: E540-30299-D245401 | E4: D245401 | F4: 4950221 | G4: USD | H4: 0 | I4: USD | J4: 0 | K4: USD | L4: 0 | M4: USD | N4: 0 | O4: USD | P4: X | R4: STAR ENERGY | S4: Production | T4: REL BUDG AVAC // BUDG | U4: =IF(IFERROR(INDEX(WBS_Dictionary!E$2:E$1212, MATCH(Table2[[#This Row],[WBS_ID]], Table26[WBS CODE],0)), "") = "", "null", IFERROR(INDEX(WBS_Dictionary!E$2:E$1212, MATCH(Table2[[#This Row],[WBS_ID]], Table26[WBS CODE],0)), "")) -> E540-30-D245401 | V4: =IF(IFERROR(INDEX(WBS_Dictionary!F$2:F$1212, MATCH(Table2[[#This Row],[WBS_ID]], Table26[WBS CODE],0)), "") = "", "null", IFERROR(INDEX(WBS_Dictionary!F$2:F$1212, MATCH(Table2[[#This Row],[WBS_ID]], Table26[WBS CODE],0)), "")) -> E540-30299-D245401 | W4: =IF(IFERROR(INDEX(WBS_Dictionary!G$2:G$1212, MATCH(Table2[[#This Row],[WBS_ID]], Table26[WBS CODE],0)), "") = "", "null", IFERROR(INDEX(WBS_Dictionary!G$2:G$1212, MATCH(Table2[[#This Row],[WBS_ID]], Table26[WBS CODE],0)), "")) -> null | X4: =IF(IFERROR(INDEX(WBS_Dictionary!H$2:H$1212, MATCH(Table2[[#This Row],[WBS_ID]], Table26[WBS CODE],0)), "") = "", "null", IFERROR(INDEX(WBS_Dictionary!H$2:H$1212, MATCH(Table2[[#This Row],[WBS_ID]], Table26[WBS CODE],0)), "")) -> null | Y4: =IF(IFERROR(INDEX(WBS_Dictionary!I$2:I$1212, MATCH(Table2[[#This Row],[WBS_ID]], Table26[WBS CODE],0)), "") = "", "null", IFERROR(INDEX(WBS_Dictionary!I$2:I$1212, MATCH(Table2[[#This Row],[WBS_ID]], Table26[WBS CODE],0)), "")) -> null | Z4: =IF(IFERROR(INDEX(WBS_Dictionary!J$2:J$1212, MATCH(Table2[[#This Row],[WBS_ID]], Table26[WBS CODE],0)), "") = "", "null", IFERROR(INDEX(WBS_Dictionary!J$2:J$1212, MATCH(Table2[[#This Row],[WBS_ID]], Table26[WBS CODE],0)), "")) -> Contingency | AA4: =IF(IFERROR(INDEX(WBS_Dictionary!K$2:K$1212, MATCH(Table2[[#This Row],[WBS_ID]], Table26[WBS CODE],0)), "") = "", "null", IFERROR(INDEX(WBS_Dictionary!K$2:K$1212, MATCH(Table2[[#This Row],[WBS_ID]], Table26[WBS CODE],0)), "")) -> null | AB4: =IF(IFERROR(INDEX(WBS_Dictionary!L$2:L$1212, MATCH(Table2[[#This Row],[WBS_ID]], Table26[WBS CODE],0)), "") = "", "null", IFERROR(INDEX(WBS_Dictionary!L$2:L$1212, MATCH(Table2[[#This Row],[WBS_ID]], Table26[WBS CODE],0)), "")) -> null | ... AE4: =IF(IFERROR(INDEX(WBS_Dictionary!O$2:O$1212, MATCH(Table2[[#This Row],[WBS_ID]], Table26[WBS CODE],0)), "") = "", "null", IFERROR(INDEX(WBS_Dictionary!O$2:O$1212, MATCH(Table2[[#This Row],[WBS_ID]], Table26[WBS CODE],0)), "")) -> null
A5: 4 | B5: 03 | C5: Contingency | D5: E540-3029901-D245401 | E5: D245401 | F5: 4950221 | G5: USD | H5: 0 | I5: USD | J5: 0 | K5: USD | L5: 0 | M5: USD | N5: 0 | O5: USD | P5: X | R5: STAR ENERGY | S5: Production | T5: REL BUDG AVAC // BUDG | U5: =IF(IFERROR(INDEX(WBS_Dictionary!E$2:E$1212, MATCH(Table2[[#This Row],[WBS_ID]], Table26[WBS CODE],0)), "") = "", "null", IFERROR(INDEX(WBS_Dictionary!E$2:E$1212, MATCH(Table2[[#This Row],[WBS_ID]], Table26[WBS CODE],0)), "")) -> E540-30-D245401 | V5: =IF(IFERROR(INDEX(WBS_Dictionary!F$2:F$1212, MATCH(Table2[[#This Row],[WBS_ID]], Table26[WBS CODE],0)), "") = "", "null", IFERROR(INDEX(WBS_Dictionary!F$2:F$1212, MATCH(Table2[[#This Row],[WBS_ID]], Table26[WBS CODE],0)), "")) -> E540-30299-D245401 | W5: =IF(IFERROR(INDEX(WBS_Dictionary!G$2:G$1212, MATCH(Table2[[#This Row],[WBS_ID]], Table26[WBS CODE],0)), "") = "", "null", IFERROR(INDEX(WBS_Dictionary!G$2:G$1212, MATCH(Table2[[#This Row],[WBS_ID]], Table26[WBS CODE],0)), "")) -> E540-3029901-D245401 | X5: =IF(IFERROR(INDEX(WBS_Dictionary!H$2:H$1212, MATCH(Table2[[#This Row],[WBS_ID]], Table26[WBS CODE],0)), "") = "", "null", IFERROR(INDEX(WBS_Dictionary!H$2:H$1212, MATCH(Table2[[#This Row],[WBS_ID]], Table26[WBS CODE],0)), "")) -> null | Y5: =IF(IFERROR(INDEX(WBS_Dictionary!I$2:I$1212, MATCH(Table2[[#This Row],[WBS_ID]], Table26[WBS CODE],0)), "") = "", "null", IFERROR(INDEX(WBS_Dictionary!I$2:I$1212, MATCH(Table2[[#This Row],[WBS_ID]], Table26[WBS CODE],0)), "")) -> null | Z5: =IF(IFERROR(INDEX(WBS_Dictionary!J$2:J$1212, MATCH(Table2[[#This Row],[WBS_ID]], Table26[WBS CODE],0)), "") = "", "null", IFERROR(INDEX(WBS_Dictionary!J$2:J$1212, MATCH(Table2[[#This Row],[WBS_ID]], Table26[WBS CODE],0)), "")) -> Contingency | AA5: =IF(IFERROR(INDEX(WBS_Dictionary!K$2:K$1212, MATCH(Table2[[#This Row],[WBS_ID]], Table26[WBS CODE],0)), "") = "", "null", IFERROR(INDEX(WBS_Dictionary!K$2:K$1212, MATCH(Table2[[#This Row],[WBS_ID]], Table26[WBS CODE],0)), "")) -> Contingency | AB5: =IF(IFERROR(INDEX(WBS_Dictionary!L$2:L$1212, MATCH(Table2[[#This Row],[WBS_ID]], Table26[WBS CODE],0)), "") = "", "null", IFERROR(INDEX(WBS_Dictionary!L$2:L$1212, MATCH(Table2[[#This Row],[WBS_ID]], Table26[WBS CODE],0)), "")) -> null | ... AE5: =IF(IFERROR(INDEX(WBS_Dictionary!O$2:O$1212, MATCH(Table2[[#This Row],[WBS_ID]], Table26[WBS CODE],0)), "") = "", "null", IFERROR(INDEX(WBS_Dictionary!O$2:O$1212, MATCH(Table2[[#This Row],[WBS_ID]], Table26[WBS CODE],0)), "")) -> null
A6: 5 | B6: 04 | C6: Contingency | D6: E540-302990115-D245401 | E6: D245401 | F6: 4950221 | G6: USD | H6: 0 | I6: USD | J6: 0 | K6: USD | L6: 0 | M6: USD | N6: 0 | O6: USD | P6: X | R6: STAR ENERGY | S6: Production | T6: REL BUDG AVAC // BUDG | U6: =IF(IFERROR(INDEX(WBS_Dictionary!E$2:E$1212, MATCH(Table2[[#This Row],[WBS_ID]], Table26[WBS CODE],0)), "") = "", "null", IFERROR(INDEX(WBS_Dictionary!E$2:E$1212, MATCH(Table2[[#This Row],[WBS_ID]], Table26[WBS CODE],0)), "")) -> E540-30-D245401 | V6: =IF(IFERROR(INDEX(WBS_Dictionary!F$2:F$1212, MATCH(Table2[[#This Row],[WBS_ID]], Table26[WBS CODE],0)), "") = "", "null", IFERROR(INDEX(WBS_Dictionary!F$2:F$1212, MATCH(Table2[[#This Row],[WBS_ID]], Table26[WBS CODE],0)), "")) -> E540-30299-D245401 | W6: =IF(IFERROR(INDEX(WBS_Dictionary!G$2:G$1212, MATCH(Table2[[#This Row],[WBS_ID]], Table26[WBS CODE],0)), "") = "", "null", IFERROR(INDEX(WBS_Dictionary!G$2:G$1212, MATCH(Table2[[#This Row],[WBS_ID]], Table26[WBS CODE],0)), "")) -> E540-3029901-D245401 | X6: =IF(IFERROR(INDEX(WBS_Dictionary!H$2:H$1212, MATCH(Table2[[#This Row],[WBS_ID]], Table26[WBS CODE],0)), "") = "", "null", IFERROR(INDEX(WBS_Dictionary!H$2:H$1212, MATCH(Table2[[#This Row],[WBS_ID]], Table26[WBS CODE],0)), "")) -> E540-302990115-D245401 | Y6: =IF(IFERROR(INDEX(WBS_Dictionary!I$2:I$1212, MATCH(Table2[[#This Row],[WBS_ID]], Table26[WBS CODE],0)), "") = "", "null", IFERROR(INDEX(WBS_Dictionary!I$2:I$1212, MATCH(Table2[[#This Row],[WBS_ID]], Table26[WBS CODE],0)), "")) -> null | Z6: =IF(IFERROR(INDEX(WBS_Dictionary!J$2:J$1212, MATCH(Table2[[#This Row],[WBS_ID]], Table26[WBS CODE],0)), "") = "", "null", IFERROR(INDEX(WBS_Dictionary!J$2:J$1212, MATCH(Table2[[#This Row],[WBS_ID]], Table26[WBS CODE],0)), "")) -> Contingency | AA6: =IF(IFERROR(INDEX(WBS_Dictionary!K$2:K$1212, MATCH(Table2[[#This Row],[WBS_ID]], Table26[WBS CODE],0)), "") = "", "null", IFERROR(INDEX(WBS_Dictionary!K$2:K$1212, MATCH(Table2[[#This Row],[WBS_ID]], Table26[WBS CODE],0)), "")) -> Contingency | AB6: =IF(IFERROR(INDEX(WBS_Dictionary!L$2:L$1212, MATCH(Table2[[#This Row],[WBS_ID]], Table26[WBS CODE],0)), "") = "", "null", IFERROR(INDEX(WBS_Dictionary!L$2:L$1212, MATCH(Table2[[#This Row],[WBS_ID]], Table26[WBS CODE],0)), "")) -> Contingency | ... AE6: =IF(IFERROR(INDEX(WBS_Dictionary!O$2:O$1212, MATCH(Table2[[#This Row],[WBS_ID]], Table26[WBS CODE],0)), "") = "", "null", IFERROR(INDEX(WBS_Dictionary!O$2:O$1212, MATCH(Table2[[#This Row],[WBS_ID]], Table26[WBS CODE],0)), "")) -> null
A7: 6 | B7: 05 | C7: Contingency | D7: E540-30299011521-D245401 | E7: D245401 | F7: 0 | G7: USD | H7: 0 | I7: USD | J7: 0 | K7: USD | L7: 0 | M7: USD | N7: 0 | O7: USD | P7: X | R7: STAR ENERGY | S7: Production | T7: REL AVAC // BUDG | U7: =IF(IFERROR(INDEX(WBS_Dictionary!E$2:E$1212, MATCH(Table2[[#This Row],[WBS_ID]], Table26[WBS CODE],0)), "") = "", "null", IFERROR(INDEX(WBS_Dictionary!E$2:E$1212, MATCH(Table2[[#This Row],[WBS_ID]], Table26[WBS CODE],0)), "")) -> E540-30-D245401 | V7: =IF(IFERROR(INDEX(WBS_Dictionary!F$2:F$1212, MATCH(Table2[[#This Row],[WBS_ID]], Table26[WBS CODE],0)), "") = "", "null", IFERROR(INDEX(WBS_Dictionary!F$2:F$1212, MATCH(Table2[[#This Row],[WBS_ID]], Table26[WBS CODE],0)), "")) -> E540-30299-D245401 | W7: =IF(IFERROR(INDEX(WBS_Dictionary!G$2:G$1212, MATCH(Table2[[#This Row],[WBS_ID]], Table26[WBS CODE],0)), "") = "", "null", IFERROR(INDEX(WBS_Dictionary!G$2:G$1212, MATCH(Table2[[#This Row],[WBS_ID]], Table26[WBS CODE],0)), "")) -> E540-3029901-D245401 | X7: =IF(IFERROR(INDEX(WBS_Dictionary!H$2:H$1212, MATCH(Table2[[#This Row],[WBS_ID]], Table26[WBS CODE],0)), "") = "", "null", IFERROR(INDEX(WBS_Dictionary!H$2:H$1212, MATCH(Table2[[#This Row],[WBS_ID]], Table26[WBS CODE],0)), "")) -> E540-302990115-D245401 | Y7: =IF(IFERROR(INDEX(WBS_Dictionary!I$2:I$1212, MATCH(Table2[[#This Row],[WBS_ID]], Table26[WBS CODE],0)), "") = "", "null", IFERROR(INDEX(WBS_Dictionary!I$2:I$1212, MATCH(Table2[[#This Row],[WBS_ID]], Table26[WBS CODE],0)), "")) -> E540-30299011521-D245401 | Z7: =IF(IFERROR(INDEX(WBS_Dictionary!J$2:J$1212, MATCH(Table2[[#This Row],[WBS_ID]], Table26[WBS CODE],0)), "") = "", "null", IFERROR(INDEX(WBS_Dictionary!J$2:J$1212, MATCH(Table2[[#This Row],[WBS_ID]], Table26[WBS CODE],0)), "")) -> Contingency | AA7: =IF(IFERROR(INDEX(WBS_Dictionary!K$2:K$1212, MATCH(Table2[[#This Row],[WBS_ID]], Table26[WBS CODE],0)), "") = "", "null", IFERROR(INDEX(WBS_Dictionary!K$2:K$1212, MATCH(Table2[[#This Row],[WBS_ID]], Table26[WBS CODE],0)), "")) -> Contingency | AB7: =IF(IFERROR(INDEX(WBS_Dictionary!L$2:L$1212, MATCH(Table2[[#This Row],[WBS_ID]], Table26[WBS CODE],0)), "") = "", "null", IFERROR(INDEX(WBS_Dictionary!L$2:L$1212, MATCH(Table2[[#This Row],[WBS_ID]], Table26[WBS CODE],0)), "")) -> Contingency | ... AE7: =IF(IFERROR(INDEX(WBS_Dictionary!O$2:O$1212, MATCH(Table2[[#This Row],[WBS_ID]], Table26[WBS CODE],0)), "") = "", "null", IFERROR(INDEX(WBS_Dictionary!O$2:O$1212, MATCH(Table2[[#This Row],[WBS_ID]], Table26[WBS CODE],0)), "")) -> null
A8: 7 | B8: 02 | C8: Surface Facilities Cost | D8: E540-30203-D245401 | E8: D245401 | F8: 12318779 | G8: USD | H8: 11266879 | I8: USD | J8: 0 | K8: USD | L8: 1677993.4 | M8: USD | N8: 4621324.5 | O8: USD | P8: X | R8: STAR ENERGY | S8: Production | T8: REL BUDG AVAC // BUDG | U8: =IF(IFERROR(INDEX(WBS_Dictionary!E$2:E$1212, MATCH(Table2[[#This Row],[WBS_ID]], Table26[WBS CODE],0)), "") = "", "null", IFERROR(INDEX(WBS_Dictionary!E$2:E$1212, MATCH(Table2[[#This Row],[WBS_ID]], Table26[WBS CODE],0)), "")) -> E540-30-D245401 | V8: =IF(IFERROR(INDEX(WBS_Dictionary!F$2:F$1212, MATCH(Table2[[#This Row],[WBS_ID]], Table26[WBS CODE],0)), "") = "", "null", IFERROR(INDEX(WBS_Dictionary!F$2:F$1212, MATCH(Table2[[#This Row],[WBS_ID]], Table26[WBS CODE],0)), "")) -> E540-30203-D245401 | W8: =IF(IFERROR(INDEX(WBS_Dictionary!G$2:G$1212, MATCH(Table2[[#This Row],[WBS_ID]], Table26[WBS CODE],0)), "") = "", "null", IFERROR(INDEX(WBS_Dictionary!G$2:G$1212, MATCH(Table2[[#This Row],[WBS_ID]], Table26[WBS CODE],0)), "")) -> null | X8: =IF(IFERROR(INDEX(WBS_Dictionary!H$2:H$1212, MATCH(Table2[[#This Row],[WBS_ID]], Table26[WBS CODE],0)), "") = "", "null", IFERROR(INDEX(WBS_Dictionary!H$2:H$1212, MATCH(Table2[[#This Row],[WBS_ID]], Table26[WBS CODE],0)), "")) -> null | Y8: =IF(IFERROR(INDEX(WBS_Dictionary!I$2:I$1212, MATCH(Table2[[#This Row],[WBS_ID]], Table26[WBS CODE],0)), "") = "", "null", IFERROR(INDEX(WBS_Dictionary!I$2:I$1212, MATCH(Table2[[#This Row],[WBS_ID]], Table26[WBS CODE],0)), "")) -> null | Z8: =IF(IFERROR(INDEX(WBS_Dictionary!J$2:J$1212, MATCH(Table2[[#This Row],[WBS_ID]], Table26[WBS CODE],0)), "") = "", "null", IFERROR(INDEX(WBS_Dictionary!J$2:J$1212, MATCH(Table2[[#This Row],[WBS_ID]], Table26[WBS CODE],0)), "")) -> Surface Facilities Cost | AA8: =IF(IFERROR(INDEX(WBS_Dictionary!K$2:K$1212, MATCH(Table2[[#This Row],[WBS_ID]], Table26[WBS CODE],0)), "") = "", "null", IFERROR(INDEX(WBS_Dictionary!K$2:K$1212, MATCH(Table2[[#This Row],[WBS_ID]], Table26[WBS CODE],0)), "")) -> null | AB8: =IF(IFERROR(INDEX(WBS_Dictionary!L$2:L$1212, MATCH(Table2[[#This Row],[WBS_ID]], Table26[WBS CODE],0)), "") = "", "null", IFERROR(INDEX(WBS_Dictionary!L$2:L$1212, MATCH(Table2[[#This Row],[WBS_ID]], Table26[WBS CODE],0)), "")) -> null | ... AE8: =IF(IFERROR(INDEX(WBS_Dictionary!O$2:O$1212, MATCH(Table2[[#This Row],[WBS_ID]], Table26[WBS CODE],0)), "") = "", "null", IFERROR(INDEX(WBS_Dictionary!O$2:O$1212, MATCH(Table2[[#This Row],[WBS_ID]], Table26[WBS CODE],0)), "")) -> null
A9: 8 | B9: 03 | C9: New Rig Pavement | D9: E540-3020393-D245401 | E9: D245401 | F9: 1051900 | G9: USD | H9: 0 | I9: USD | J9: 0 | K9: USD | L9: 0 | M9: USD | N9: 0 | O9: USD | P9: X | R9: STAR ENERGY | S9: Production | T9: REL BUDG AVAC // BUDG | U9: =IF(IFERROR(INDEX(WBS_Dictionary!E$2:E$1212, MATCH(Table2[[#This Row],[WBS_ID]], Table26[WBS CODE],0)), "") = "", "null", IFERROR(INDEX(WBS_Dictionary!E$2:E$1212, MATCH(Table2[[#This Row],[WBS_ID]], Table26[WBS CODE],0)), "")) -> E540-30-D245401 | V9: =IF(IFERROR(INDEX(WBS_Dictionary!F$2:F$1212, MATCH(Table2[[#This Row],[WBS_ID]], Table26[WBS CODE],0)), "") = "", "null", IFERROR(INDEX(WBS_Dictionary!F$2:F$1212, MATCH(Table2[[#This Row],[WBS_ID]], Table26[WBS CODE],0)), "")) -> E540-30203-D245401 | W9: =IF(IFERROR(INDEX(WBS_Dictionary!G$2:G$1212, MATCH(Table2[[#This Row],[WBS_ID]], Table26[WBS CODE],0)), "") = "", "null", IFERROR(INDEX(WBS_Dictionary!G$2:G$1212, MATCH(Table2[[#This Row],[WBS_ID]], Table26[WBS CODE],0)), "")) -> E540-3020393-D245401 | X9: =IF(IFERROR(INDEX(WBS_Dictionary!H$2:H$1212, MATCH(Table2[[#This Row],[WBS_ID]], Table26[WBS CODE],0)), "") = "", "null", IFERROR(INDEX(WBS_Dictionary!H$2:H$1212, MATCH(Table2[[#This Row],[WBS_ID]], Table26[WBS CODE],0)), "")) -> null | Y9: =IF(IFERROR(INDEX(WBS_Dictionary!I$2:I$1212, MATCH(Table2[[#This Row],[WBS_ID]], Table26[WBS CODE],0)), "") = "", "null", IFERROR(INDEX(WBS_Dictionary!I$2:I$1212, MATCH(Table2[[#This Row],[WBS_ID]], Table26[WBS CODE],0)), "")) -> null | Z9: =IF(IFERROR(INDEX(WBS_Dictionary!J$2:J$1212, MATCH(Table2[[#This Row],[WBS_ID]], Table26[WBS CODE],0)), "") = "", "null", IFERROR(INDEX(WBS_Dictionary!J$2:J$1212, MATCH(Table2[[#This Row],[WBS_ID]], Table26[WBS CODE],0)), "")) -> Surface Facilities Cost | AA9: =IF(IFERROR(INDEX(WBS_Dictionary!K$2:K$1212, MATCH(Table2[[#This Row],[WBS_ID]], Table26[WBS CODE],0)), "") = "", "null", IFERROR(INDEX(WBS_Dictionary!K$2:K$1212, MATCH(Table2[[#This Row],[WBS_ID]], Table26[WBS CODE],0)), "")) -> New Rig Pavement | AB9: =IF(IFERROR(INDEX(WBS_Dictionary!L$2:L$1212, MATCH(Table2[[#This Row],[WBS_ID]], Table26[WBS CODE],0)), "") = "", "null", IFERROR(INDEX(WBS_Dictionary!L$2:L$1212, MATCH(Table2[[#This Row],[WBS_ID]], Table26[WBS CODE],0)), "")) -> null | ... AE9: =IF(IFERROR(INDEX(WBS_Dictionary!O$2:O$1212, MATCH(Table2[[#This Row],[WBS_ID]], Table26[WBS CODE],0)), "") = "", "null", IFERROR(INDEX(WBS_Dictionary!O$2:O$1212, MATCH(Table2[[#This Row],[WBS_ID]], Table26[WBS CODE],0)), "")) -> null
A10: 9 | B10: 04 | C10: New Rig Pavement | D10: E540-302039309-D245401 | E10: D245401 | F10: 0 | G10: USD | H10: 0 | I10: USD | J10: 0 | K10: USD | L10: 0 | M10: USD | N10: 0 | O10: USD | P10: X | R10: STAR ENERGY | S10: Production | T10: REL AVAC // BUDG | U10: =IF(IFERROR(INDEX(WBS_Dictionary!E$2:E$1212, MATCH(Table2[[#This Row],[WBS_ID]], Table26[WBS CODE],0)), "") = "", "null", IFERROR(INDEX(WBS_Dictionary!E$2:E$1212, MATCH(Table2[[#This Row],[WBS_ID]], Table26[WBS CODE],0)), "")) -> E540-30-D245401 | V10: =IF(IFERROR(INDEX(WBS_Dictionary!F$2:F$1212, MATCH(Table2[[#This Row],[WBS_ID]], Table26[WBS CODE],0)), "") = "", "null", IFERROR(INDEX(WBS_Dictionary!F$2:F$1212, MATCH(Table2[[#This Row],[WBS_ID]], Table26[WBS CODE],0)), "")) -> E540-30203-D245401 | W10: =IF(IFERROR(INDEX(WBS_Dictionary!G$2:G$1212, MATCH(Table2[[#This Row],[WBS_ID]], Table26[WBS CODE],0)), "") = "", "null", IFERROR(INDEX(WBS_Dictionary!G$2:G$1212, MATCH(Table2[[#This Row],[WBS_ID]], Table26[WBS CODE],0)), "")) -> E540-3020393-D245401 | X10: =IF(IFERROR(INDEX(WBS_Dictionary!H$2:H$1212, MATCH(Table2[[#This Row],[WBS_ID]], Table26[WBS CODE],0)), "") = "", "null", IFERROR(INDEX(WBS_Dictionary!H$2:H$1212, MATCH(Table2[[#This Row],[WBS_ID]], Table26[WBS CODE],0)), "")) -> E540-302039309-D245401 | Y10: =IF(IFERROR(INDEX(WBS_Dictionary!I$2:I$1212, MATCH(Table2[[#This Row],[WBS_ID]], Table26[WBS CODE],0)), "") = "", "null", IFERROR(INDEX(WBS_Dictionary!I$2:I$1212, MATCH(Table2[[#This Row],[WBS_ID]], Table26[WBS CODE],0)), "")) -> null | Z10: =IF(IFERROR(INDEX(WBS_Dictionary!J$2:J$1212, MATCH(Table2[[#This Row],[WBS_ID]], Table26[WBS CODE],0)), "") = "", "null", IFERROR(INDEX(WBS_Dictionary!J$2:J$1212, MATCH(Table2[[#This Row],[WBS_ID]], Table26[WBS CODE],0)), "")) -> Surface Facilities Cost | AA10: =IF(IFERROR(INDEX(WBS_Dictionary!K$2:K$1212, MATCH(Table2[[#This Row],[WBS_ID]], Table26[WBS CODE],0)), "") = "", "null", IFERROR(INDEX(WBS_Dictionary!K$2:K$1212, MATCH(Table2[[#This Row],[WBS_ID]], Table26[WBS CODE],0)), "")) -> New Rig Pavement | AB10: =IF(IFERROR(INDEX(WBS_Dictionary!L$2:L$1212, MATCH(Table2[[#This Row],[WBS_ID]], Table26[WBS CODE],0)), "") = "", "null", IFERROR(INDEX(WBS_Dictionary!L$2:L$1212, MATCH(Table2[[#This Row],[WBS_ID]], Table26[WBS CODE],0)), "")) -> Construction | ... AE10: =IF(IFERROR(INDEX(WBS_Dictionary!O$2:O$1212, MATCH(Table2[[#This Row],[WBS_ID]], Table26[WBS CODE],0)), "") = "", "null", IFERROR(INDEX(WBS_Dictionary!O$2:O$1212, MATCH(Table2[[#This Row],[WBS_ID]], Table26[WBS CODE],0)), "")) -> null
A11: 10 | B11: 05 | C11: New Rig Pavement | D11: E540-30203930961-D245401 | E11: D245401 | F11: 0 | G11: USD | H11: 0 | I11: USD | J11: 0 | K11: USD | L11: 0 | M11: USD | N11: 0 | O11: USD | P11: X | R11: STAR ENERGY | S11: Production | T11: REL AVAC // BUDG | U11: =IF(IFERROR(INDEX(WBS_Dictionary!E$2:E$1212, MATCH(Table2[[#This Row],[WBS_ID]], Table26[WBS CODE],0)), "") = "", "null", IFERROR(INDEX(WBS_Dictionary!E$2:E$1212, MATCH(Table2[[#This Row],[WBS_ID]], Table26[WBS CODE],0)), "")) -> E540-30-D245401 | V11: =IF(IFERROR(INDEX(WBS_Dictionary!F$2:F$1212, MATCH(Table2[[#This Row],[WBS_ID]], Table26[WBS CODE],0)), "") = "", "null", IFERROR(INDEX(WBS_Dictionary!F$2:F$1212, MATCH(Table2[[#This Row],[WBS_ID]], Table26[WBS CODE],0)), "")) -> E540-30203-D245401 | W11: =IF(IFERROR(INDEX(WBS_Dictionary!G$2:G$1212, MATCH(Table2[[#This Row],[WBS_ID]], Table26[WBS CODE],0)), "") = "", "null", IFERROR(INDEX(WBS_Dictionary!G$2:G$1212, MATCH(Table2[[#This Row],[WBS_ID]], Table26[WBS CODE],0)), "")) -> E540-3020393-D245401 | X11: =IF(IFERROR(INDEX(WBS_Dictionary!H$2:H$1212, MATCH(Table2[[#This Row],[WBS_ID]], Table26[WBS CODE],0)), "") = "", "null", IFERROR(INDEX(WBS_Dictionary!H$2:H$1212, MATCH(Table2[[#This Row],[WBS_ID]], Table26[WBS CODE],0)), "")) -> E540-302039309-D245401 | Y11: =IF(IFERROR(INDEX(WBS_Dictionary!I$2:I$1212, MATCH(Table2[[#This Row],[WBS_ID]], Table26[WBS CODE],0)), "") = "", "null", IFERROR(INDEX(WBS_Dictionary!I$2:I$1212, MATCH(Table2[[#This Row],[WBS_ID]], Table26[WBS CODE],0)), "")) -> E540-30203930961-D245401 | Z11: =IF(IFERROR(INDEX(WBS_Dictionary!J$2:J$1212, MATCH(Table2[[#This Row],[WBS_ID]], Table26[WBS CODE],0)), "") = "", "null", IFERROR(INDEX(WBS_Dictionary!J$2:J$1212, MATCH(Table2[[#This Row],[WBS_ID]], Table26[WBS CODE],0)), "")) -> Surface Facilities Cost | AA11: =IF(IFERROR(INDEX(WBS_Dictionary!K$2:K$1212, MATCH(Table2[[#This Row],[WBS_ID]], Table26[WBS CODE],0)), "") = "", "null", IFERROR(INDEX(WBS_Dictionary!K$2:K$1212, MATCH(Table2[[#This Row],[WBS_ID]], Table26[WBS CODE],0)), "")) -> New Rig Pavement | AB11: =IF(IFERROR(INDEX(WBS_Dictionary!L$2:L$1212, MATCH(Table2[[#This Row],[WBS_ID]], Table26[WBS CODE],0)), "") = "", "null", IFERROR(INDEX(WBS_Dictionary!L$2:L$1212, MATCH(Table2[[#This Row],[WBS_ID]], Table26[WBS CODE],0)), "")) -> Construction | ... AE11: =IF(IFERROR(INDEX(WBS_Dictionary!O$2:O$1212, MATCH(Table2[[#This Row],[WBS_ID]], Table26[WBS CODE],0)), "") = "", "null", IFERROR(INDEX(WBS_Dictionary!O$2:O$1212, MATCH(Table2[[#This Row],[WBS_ID]], Table26[WBS CODE],0)), "")) -> null
A12: 11 | B12: 03 | C12: Tie-in AWI3 | D12: E540-3020394-D245401 | E12: D245401 | F12: 442618.13 | G12: USD | H12: 442618.13 | I12: USD | J12: 0 | K12: USD | L12: 18695.05 | M12: USD | N12: 336073.61 | O12: USD | P12: X | R12: STAR ENERGY | S12: Production | T12: REL BUDG AVAC // BUDG | U12: =IF(IFERROR(INDEX(WBS_Dictionary!E$2:E$1212, MATCH(Table2[[#This Row],[WBS_ID]], Table26[WBS CODE],0)), "") = "", "null", IFERROR(INDEX(WBS_Dictionary!E$2:E$1212, MATCH(Table2[[#This Row],[WBS_ID]], Table26[WBS CODE],0)), "")) -> E540-30-D245401 | V12: =IF(IFERROR(INDEX(WBS_Dictionary!F$2:F$1212, MATCH(Table2[[#This Row],[WBS_ID]], Table26[WBS CODE],0)), "") = "", "null", IFERROR(INDEX(WBS_Dictionary!F$2:F$1212, MATCH(Table2[[#This Row],[WBS_ID]], Table26[WBS CODE],0)), "")) -> E540-30203-D245401 | W12: =IF(IFERROR(INDEX(WBS_Dictionary!G$2:G$1212, MATCH(Table2[[#This Row],[WBS_ID]], Table26[WBS CODE],0)), "") = "", "null", IFERROR(INDEX(WBS_Dictionary!G$2:G$1212, MATCH(Table2[[#This Row],[WBS_ID]], Table26[WBS CODE],0)), "")) -> E540-3020394-D245401 | X12: =IF(IFERROR(INDEX(WBS_Dictionary!H$2:H$1212, MATCH(Table2[[#This Row],[WBS_ID]], Table26[WBS CODE],0)), "") = "", "null", IFERROR(INDEX(WBS_Dictionary!H$2:H$1212, MATCH(Table2[[#This Row],[WBS_ID]], Table26[WBS CODE],0)), "")) -> null | Y12: =IF(IFERROR(INDEX(WBS_Dictionary!I$2:I$1212, MATCH(Table2[[#This Row],[WBS_ID]], Table26[WBS CODE],0)), "") = "", "null", IFERROR(INDEX(WBS_Dictionary!I$2:I$1212, MATCH(Table2[[#This Row],[WBS_ID]], Table26[WBS CODE],0)), "")) -> null | Z12: =IF(IFERROR(INDEX(WBS_Dictionary!J$2:J$1212, MATCH(Table2[[#This Row],[WBS_ID]], Table26[WBS CODE],0)), "") = "", "null", IFERROR(INDEX(WBS_Dictionary!J$2:J$1212, MATCH(Table2[[#This Row],[WBS_ID]], Table26[WBS CODE],0)), "")) -> Surface Facilities Cost | AA12: =IF(IFERROR(INDEX(WBS_Dictionary!K$2:K$1212, MATCH(Table2[[#This Row],[WBS_ID]], Table26[WBS CODE],0)), "") = "", "null", IFERROR(INDEX(WBS_Dictionary!K$2:K$1212, MATCH(Table2[[#This Row],[WBS_ID]], Table26[WBS CODE],0)), "")) -> Tie-in | AB12: =IF(IFERROR(INDEX(WBS_Dictionary!L$2:L$1212, MATCH(Table2[[#This Row],[WBS_ID]], Table26[WBS CODE],0)), "") = "", "null", IFERROR(INDEX(WBS_Dictionary!L$2:L$1212, MATCH(Table2[[#This Row],[WBS_ID]], Table26[WBS CODE],0)), "")) -> null | ... AE12: =IF(IFERROR(INDEX(WBS_Dictionary!O$2:O$1212, MATCH(Table2[[#This Row],[WBS_ID]], Table26[WBS CODE],0)), "") = "", "null", IFERROR(INDEX(WBS_Dictionary!O$2:O$1212, MATCH(Table2[[#This Row],[WBS_ID]], Table26[WBS CODE],0)), "")) -> Pad
A13: 12 | B13: 04 | C13: Tie In - Const Pad AWI3 | D13: E540-302039409-D245401 | E13: D245401 | F13: 186765.16 | G13: USD | H13: 186765.16 | I13: USD | J13: 0 | K13: USD | L13: 11341.6 | M13: USD | N13: 143570.32 | O13: USD | P13: X | R13: STAR ENERGY | S13: Production | T13: REL BUDG ISBD AVAC // BUDG | U13: =IF(IFERROR(INDEX(WBS_Dictionary!E$2:E$1212, MATCH(Table2[[#This Row],[WBS_ID]], Table26[WBS CODE],0)), "") = "", "null", IFERROR(INDEX(WBS_Dictionary!E$2:E$1212, MATCH(Table2[[#This Row],[WBS_ID]], Table26[WBS CODE],0)), "")) -> E540-30-D245401 | V13: =IF(IFERROR(INDEX(WBS_Dictionary!F$2:F$1212, MATCH(Table2[[#This Row],[WBS_ID]], Table26[WBS CODE],0)), "") = "", "null", IFERROR(INDEX(WBS_Dictionary!F$2:F$1212, MATCH(Table2[[#This Row],[WBS_ID]], Table26[WBS CODE],0)), "")) -> E540-30203-D245401 | W13: =IF(IFERROR(INDEX(WBS_Dictionary!G$2:G$1212, MATCH(Table2[[#This Row],[WBS_ID]], Table26[WBS CODE],0)), "") = "", "null", IFERROR(INDEX(WBS_Dictionary!G$2:G$1212, MATCH(Table2[[#This Row],[WBS_ID]], Table26[WBS CODE],0)), "")) -> E540-3020394-D245401 | X13: =IF(IFERROR(INDEX(WBS_Dictionary!H$2:H$1212, MATCH(Table2[[#This Row],[WBS_ID]], Table26[WBS CODE],0)), "") = "", "null", IFERROR(INDEX(WBS_Dictionary!H$2:H$1212, MATCH(Table2[[#This Row],[WBS_ID]], Table26[WBS CODE],0)), "")) -> E540-302039409-D245401 | Y13: =IF(IFERROR(INDEX(WBS_Dictionary!I$2:I$1212, MATCH(Table2[[#This Row],[WBS_ID]], Table26[WBS CODE],0)), "") = "", "null", IFERROR(INDEX(WBS_Dictionary!I$2:I$1212, MATCH(Table2[[#This Row],[WBS_ID]], Table26[WBS CODE],0)), "")) -> null | Z13: =IF(IFERROR(INDEX(WBS_Dictionary!J$2:J$1212, MATCH(Table2[[#This Row],[WBS_ID]], Table26[WBS CODE],0)), "") = "", "null", IFERROR(INDEX(WBS_Dictionary!J$2:J$1212, MATCH(Table2[[#This Row],[WBS_ID]], Table26[WBS CODE],0)), "")) -> Surface Facilities Cost | AA13: =IF(IFERROR(INDEX(WBS_Dictionary!K$2:K$1212, MATCH(Table2[[#This Row],[WBS_ID]], Table26[WBS CODE],0)), "") = "", "null", IFERROR(INDEX(WBS_Dictionary!K$2:K$1212, MATCH(Table2[[#This Row],[WBS_ID]], Table26[WBS CODE],0)), "")) -> Tie-in | AB13: =IF(IFERROR(INDEX(WBS_Dictionary!L$2:L$1212, MATCH(Table2[[#This Row],[WBS_ID]], Table26[WBS CODE],0)), "") = "", "null", IFERROR(INDEX(WBS_Dictionary!L$2:L$1212, MATCH(Table2[[#This Row],[WBS_ID]], Table26[WBS CODE],0)), "")) -> Construction | ... AE13: =IF(IFERROR(INDEX(WBS_Dictionary!O$2:O$1212, MATCH(Table2[[#This Row],[WBS_ID]], Table26[WBS CODE],0)), "") = "", "null", IFERROR(INDEX(WBS_Dictionary!O$2:O$1212, MATCH(Table2[[#This Row],[WBS_ID]], Table26[WBS CODE],0)), "")) -> Pad
A14: 13 | B14: 05 | C14: Tie In-Inst,HookUp&Pre-Comm Pad AWI3 | D14: E540-30203940963-D245401 | E14: D245401 | F14: 0 | G14: USD | H14: 0 | I14: USD | J14: 0 | K14: USD | L14: 11341.6 | M14: USD | N14: 143570.32 | O14: USD | P14: X | R14: STAR ENERGY | S14: Production | T14: REL AUC AVAC SETC // BUDG | U14: =IF(IFERROR(INDEX(WBS_Dictionary!E$2:E$1212, MATCH(Table2[[#This Row],[WBS_ID]], Table26[WBS CODE],0)), "") = "", "null", IFERROR(INDEX(WBS_Dictionary!E$2:E$1212, MATCH(Table2[[#This Row],[WBS_ID]], Table26[WBS CODE],0)), "")) -> E540-30-D245401 | V14: =IF(IFERROR(INDEX(WBS_Dictionary!F$2:F$1212, MATCH(Table2[[#This Row],[WBS_ID]], Table26[WBS CODE],0)), "") = "", "null", IFERROR(INDEX(WBS_Dictionary!F$2:F$1212, MATCH(Table2[[#This Row],[WBS_ID]], Table26[WBS CODE],0)), "")) -> E540-30203-D245401 | W14: =IF(IFERROR(INDEX(WBS_Dictionary!G$2:G$1212, MATCH(Table2[[#This Row],[WBS_ID]], Table26[WBS CODE],0)), "") = "", "null", IFERROR(INDEX(WBS_Dictionary!G$2:G$1212, MATCH(Table2[[#This Row],[WBS_ID]], Table26[WBS CODE],0)), "")) -> E540-3020394-D245401 | X14: =IF(IFERROR(INDEX(WBS_Dictionary!H$2:H$1212, MATCH(Table2[[#This Row],[WBS_ID]], Table26[WBS CODE],0)), "") = "", "null", IFERROR(INDEX(WBS_Dictionary!H$2:H$1212, MATCH(Table2[[#This Row],[WBS_ID]], Table26[WBS CODE],0)), "")) -> E540-302039409-D245401 | Y14: =IF(IFERROR(INDEX(WBS_Dictionary!I$2:I$1212, MATCH(Table2[[#This Row],[WBS_ID]], Table26[WBS CODE],0)), "") = "", "null", IFERROR(INDEX(WBS_Dictionary!I$2:I$1212, MATCH(Table2[[#This Row],[WBS_ID]], Table26[WBS CODE],0)), "")) -> E540-30203940963-D245401 | Z14: =IF(IFERROR(INDEX(WBS_Dictionary!J$2:J$1212, MATCH(Table2[[#This Row],[WBS_ID]], Table26[WBS CODE],0)), "") = "", "null", IFERROR(INDEX(WBS_Dictionary!J$2:J$1212, MATCH(Table2[[#This Row],[WBS_ID]], Table26[WBS CODE],0)), "")) -> Surface Facilities Cost | AA14: =IF(IFERROR(INDEX(WBS_Dictionary!K$2:K$1212, MATCH(Table2[[#This Row],[WBS_ID]], Table26[WBS CODE],0)), "") = "", "null", IFERROR(INDEX(WBS_Dictionary!K$2:K$1212, MATCH(Table2[[#This Row],[WBS_ID]], Table26[WBS CODE],0)), "")) -> Tie-in | AB14: =IF(IFERROR(INDEX(WBS_Dictionary!L$2:L$1212, MATCH(Table2[[#This Row],[WBS_ID]], Table26[WBS CODE],0)), "") = "", "null", IFERROR(INDEX(WBS_Dictionary!L$2:L$1212, MATCH(Table2[[#This Row],[WBS_ID]], Table26[WBS CODE],0)), "")) -> Construction | ... AE14: =IF(IFERROR(INDEX(WBS_Dictionary!O$2:O$1212, MATCH(Table2[[#This Row],[WBS_ID]], Table26[WBS CODE],0)), "") = "", "null", IFERROR(INDEX(WBS_Dictionary!O$2:O$1212, MATCH(Table2[[#This Row],[WBS_ID]], Table26[WBS CODE],0)), "")) -> Pad
A15: 14 | B15: 04 | C15: Tie In - Proc Pad AWI3 | D15: E540-302039408-D245401 | E15: D245401 | F15: 201428.97 | G15: USD | H15: 201428.97 | I15: USD | J15: 0 | K15: USD | L15: 7353.45 | M15: USD | N15: 158684.62 | O15: USD | P15: X | R15: STAR ENERGY | S15: Production | T15: REL BUDG ISBD AVAC // BUDG | U15: =IF(IFERROR(INDEX(WBS_Dictionary!E$2:E$1212, MATCH(Table2[[#This Row],[WBS_ID]], Table26[WBS CODE],0)), "") = "", "null", IFERROR(INDEX(WBS_Dictionary!E$2:E$1212, MATCH(Table2[[#This Row],[WBS_ID]], Table26[WBS CODE],0)), "")) -> E540-30-D245401 | V15: =IF(IFERROR(INDEX(WBS_Dictionary!F$2:F$1212, MATCH(Table2[[#This Row],[WBS_ID]], Table26[WBS CODE],0)), "") = "", "null", IFERROR(INDEX(WBS_Dictionary!F$2:F$1212, MATCH(Table2[[#This Row],[WBS_ID]], Table26[WBS CODE],0)), "")) -> E540-30203-D245401 | W15: =IF(IFERROR(INDEX(WBS_Dictionary!G$2:G$1212, MATCH(Table2[[#This Row],[WBS_ID]], Table26[WBS CODE],0)), "") = "", "null", IFERROR(INDEX(WBS_Dictionary!G$2:G$1212, MATCH(Table2[[#This Row],[WBS_ID]], Table26[WBS CODE],0)), "")) -> E540-3020394-D245401 | X15: =IF(IFERROR(INDEX(WBS_Dictionary!H$2:H$1212, MATCH(Table2[[#This Row],[WBS_ID]], Table26[WBS CODE],0)), "") = "", "null", IFERROR(INDEX(WBS_Dictionary!H$2:H$1212, MATCH(Table2[[#This Row],[WBS_ID]], Table26[WBS CODE],0)), "")) -> E540-302039408-D245401 | Y15: =IF(IFERROR(INDEX(WBS_Dictionary!I$2:I$1212, MATCH(Table2[[#This Row],[WBS_ID]], Table26[WBS CODE],0)), "") = "", "null", IFERROR(INDEX(WBS_Dictionary!I$2:I$1212, MATCH(Table2[[#This Row],[WBS_ID]], Table26[WBS CODE],0)), "")) -> null | Z15: =IF(IFERROR(INDEX(WBS_Dictionary!J$2:J$1212, MATCH(Table2[[#This Row],[WBS_ID]], Table26[WBS CODE],0)), "") = "", "null", IFERROR(INDEX(WBS_Dictionary!J$2:J$1212, MATCH(Table2[[#This Row],[WBS_ID]], Table26[WBS CODE],0)), "")) -> Surface Facilities Cost | AA15: =IF(IFERROR(INDEX(WBS_Dictionary!K$2:K$1212, MATCH(Table2[[#This Row],[WBS_ID]], Table26[WBS CODE],0)), "") = "", "null", IFERROR(INDEX(WBS_Dictionary!K$2:K$1212, MATCH(Table2[[#This Row],[WBS_ID]], Table26[WBS CODE],0)), "")) -> Tie-in | AB15: =IF(IFERROR(INDEX(WBS_Dictionary!L$2:L$1212, MATCH(Table2[[#This Row],[WBS_ID]], Table26[WBS CODE],0)), "") = "", "null", IFERROR(INDEX(WBS_Dictionary!L$2:L$1212, MATCH(Table2[[#This Row],[WBS_ID]], Table26[WBS CODE],0)), "")) -> Procurement | ... AE15: =IF(IFERROR(INDEX(WBS_Dictionary!O$2:O$1212, MATCH(Table2[[#This Row],[WBS_ID]], Table26[WBS CODE],0)), "") = "", "null", IFERROR(INDEX(WBS_Dictionary!O$2:O$1212, MATCH(Table2[[#This Row],[WBS_ID]], Table26[WBS CODE],0)), "")) -> Pad
... A76: 75 | B76: 05 | C76: Road & Pad Eng Pad AWI2 | D76: E540-30203830759-D245401 | E76: D245401 | F76: 0 | G76: USD | H76: 0 | I76: USD | J76: 0 | K76: USD | L76: 0 | M76: USD | N76: 24412.75 | O76: USD | P76: X | R76: STAR ENERGY | S76: Production | T76: REL AUC AVAC SETC // BUDG | U76: =IF(IFERROR(INDEX(WBS_Dictionary!E$2:E$1212, MATCH(Table2[[#This Row],[WBS_ID]], Table26[WBS CODE],0)), "") = "", "null", IFERROR(INDEX(WBS_Dictionary!E$2:E$1212, MATCH(Table2[[#This Row],[WBS_ID]], Table26[WBS CODE],0)), "")) -> E540-30-D245401 | V76: =IF(IFERROR(INDEX(WBS_Dictionary!F$2:F$1212, MATCH(Table2[[#This Row],[WBS_ID]], Table26[WBS CODE],0)), "") = "", "null", IFERROR(INDEX(WBS_Dictionary!F$2:F$1212, MATCH(Table2[[#This Row],[WBS_ID]], Table26[WBS CODE],0)), "")) -> E540-30203-D245401 | W76: =IF(IFERROR(INDEX(WBS_Dictionary!G$2:G$1212, MATCH(Table2[[#This Row],[WBS_ID]], Table26[WBS CODE],0)), "") = "", "null", IFERROR(INDEX(WBS_Dictionary!G$2:G$1212, MATCH(Table2[[#This Row],[WBS_ID]], Table26[WBS CODE],0)), "")) -> E540-3020383-D245401 | X76: =IF(IFERROR(INDEX(WBS_Dictionary!H$2:H$1212, MATCH(Table2[[#This Row],[WBS_ID]], Table26[WBS CODE],0)), "") = "", "null", IFERROR(INDEX(WBS_Dictionary!H$2:H$1212, MATCH(Table2[[#This Row],[WBS_ID]], Table26[WBS CODE],0)), "")) -> E540-302038307-D245401 | Y76: =IF(IFERROR(INDEX(WBS_Dictionary!I$2:I$1212, MATCH(Table2[[#This Row],[WBS_ID]], Table26[WBS CODE],0)), "") = "", "null", IFERROR(INDEX(WBS_Dictionary!I$2:I$1212, MATCH(Table2[[#This Row],[WBS_ID]], Table26[WBS CODE],0)), "")) -> E540-30203830759-D245401 | Z76: =IF(IFERROR(INDEX(WBS_Dictionary!J$2:J$1212, MATCH(Table2[[#This Row],[WBS_ID]], Table26[WBS CODE],0)), "") = "", "null", IFERROR(INDEX(WBS_Dictionary!J$2:J$1212, MATCH(Table2[[#This Row],[WBS_ID]], Table26[WBS CODE],0)), "")) -> Surface Facilities Cost | AA76: =IF(IFERROR(INDEX(WBS_Dictionary!K$2:K$1212, MATCH(Table2[[#This Row],[WBS_ID]], Table26[WBS CODE],0)), "") = "", "null", IFERROR(INDEX(WBS_Dictionary!K$2:K$1212, MATCH(Table2[[#This Row],[WBS_ID]], Table26[WBS CODE],0)), "")) -> Road & Pad | AB76: =IF(IFERROR(INDEX(WBS_Dictionary!L$2:L$1212, MATCH(Table2[[#This Row],[WBS_ID]], Table26[WBS CODE],0)), "") = "", "null", IFERROR(INDEX(WBS_Dictionary!L$2:L$1212, MATCH(Table2[[#This Row],[WBS_ID]], Table26[WBS CODE],0)), "")) -> Engineering | ... AE76: =IF(IFERROR(INDEX(WBS_Dictionary!O$2:O$1212, MATCH(Table2[[#This Row],[WBS_ID]], Table26[WBS CODE],0)), "") = "", "null", IFERROR(INDEX(WBS_Dictionary!O$2:O$1212, MATCH(Table2[[#This Row],[WBS_ID]], Table26[WBS CODE],0)), "")) -> Pad
A77: 76 | B77: 03 | C77: Conductor casing installation & material | D77: E540-3020374-D245401 | E77: D245401 | F77: 2987092.4 | G77: USD | H77: 2987092.4 | I77: USD | J77: 0 | K77: USD | L77: 0 | M77: USD | N77: 1843582.9 | O77: USD | Q77: X | R77: STAR ENERGY | S77: Production | T77: REL BUDG AVAC // BUDG | U77: =IF(IFERROR(INDEX(WBS_Dictionary!E$2:E$1212, MATCH(Table2[[#This Row],[WBS_ID]], Table26[WBS CODE],0)), "") = "", "null", IFERROR(INDEX(WBS_Dictionary!E$2:E$1212, MATCH(Table2[[#This Row],[WBS_ID]], Table26[WBS CODE],0)), "")) -> E540-30-D245401 | V77: =IF(IFERROR(INDEX(WBS_Dictionary!F$2:F$1212, MATCH(Table2[[#This Row],[WBS_ID]], Table26[WBS CODE],0)), "") = "", "null", IFERROR(INDEX(WBS_Dictionary!F$2:F$1212, MATCH(Table2[[#This Row],[WBS_ID]], Table26[WBS CODE],0)), "")) -> E540-30203-D245401 | W77: =IF(IFERROR(INDEX(WBS_Dictionary!G$2:G$1212, MATCH(Table2[[#This Row],[WBS_ID]], Table26[WBS CODE],0)), "") = "", "null", IFERROR(INDEX(WBS_Dictionary!G$2:G$1212, MATCH(Table2[[#This Row],[WBS_ID]], Table26[WBS CODE],0)), "")) -> E540-3020374-D245401 | X77: =IF(IFERROR(INDEX(WBS_Dictionary!H$2:H$1212, MATCH(Table2[[#This Row],[WBS_ID]], Table26[WBS CODE],0)), "") = "", "null", IFERROR(INDEX(WBS_Dictionary!H$2:H$1212, MATCH(Table2[[#This Row],[WBS_ID]], Table26[WBS CODE],0)), "")) -> null | Y77: =IF(IFERROR(INDEX(WBS_Dictionary!I$2:I$1212, MATCH(Table2[[#This Row],[WBS_ID]], Table26[WBS CODE],0)), "") = "", "null", IFERROR(INDEX(WBS_Dictionary!I$2:I$1212, MATCH(Table2[[#This Row],[WBS_ID]], Table26[WBS CODE],0)), "")) -> null | Z77: =IF(IFERROR(INDEX(WBS_Dictionary!J$2:J$1212, MATCH(Table2[[#This Row],[WBS_ID]], Table26[WBS CODE],0)), "") = "", "null", IFERROR(INDEX(WBS_Dictionary!J$2:J$1212, MATCH(Table2[[#This Row],[WBS_ID]], Table26[WBS CODE],0)), "")) -> Surface Facilities Cost | AA77: =IF(IFERROR(INDEX(WBS_Dictionary!K$2:K$1212, MATCH(Table2[[#This Row],[WBS_ID]], Table26[WBS CODE],0)), "") = "", "null", IFERROR(INDEX(WBS_Dictionary!K$2:K$1212, MATCH(Table2[[#This Row],[WBS_ID]], Table26[WBS CODE],0)), "")) -> Conductor Casing Installation & Material | AB77: =IF(IFERROR(INDEX(WBS_Dictionary!L$2:L$1212, MATCH(Table2[[#This Row],[WBS_ID]], Table26[WBS CODE],0)), "") = "", "null", IFERROR(INDEX(WBS_Dictionary!L$2:L$1212, MATCH(Table2[[#This Row],[WBS_ID]], Table26[WBS CODE],0)), "")) -> null | ... AE77: =IF(IFERROR(INDEX(WBS_Dictionary!O$2:O$1212, MATCH(Table2[[#This Row],[WBS_ID]], Table26[WBS CODE],0)), "") = "", "null", IFERROR(INDEX(WBS_Dictionary!O$2:O$1212, MATCH(Table2[[#This Row],[WBS_ID]], Table26[WBS CODE],0)), "")) -> null
A78: 77 | B78: 04 | C78: Conductor Casing Inst & Mat Well 9 | D78: E540-302037409-D245401 | E78: D245401 | F78: 344287 | G78: USD | H78: 344287 | I78: USD | J78: 0 | K78: USD | L78: 0 | M78: USD | N78: 0 | O78: USD | Q78: X | R78: STAR ENERGY | S78: Production | T78: REL BUDG AVAC // BUDG | U78: =IF(IFERROR(INDEX(WBS_Dictionary!E$2:E$1212, MATCH(Table2[[#This Row],[WBS_ID]], Table26[WBS CODE],0)), "") = "", "null", IFERROR(INDEX(WBS_Dictionary!E$2:E$1212, MATCH(Table2[[#This Row],[WBS_ID]], Table26[WBS CODE],0)), "")) -> E540-30-D245401 | V78: =IF(IFERROR(INDEX(WBS_Dictionary!F$2:F$1212, MATCH(Table2[[#This Row],[WBS_ID]], Table26[WBS CODE],0)), "") = "", "null", IFERROR(INDEX(WBS_Dictionary!F$2:F$1212, MATCH(Table2[[#This Row],[WBS_ID]], Table26[WBS CODE],0)), "")) -> E540-30203-D245401 | W78: =IF(IFERROR(INDEX(WBS_Dictionary!G$2:G$1212, MATCH(Table2[[#This Row],[WBS_ID]], Table26[WBS CODE],0)), "") = "", "null", IFERROR(INDEX(WBS_Dictionary!G$2:G$1212, MATCH(Table2[[#This Row],[WBS_ID]], Table26[WBS CODE],0)), "")) -> E540-3020374-D245401 | X78: =IF(IFERROR(INDEX(WBS_Dictionary!H$2:H$1212, MATCH(Table2[[#This Row],[WBS_ID]], Table26[WBS CODE],0)), "") = "", "null", IFERROR(INDEX(WBS_Dictionary!H$2:H$1212, MATCH(Table2[[#This Row],[WBS_ID]], Table26[WBS CODE],0)), "")) -> E540-302037409-D245401 | Y78: =IF(IFERROR(INDEX(WBS_Dictionary!I$2:I$1212, MATCH(Table2[[#This Row],[WBS_ID]], Table26[WBS CODE],0)), "") = "", "null", IFERROR(INDEX(WBS_Dictionary!I$2:I$1212, MATCH(Table2[[#This Row],[WBS_ID]], Table26[WBS CODE],0)), "")) -> null | Z78: =IF(IFERROR(INDEX(WBS_Dictionary!J$2:J$1212, MATCH(Table2[[#This Row],[WBS_ID]], Table26[WBS CODE],0)), "") = "", "null", IFERROR(INDEX(WBS_Dictionary!J$2:J$1212, MATCH(Table2[[#This Row],[WBS_ID]], Table26[WBS CODE],0)), "")) -> Surface Facilities Cost | AA78: =IF(IFERROR(INDEX(WBS_Dictionary!K$2:K$1212, MATCH(Table2[[#This Row],[WBS_ID]], Table26[WBS CODE],0)), "") = "", "null", IFERROR(INDEX(WBS_Dictionary!K$2:K$1212, MATCH(Table2[[#This Row],[WBS_ID]], Table26[WBS CODE],0)), "")) -> Conductor Casing Installation & Material | AB78: =IF(IFERROR(INDEX(WBS_Dictionary!L$2:L$1212, MATCH(Table2[[#This Row],[WBS_ID]], Table26[WBS CODE],0)), "") = "", "null", IFERROR(INDEX(WBS_Dictionary!L$2:L$1212, MATCH(Table2[[#This Row],[WBS_ID]], Table26[WBS CODE],0)), "")) -> Conductor Casing Installation & Material | ... AE78: =IF(IFERROR(INDEX(WBS_Dictionary!O$2:O$1212, MATCH(Table2[[#This Row],[WBS_ID]], Table26[WBS CODE],0)), "") = "", "null", IFERROR(INDEX(WBS_Dictionary!O$2:O$1212, MATCH(Table2[[#This Row],[WBS_ID]], Table26[WBS CODE],0)), "")) -> null
A79: 78 | B79: 05 | C79: Cdtr Csg Material Well 9 | D79: E540-30203740960-D245401 | E79: D245401 | F79: 0 | G79: USD | H79: 0 | I79: USD | J79: 0 | K79: USD | L79: 0 | M79: USD | N79: 0 | O79: USD | Q79: X | R79: STAR ENERGY | S79: Production | T79: REL AVAC SETC // BUDG | U79: =IF(IFERROR(INDEX(WBS_Dictionary!E$2:E$1212, MATCH(Table2[[#This Row],[WBS_ID]], Table26[WBS CODE],0)), "") = "", "null", IFERROR(INDEX(WBS_Dictionary!E$2:E$1212, MATCH(Table2[[#This Row],[WBS_ID]], Table26[WBS CODE],0)), "")) -> E540-30-D245401 | V79: =IF(IFERROR(INDEX(WBS_Dictionary!F$2:F$1212, MATCH(Table2[[#This Row],[WBS_ID]], Table26[WBS CODE],0)), "") = "", "null", IFERROR(INDEX(WBS_Dictionary!F$2:F$1212, MATCH(Table2[[#This Row],[WBS_ID]], Table26[WBS CODE],0)), "")) -> E540-30203-D245401 | W79: =IF(IFERROR(INDEX(WBS_Dictionary!G$2:G$1212, MATCH(Table2[[#This Row],[WBS_ID]], Table26[WBS CODE],0)), "") = "", "null", IFERROR(INDEX(WBS_Dictionary!G$2:G$1212, MATCH(Table2[[#This Row],[WBS_ID]], Table26[WBS CODE],0)), "")) -> E540-3020374-D245401 | X79: =IF(IFERROR(INDEX(WBS_Dictionary!H$2:H$1212, MATCH(Table2[[#This Row],[WBS_ID]], Table26[WBS CODE],0)), "") = "", "null", IFERROR(INDEX(WBS_Dictionary!H$2:H$1212, MATCH(Table2[[#This Row],[WBS_ID]], Table26[WBS CODE],0)), "")) -> E540-302037409-D245401 | Y79: =IF(IFERROR(INDEX(WBS_Dictionary!I$2:I$1212, MATCH(Table2[[#This Row],[WBS_ID]], Table26[WBS CODE],0)), "") = "", "null", IFERROR(INDEX(WBS_Dictionary!I$2:I$1212, MATCH(Table2[[#This Row],[WBS_ID]], Table26[WBS CODE],0)), "")) -> E540-30203740960-D245401 | Z79: =IF(IFERROR(INDEX(WBS_Dictionary!J$2:J$1212, MATCH(Table2[[#This Row],[WBS_ID]], Table26[WBS CODE],0)), "") = "", "null", IFERROR(INDEX(WBS_Dictionary!J$2:J$1212, MATCH(Table2[[#This Row],[WBS_ID]], Table26[WBS CODE],0)), "")) -> Surface Facilities Cost | AA79: =IF(IFERROR(INDEX(WBS_Dictionary!K$2:K$1212, MATCH(Table2[[#This Row],[WBS_ID]], Table26[WBS CODE],0)), "") = "", "null", IFERROR(INDEX(WBS_Dictionary!K$2:K$1212, MATCH(Table2[[#This Row],[WBS_ID]], Table26[WBS CODE],0)), "")) -> Conductor Casing Installation & Material | AB79: =IF(IFERROR(INDEX(WBS_Dictionary!L$2:L$1212, MATCH(Table2[[#This Row],[WBS_ID]], Table26[WBS CODE],0)), "") = "", "null", IFERROR(INDEX(WBS_Dictionary!L$2:L$1212, MATCH(Table2[[#This Row],[WBS_ID]], Table26[WBS CODE],0)), "")) -> Material | ... AE79: =IF(IFERROR(INDEX(WBS_Dictionary!O$2:O$1212, MATCH(Table2[[#This Row],[WBS_ID]], Table26[WBS CODE],0)), "") = "", "null", IFERROR(INDEX(WBS_Dictionary!O$2:O$1212, MATCH(Table2[[#This Row],[WBS_ID]], Table26[WBS CODE],0)), "")) -> null
A80: 79 | B80: 05 | C80: Cdtr Csg Service Well 9 | D80: E540-30203740903-D245401 | E80: D245401 | F80: 0 | G80: USD | H80: 0 | I80: USD | J80: 0 | K80: USD | L80: 0 | M80: USD | N80: 0 | O80: USD | Q80: X | R80: STAR ENERGY | S80: Production | T80: REL AVAC SETC // BUDG | U80: =IF(IFERROR(INDEX(WBS_Dictionary!E$2:E$1212, MATCH(Table2[[#This Row],[WBS_ID]], Table26[WBS CODE],0)), "") = "", "null", IFERROR(INDEX(WBS_Dictionary!E$2:E$1212, MATCH(Table2[[#This Row],[WBS_ID]], Table26[WBS CODE],0)), "")) -> E540-30-D245401 | V80: =IF(IFERROR(INDEX(WBS_Dictionary!F$2:F$1212, MATCH(Table2[[#This Row],[WBS_ID]], Table26[WBS CODE],0)), "") = "", "null", IFERROR(INDEX(WBS_Dictionary!F$2:F$1212, MATCH(Table2[[#This Row],[WBS_ID]], Table26[WBS CODE],0)), "")) -> E540-30203-D245401 | W80: =IF(IFERROR(INDEX(WBS_Dictionary!G$2:G$1212, MATCH(Table2[[#This Row],[WBS_ID]], Table26[WBS CODE],0)), "") = "", "null", IFERROR(INDEX(WBS_Dictionary!G$2:G$1212, MATCH(Table2[[#This Row],[WBS_ID]], Table26[WBS CODE],0)), "")) -> E540-3020374-D245401 | X80: =IF(IFERROR(INDEX(WBS_Dictionary!H$2:H$1212, MATCH(Table2[[#This Row],[WBS_ID]], Table26[WBS CODE],0)), "") = "", "null", IFERROR(INDEX(WBS_Dictionary!H$2:H$1212, MATCH(Table2[[#This Row],[WBS_ID]], Table26[WBS CODE],0)), "")) -> E540-302037409-D245401 | Y80: =IF(IFERROR(INDEX(WBS_Dictionary!I$2:I$1212, MATCH(Table2[[#This Row],[WBS_ID]], Table26[WBS CODE],0)), "") = "", "null", IFERROR(INDEX(WBS_Dictionary!I$2:I$1212, MATCH(Table2[[#This Row],[WBS_ID]], Table26[WBS CODE],0)), "")) -> E540-30203740903-D245401 | Z80: =IF(IFERROR(INDEX(WBS_Dictionary!J$2:J$1212, MATCH(Table2[[#This Row],[WBS_ID]], Table26[WBS CODE],0)), "") = "", "null", IFERROR(INDEX(WBS_Dictionary!J$2:J$1212, MATCH(Table2[[#This Row],[WBS_ID]], Table26[WBS CODE],0)), "")) -> Surface Facilities Cost | AA80: =IF(IFERROR(INDEX(WBS_Dictionary!K$2:K$1212, MATCH(Table2[[#This Row],[WBS_ID]], Table26[WBS CODE],0)), "") = "", "null", IFERROR(INDEX(WBS_Dictionary!K$2:K$1212, MATCH(Table2[[#This Row],[WBS_ID]], Table26[WBS CODE],0)), "")) -> Conductor Casing Installation & Material | AB80: =IF(IFERROR(INDEX(WBS_Dictionary!L$2:L$1212, MATCH(Table2[[#This Row],[WBS_ID]], Table26[WBS CODE],0)), "") = "", "null", IFERROR(INDEX(WBS_Dictionary!L$2:L$1212, MATCH(Table2[[#This Row],[WBS_ID]], Table26[WBS CODE],0)), "")) -> Services | ... AE80: =IF(IFERROR(INDEX(WBS_Dictionary!O$2:O$1212, MATCH(Table2[[#This Row],[WBS_ID]], Table26[WBS CODE],0)), "") = "", "null", IFERROR(INDEX(WBS_Dictionary!O$2:O$1212, MATCH(Table2[[#This Row],[WBS_ID]], Table26[WBS CODE],0)), "")) -> null
A81: 80 | B81: 04 | C81: Conductor Casing Inst & Mat Well 8 | D81: E540-302037408-D245401 | E81: D245401 | F81: 344287 | G81: USD | H81: 344287 | I81: USD | J81: 0 | K81: USD | L81: 0 | M81: USD | N81: 0 | O81: USD | Q81: X | R81: STAR ENERGY | S81: Production | T81: REL BUDG AVAC // BUDG | U81: =IF(IFERROR(INDEX(WBS_Dictionary!E$2:E$1212, MATCH(Table2[[#This Row],[WBS_ID]], Table26[WBS CODE],0)), "") = "", "null", IFERROR(INDEX(WBS_Dictionary!E$2:E$1212, MATCH(Table2[[#This Row],[WBS_ID]], Table26[WBS CODE],0)), "")) -> E540-30-D245401 | V81: =IF(IFERROR(INDEX(WBS_Dictionary!F$2:F$1212, MATCH(Table2[[#This Row],[WBS_ID]], Table26[WBS CODE],0)), "") = "", "null", IFERROR(INDEX(WBS_Dictionary!F$2:F$1212, MATCH(Table2[[#This Row],[WBS_ID]], Table26[WBS CODE],0)), "")) -> E540-30203-D245401 | W81: =IF(IFERROR(INDEX(WBS_Dictionary!G$2:G$1212, MATCH(Table2[[#This Row],[WBS_ID]], Table26[WBS CODE],0)), "") = "", "null", IFERROR(INDEX(WBS_Dictionary!G$2:G$1212, MATCH(Table2[[#This Row],[WBS_ID]], Table26[WBS CODE],0)), "")) -> E540-3020374-D245401 | X81: =IF(IFERROR(INDEX(WBS_Dictionary!H$2:H$1212, MATCH(Table2[[#This Row],[WBS_ID]], Table26[WBS CODE],0)), "") = "", "null", IFERROR(INDEX(WBS_Dictionary!H$2:H$1212, MATCH(Table2[[#This Row],[WBS_ID]], Table26[WBS CODE],0)), "")) -> E540-302037408-D245401 | Y81: =IF(IFERROR(INDEX(WBS_Dictionary!I$2:I$1212, MATCH(Table2[[#This Row],[WBS_ID]], Table26[WBS CODE],0)), "") = "", "null", IFERROR(INDEX(WBS_Dictionary!I$2:I$1212, MATCH(Table2[[#This Row],[WBS_ID]], Table26[WBS CODE],0)), "")) -> null | Z81: =IF(IFERROR(INDEX(WBS_Dictionary!J$2:J$1212, MATCH(Table2[[#This Row],[WBS_ID]], Table26[WBS CODE],0)), "") = "", "null", IFERROR(INDEX(WBS_Dictionary!J$2:J$1212, MATCH(Table2[[#This Row],[WBS_ID]], Table26[WBS CODE],0)), "")) -> Surface Facilities Cost | AA81: =IF(IFERROR(INDEX(WBS_Dictionary!K$2:K$1212, MATCH(Table2[[#This Row],[WBS_ID]], Table26[WBS CODE],0)), "") = "", "null", IFERROR(INDEX(WBS_Dictionary!K$2:K$1212, MATCH(Table2[[#This Row],[WBS_ID]], Table26[WBS CODE],0)), "")) -> Conductor Casing Installation & Material | AB81: =IF(IFERROR(INDEX(WBS_Dictionary!L$2:L$1212, MATCH(Table2[[#This Row],[WBS_ID]], Table26[WBS CODE],0)), "") = "", "null", IFERROR(INDEX(WBS_Dictionary!L$2:L$1212, MATCH(Table2[[#This Row],[WBS_ID]], Table26[WBS CODE],0)), "")) -> Conductor Casing Installation & Material | ... AE81: =IF(IFERROR(INDEX(WBS_Dictionary!O$2:O$1212, MATCH(Table2[[#This Row],[WBS_ID]], Table26[WBS CODE],0)), "") = "", "null", IFERROR(INDEX(WBS_Dictionary!O$2:O$1212, MATCH(Table2[[#This Row],[WBS_ID]], Table26[WBS CODE],0)), "")) -> null
A82: 81 | B82: 05 | C82: Cdtr Csg Material Well 8 | D82: E540-30203740860-D245401 | E82: D245401 | F82: 0 | G82: USD | H82: 0 | I82: USD | J82: 0 | K82: USD | L82: 0 | M82: USD | N82: 0 | O82: USD | Q82: X | R82: STAR ENERGY | S82: Production | T82: REL AVAC SETC // BUDG | U82: =IF(IFERROR(INDEX(WBS_Dictionary!E$2:E$1212, MATCH(Table2[[#This Row],[WBS_ID]], Table26[WBS CODE],0)), "") = "", "null", IFERROR(INDEX(WBS_Dictionary!E$2:E$1212, MATCH(Table2[[#This Row],[WBS_ID]], Table26[WBS CODE],0)), "")) -> E540-30-D245401 | V82: =IF(IFERROR(INDEX(WBS_Dictionary!F$2:F$1212, MATCH(Table2[[#This Row],[WBS_ID]], Table26[WBS CODE],0)), "") = "", "null", IFERROR(INDEX(WBS_Dictionary!F$2:F$1212, MATCH(Table2[[#This Row],[WBS_ID]], Table26[WBS CODE],0)), "")) -> E540-30203-D245401 | W82: =IF(IFERROR(INDEX(WBS_Dictionary!G$2:G$1212, MATCH(Table2[[#This Row],[WBS_ID]], Table26[WBS CODE],0)), "") = "", "null", IFERROR(INDEX(WBS_Dictionary!G$2:G$1212, MATCH(Table2[[#This Row],[WBS_ID]], Table26[WBS CODE],0)), "")) -> E540-3020374-D245401 | X82: =IF(IFERROR(INDEX(WBS_Dictionary!H$2:H$1212, MATCH(Table2[[#This Row],[WBS_ID]], Table26[WBS CODE],0)), "") = "", "null", IFERROR(INDEX(WBS_Dictionary!H$2:H$1212, MATCH(Table2[[#This Row],[WBS_ID]], Table26[WBS CODE],0)), "")) -> E540-302037408-D245401 | Y82: =IF(IFERROR(INDEX(WBS_Dictionary!I$2:I$1212, MATCH(Table2[[#This Row],[WBS_ID]], Table26[WBS CODE],0)), "") = "", "null", IFERROR(INDEX(WBS_Dictionary!I$2:I$1212, MATCH(Table2[[#This Row],[WBS_ID]], Table26[WBS CODE],0)), "")) -> E540-30203740860-D245401 | Z82: =IF(IFERROR(INDEX(WBS_Dictionary!J$2:J$1212, MATCH(Table2[[#This Row],[WBS_ID]], Table26[WBS CODE],0)), "") = "", "null", IFERROR(INDEX(WBS_Dictionary!J$2:J$1212, MATCH(Table2[[#This Row],[WBS_ID]], Table26[WBS CODE],0)), "")) -> Surface Facilities Cost | AA82: =IF(IFERROR(INDEX(WBS_Dictionary!K$2:K$1212, MATCH(Table2[[#This Row],[WBS_ID]], Table26[WBS CODE],0)), "") = "", "null", IFERROR(INDEX(WBS_Dictionary!K$2:K$1212, MATCH(Table2[[#This Row],[WBS_ID]], Table26[WBS CODE],0)), "")) -> Conductor Casing Installation & Material | AB82: =IF(IFERROR(INDEX(WBS_Dictionary!L$2:L$1212, MATCH(Table2[[#This Row],[WBS_ID]], Table26[WBS CODE],0)), "") = "", "null", IFERROR(INDEX(WBS_Dictionary!L$2:L$1212, MATCH(Table2[[#This Row],[WBS_ID]], Table26[WBS CODE],0)), "")) -> Material | ... AE82: =IF(IFERROR(INDEX(WBS_Dictionary!O$2:O$1212, MATCH(Table2[[#This Row],[WBS_ID]], Table26[WBS CODE],0)), "") = "", "null", IFERROR(INDEX(WBS_Dictionary!O$2:O$1212, MATCH(Table2[[#This Row],[WBS_ID]], Table26[WBS CODE],0)), "")) -> null
A83: 82 | B83: 05 | C83: Cdtr Csg Service Well 8 | D83: E540-30203740803-D245401 | E83: D245401 | F83: 0 | G83: USD | H83: 0 | I83: USD | J83: 0 | K83: USD | L83: 0 | M83: USD | N83: 0 | O83: USD | Q83: X | R83: STAR ENERGY | S83: Production | T83: REL AVAC SETC // BUDG | U83: =IF(IFERROR(INDEX(WBS_Dictionary!E$2:E$1212, MATCH(Table2[[#This Row],[WBS_ID]], Table26[WBS CODE],0)), "") = "", "null", IFERROR(INDEX(WBS_Dictionary!E$2:E$1212, MATCH(Table2[[#This Row],[WBS_ID]], Table26[WBS CODE],0)), "")) -> E540-30-D245401 | V83: =IF(IFERROR(INDEX(WBS_Dictionary!F$2:F$1212, MATCH(Table2[[#This Row],[WBS_ID]], Table26[WBS CODE],0)), "") = "", "null", IFERROR(INDEX(WBS_Dictionary!F$2:F$1212, MATCH(Table2[[#This Row],[WBS_ID]], Table26[WBS CODE],0)), "")) -> E540-30203-D245401 | W83: =IF(IFERROR(INDEX(WBS_Dictionary!G$2:G$1212, MATCH(Table2[[#This Row],[WBS_ID]], Table26[WBS CODE],0)), "") = "", "null", IFERROR(INDEX(WBS_Dictionary!G$2:G$1212, MATCH(Table2[[#This Row],[WBS_ID]], Table26[WBS CODE],0)), "")) -> E540-3020374-D245401 | X83: =IF(IFERROR(INDEX(WBS_Dictionary!H$2:H$1212, MATCH(Table2[[#This Row],[WBS_ID]], Table26[WBS CODE],0)), "") = "", "null", IFERROR(INDEX(WBS_Dictionary!H$2:H$1212, MATCH(Table2[[#This Row],[WBS_ID]], Table26[WBS CODE],0)), "")) -> E540-302037408-D245401 | Y83: =IF(IFERROR(INDEX(WBS_Dictionary!I$2:I$1212, MATCH(Table2[[#This Row],[WBS_ID]], Table26[WBS CODE],0)), "") = "", "null", IFERROR(INDEX(WBS_Dictionary!I$2:I$1212, MATCH(Table2[[#This Row],[WBS_ID]], Table26[WBS CODE],0)), "")) -> E540-30203740803-D245401 | Z83: =IF(IFERROR(INDEX(WBS_Dictionary!J$2:J$1212, MATCH(Table2[[#This Row],[WBS_ID]], Table26[WBS CODE],0)), "") = "", "null", IFERROR(INDEX(WBS_Dictionary!J$2:J$1212, MATCH(Table2[[#This Row],[WBS_ID]], Table26[WBS CODE],0)), "")) -> Surface Facilities Cost | AA83: =IF(IFERROR(INDEX(WBS_Dictionary!K$2:K$1212, MATCH(Table2[[#This Row],[WBS_ID]], Table26[WBS CODE],0)), "") = "", "null", IFERROR(INDEX(WBS_Dictionary!K$2:K$1212, MATCH(Table2[[#This Row],[WBS_ID]], Table26[WBS CODE],0)), "")) -> Conductor Casing Installation & Material | AB83: =IF(IFERROR(INDEX(WBS_Dictionary!L$2:L$1212, MATCH(Table2[[#This Row],[WBS_ID]], Table26[WBS CODE],0)), "") = "", "null", IFERROR(INDEX(WBS_Dictionary!L$2:L$1212, MATCH(Table2[[#This Row],[WBS_ID]], Table26[WBS CODE],0)), "")) -> Services | ... AE83: =IF(IFERROR(INDEX(WBS_Dictionary!O$2:O$1212, MATCH(Table2[[#This Row],[WBS_ID]], Table26[WBS CODE],0)), "") = "", "null", IFERROR(INDEX(WBS_Dictionary!O$2:O$1212, MATCH(Table2[[#This Row],[WBS_ID]], Table26[WBS CODE],0)), "")) -> null
A84: 83 | B84: 04 | C84: Conductor Casing Inst & Mat Well 7 | D84: E540-302037407-D245401 | E84: D245401 | F84: 321865 | G84: USD | H84: 321865 | I84: USD | J84: 0 | K84: USD | L84: 0 | M84: USD | N84: 0 | O84: USD | Q84: X | R84: STAR ENERGY | S84: Production | T84: REL BUDG AVAC // BUDG | U84: =IF(IFERROR(INDEX(WBS_Dictionary!E$2:E$1212, MATCH(Table2[[#This Row],[WBS_ID]], Table26[WBS CODE],0)), "") = "", "null", IFERROR(INDEX(WBS_Dictionary!E$2:E$1212, MATCH(Table2[[#This Row],[WBS_ID]], Table26[WBS CODE],0)), "")) -> E540-30-D245401 | V84: =IF(IFERROR(INDEX(WBS_Dictionary!F$2:F$1212, MATCH(Table2[[#This Row],[WBS_ID]], Table26[WBS CODE],0)), "") = "", "null", IFERROR(INDEX(WBS_Dictionary!F$2:F$1212, MATCH(Table2[[#This Row],[WBS_ID]], Table26[WBS CODE],0)), "")) -> E540-30203-D245401 | W84: =IF(IFERROR(INDEX(WBS_Dictionary!G$2:G$1212, MATCH(Table2[[#This Row],[WBS_ID]], Table26[WBS CODE],0)), "") = "", "null", IFERROR(INDEX(WBS_Dictionary!G$2:G$1212, MATCH(Table2[[#This Row],[WBS_ID]], Table26[WBS CODE],0)), "")) -> E540-3020374-D245401 | X84: =IF(IFERROR(INDEX(WBS_Dictionary!H$2:H$1212, MATCH(Table2[[#This Row],[WBS_ID]], Table26[WBS CODE],0)), "") = "", "null", IFERROR(INDEX(WBS_Dictionary!H$2:H$1212, MATCH(Table2[[#This Row],[WBS_ID]], Table26[WBS CODE],0)), "")) -> E540-302037407-D245401 | Y84: =IF(IFERROR(INDEX(WBS_Dictionary!I$2:I$1212, MATCH(Table2[[#This Row],[WBS_ID]], Table26[WBS CODE],0)), "") = "", "null", IFERROR(INDEX(WBS_Dictionary!I$2:I$1212, MATCH(Table2[[#This Row],[WBS_ID]], Table26[WBS CODE],0)), "")) -> null | Z84: =IF(IFERROR(INDEX(WBS_Dictionary!J$2:J$1212, MATCH(Table2[[#This Row],[WBS_ID]], Table26[WBS CODE],0)), "") = "", "null", IFERROR(INDEX(WBS_Dictionary!J$2:J$1212, MATCH(Table2[[#This Row],[WBS_ID]], Table26[WBS CODE],0)), "")) -> Surface Facilities Cost | AA84: =IF(IFERROR(INDEX(WBS_Dictionary!K$2:K$1212, MATCH(Table2[[#This Row],[WBS_ID]], Table26[WBS CODE],0)), "") = "", "null", IFERROR(INDEX(WBS_Dictionary!K$2:K$1212, MATCH(Table2[[#This Row],[WBS_ID]], Table26[WBS CODE],0)), "")) -> Conductor Casing Installation & Material | AB84: =IF(IFERROR(INDEX(WBS_Dictionary!L$2:L$1212, MATCH(Table2[[#This Row],[WBS_ID]], Table26[WBS CODE],0)), "") = "", "null", IFERROR(INDEX(WBS_Dictionary!L$2:L$1212, MATCH(Table2[[#This Row],[WBS_ID]], Table26[WBS CODE],0)), "")) -> Conductor Casing Installation & Material | ... AE84: =IF(IFERROR(INDEX(WBS_Dictionary!O$2:O$1212, MATCH(Table2[[#This Row],[WBS_ID]], Table26[WBS CODE],0)), "") = "", "null", IFERROR(INDEX(WBS_Dictionary!O$2:O$1212, MATCH(Table2[[#This Row],[WBS_ID]], Table26[WBS CODE],0)), "")) -> null
A85: 84 | B85: 05 | C85: Cdtr Csg Material Well 7 | D85: E540-30203740760-D245401 | E85: D245401 | F85: 0 | G85: USD | H85: 0 | I85: USD | J85: 0 | K85: USD | L85: 0 | M85: USD | N85: 0 | O85: USD | Q85: X | R85: STAR ENERGY | S85: Production | T85: REL AVAC SETC // BUDG | U85: =IF(IFERROR(INDEX(WBS_Dictionary!E$2:E$1212, MATCH(Table2[[#This Row],[WBS_ID]], Table26[WBS CODE],0)), "") = "", "null", IFERROR(INDEX(WBS_Dictionary!E$2:E$1212, MATCH(Table2[[#This Row],[WBS_ID]], Table26[WBS CODE],0)), "")) -> E540-30-D245401 | V85: =IF(IFERROR(INDEX(WBS_Dictionary!F$2:F$1212, MATCH(Table2[[#This Row],[WBS_ID]], Table26[WBS CODE],0)), "") = "", "null", IFERROR(INDEX(WBS_Dictionary!F$2:F$1212, MATCH(Table2[[#This Row],[WBS_ID]], Table26[WBS CODE],0)), "")) -> E540-30203-D245401 | W85: =IF(IFERROR(INDEX(WBS_Dictionary!G$2:G$1212, MATCH(Table2[[#This Row],[WBS_ID]], Table26[WBS CODE],0)), "") = "", "null", IFERROR(INDEX(WBS_Dictionary!G$2:G$1212, MATCH(Table2[[#This Row],[WBS_ID]], Table26[WBS CODE],0)), "")) -> E540-3020374-D245401 | X85: =IF(IFERROR(INDEX(WBS_Dictionary!H$2:H$1212, MATCH(Table2[[#This Row],[WBS_ID]], Table26[WBS CODE],0)), "") = "", "null", IFERROR(INDEX(WBS_Dictionary!H$2:H$1212, MATCH(Table2[[#This Row],[WBS_ID]], Table26[WBS CODE],0)), "")) -> E540-302037407-D245401 | Y85: =IF(IFERROR(INDEX(WBS_Dictionary!I$2:I$1212, MATCH(Table2[[#This Row],[WBS_ID]], Table26[WBS CODE],0)), "") = "", "null", IFERROR(INDEX(WBS_Dictionary!I$2:I$1212, MATCH(Table2[[#This Row],[WBS_ID]], Table26[WBS CODE],0)), "")) -> E540-30203740760-D245401 | Z85: =IF(IFERROR(INDEX(WBS_Dictionary!J$2:J$1212, MATCH(Table2[[#This Row],[WBS_ID]], Table26[WBS CODE],0)), "") = "", "null", IFERROR(INDEX(WBS_Dictionary!J$2:J$1212, MATCH(Table2[[#This Row],[WBS_ID]], Table26[WBS CODE],0)), "")) -> Surface Facilities Cost | AA85: =IF(IFERROR(INDEX(WBS_Dictionary!K$2:K$1212, MATCH(Table2[[#This Row],[WBS_ID]], Table26[WBS CODE],0)), "") = "", "null", IFERROR(INDEX(WBS_Dictionary!K$2:K$1212, MATCH(Table2[[#This Row],[WBS_ID]], Table26[WBS CODE],0)), "")) -> Conductor Casing Installation & Material | AB85: =IF(IFERROR(INDEX(WBS_Dictionary!L$2:L$1212, MATCH(Table2[[#This Row],[WBS_ID]], Table26[WBS CODE],0)), "") = "", "null", IFERROR(INDEX(WBS_Dictionary!L$2:L$1212, MATCH(Table2[[#This Row],[WBS_ID]], Table26[WBS CODE],0)), "")) -> Material | ... AE85: =IF(IFERROR(INDEX(WBS_Dictionary!O$2:O$1212, MATCH(Table2[[#This Row],[WBS_ID]], Table26[WBS CODE],0)), "") = "", "null", IFERROR(INDEX(WBS_Dictionary!O$2:O$1212, MATCH(Table2[[#This Row],[WBS_ID]], Table26[WBS CODE],0)), "")) -> null
A86: 85 | B86: 05 | C86: Cdtr Csg Service Well 7 | D86: E540-30203740703-D245401 | E86: D245401 | F86: 0 | G86: USD | H86: 0 | I86: USD | J86: 0 | K86: USD | L86: 0 | M86: USD | N86: 0 | O86: USD | Q86: X | R86: STAR ENERGY | S86: Production | T86: REL AVAC SETC // BUDG | U86: =IF(IFERROR(INDEX(WBS_Dictionary!E$2:E$1212, MATCH(Table2[[#This Row],[WBS_ID]], Table26[WBS CODE],0)), "") = "", "null", IFERROR(INDEX(WBS_Dictionary!E$2:E$1212, MATCH(Table2[[#This Row],[WBS_ID]], Table26[WBS CODE],0)), "")) -> E540-30-D245401 | V86: =IF(IFERROR(INDEX(WBS_Dictionary!F$2:F$1212, MATCH(Table2[[#This Row],[WBS_ID]], Table26[WBS CODE],0)), "") = "", "null", IFERROR(INDEX(WBS_Dictionary!F$2:F$1212, MATCH(Table2[[#This Row],[WBS_ID]], Table26[WBS CODE],0)), "")) -> E540-30203-D245401 | W86: =IF(IFERROR(INDEX(WBS_Dictionary!G$2:G$1212, MATCH(Table2[[#This Row],[WBS_ID]], Table26[WBS CODE],0)), "") = "", "null", IFERROR(INDEX(WBS_Dictionary!G$2:G$1212, MATCH(Table2[[#This Row],[WBS_ID]], Table26[WBS CODE],0)), "")) -> E540-3020374-D245401 | X86: =IF(IFERROR(INDEX(WBS_Dictionary!H$2:H$1212, MATCH(Table2[[#This Row],[WBS_ID]], Table26[WBS CODE],0)), "") = "", "null", IFERROR(INDEX(WBS_Dictionary!H$2:H$1212, MATCH(Table2[[#This Row],[WBS_ID]], Table26[WBS CODE],0)), "")) -> E540-302037407-D245401 | Y86: =IF(IFERROR(INDEX(WBS_Dictionary!I$2:I$1212, MATCH(Table2[[#This Row],[WBS_ID]], Table26[WBS CODE],0)), "") = "", "null", IFERROR(INDEX(WBS_Dictionary!I$2:I$1212, MATCH(Table2[[#This Row],[WBS_ID]], Table26[WBS CODE],0)), "")) -> E540-30203740703-D245401 | Z86: =IF(IFERROR(INDEX(WBS_Dictionary!J$2:J$1212, MATCH(Table2[[#This Row],[WBS_ID]], Table26[WBS CODE],0)), "") = "", "null", IFERROR(INDEX(WBS_Dictionary!J$2:J$1212, MATCH(Table2[[#This Row],[WBS_ID]], Table26[WBS CODE],0)), "")) -> Surface Facilities Cost | AA86: =IF(IFERROR(INDEX(WBS_Dictionary!K$2:K$1212, MATCH(Table2[[#This Row],[WBS_ID]], Table26[WBS CODE],0)), "") = "", "null", IFERROR(INDEX(WBS_Dictionary!K$2:K$1212, MATCH(Table2[[#This Row],[WBS_ID]], Table26[WBS CODE],0)), "")) -> Conductor Casing Installation & Material | AB86: =IF(IFERROR(INDEX(WBS_Dictionary!L$2:L$1212, MATCH(Table2[[#This Row],[WBS_ID]], Table26[WBS CODE],0)), "") = "", "null", IFERROR(INDEX(WBS_Dictionary!L$2:L$1212, MATCH(Table2[[#This Row],[WBS_ID]], Table26[WBS CODE],0)), "")) -> Services | ... AE86: =IF(IFERROR(INDEX(WBS_Dictionary!O$2:O$1212, MATCH(Table2[[#This Row],[WBS_ID]], Table26[WBS CODE],0)), "") = "", "null", IFERROR(INDEX(WBS_Dictionary!O$2:O$1212, MATCH(Table2[[#This Row],[WBS_ID]], Table26[WBS CODE],0)), "")) -> null
A87: 86 | B87: 04 | C87: Conductor Casing Inst & Mat Well 6 | D87: E540-302037406-D245401 | E87: D245401 | F87: 331778.43 | G87: USD | H87: 331778.43 | I87: USD | J87: 0 | K87: USD | L87: 0 | M87: USD | N87: 288015.57 | O87: USD | Q87: X | R87: STAR ENERGY | S87: Production | T87: REL BUDG AVAC // BUDG | U87: =IF(IFERROR(INDEX(WBS_Dictionary!E$2:E$1212, MATCH(Table2[[#This Row],[WBS_ID]], Table26[WBS CODE],0)), "") = "", "null", IFERROR(INDEX(WBS_Dictionary!E$2:E$1212, MATCH(Table2[[#This Row],[WBS_ID]], Table26[WBS CODE],0)), "")) -> E540-30-D245401 | V87: =IF(IFERROR(INDEX(WBS_Dictionary!F$2:F$1212, MATCH(Table2[[#This Row],[WBS_ID]], Table26[WBS CODE],0)), "") = "", "null", IFERROR(INDEX(WBS_Dictionary!F$2:F$1212, MATCH(Table2[[#This Row],[WBS_ID]], Table26[WBS CODE],0)), "")) -> E540-30203-D245401 | W87: =IF(IFERROR(INDEX(WBS_Dictionary!G$2:G$1212, MATCH(Table2[[#This Row],[WBS_ID]], Table26[WBS CODE],0)), "") = "", "null", IFERROR(INDEX(WBS_Dictionary!G$2:G$1212, MATCH(Table2[[#This Row],[WBS_ID]], Table26[WBS CODE],0)), "")) -> E540-3020374-D245401 | X87: =IF(IFERROR(INDEX(WBS_Dictionary!H$2:H$1212, MATCH(Table2[[#This Row],[WBS_ID]], Table26[WBS CODE],0)), "") = "", "null", IFERROR(INDEX(WBS_Dictionary!H$2:H$1212, MATCH(Table2[[#This Row],[WBS_ID]], Table26[WBS CODE],0)), "")) -> E540-302037406-D245401 | Y87: =IF(IFERROR(INDEX(WBS_Dictionary!I$2:I$1212, MATCH(Table2[[#This Row],[WBS_ID]], Table26[WBS CODE],0)), "") = "", "null", IFERROR(INDEX(WBS_Dictionary!I$2:I$1212, MATCH(Table2[[#This Row],[WBS_ID]], Table26[WBS CODE],0)), "")) -> null | Z87: =IF(IFERROR(INDEX(WBS_Dictionary!J$2:J$1212, MATCH(Table2[[#This Row],[WBS_ID]], Table26[WBS CODE],0)), "") = "", "null", IFERROR(INDEX(WBS_Dictionary!J$2:J$1212, MATCH(Table2[[#This Row],[WBS_ID]], Table26[WBS CODE],0)), "")) -> Surface Facilities Cost | AA87: =IF(IFERROR(INDEX(WBS_Dictionary!K$2:K$1212, MATCH(Table2[[#This Row],[WBS_ID]], Table26[WBS CODE],0)), "") = "", "null", IFERROR(INDEX(WBS_Dictionary!K$2:K$1212, MATCH(Table2[[#This Row],[WBS_ID]], Table26[WBS CODE],0)), "")) -> Conductor Casing Installation & Material | AB87: =IF(IFERROR(INDEX(WBS_Dictionary!L$2:L$1212, MATCH(Table2[[#This Row],[WBS_ID]], Table26[WBS CODE],0)), "") = "", "null", IFERROR(INDEX(WBS_Dictionary!L$2:L$1212, MATCH(Table2[[#This Row],[WBS_ID]], Table26[WBS CODE],0)), "")) -> Conductor Casing Installation & Material | ... AE87: =IF(IFERROR(INDEX(WBS_Dictionary!O$2:O$1212, MATCH(Table2[[#This Row],[WBS_ID]], Table26[WBS CODE],0)), "") = "", "null", IFERROR(INDEX(WBS_Dictionary!O$2:O$1212, MATCH(Table2[[#This Row],[WBS_ID]], Table26[WBS CODE],0)), "")) -> null
A88: 87 | B88: 05 | C88: Cdtr Csg Material Well 6 | D88: E540-30203740660-D245401 | E88: D245401 | F88: 0 | G88: USD | H88: 0 | I88: USD | J88: 0 | K88: USD | L88: 0 | M88: USD | N88: 67824.48 | O88: USD | Q88: X | R88: STAR ENERGY | S88: Production | T88: REL AVAC SETC // BUDG | U88: =IF(IFERROR(INDEX(WBS_Dictionary!E$2:E$1212, MATCH(Table2[[#This Row],[WBS_ID]], Table26[WBS CODE],0)), "") = "", "null", IFERROR(INDEX(WBS_Dictionary!E$2:E$1212, MATCH(Table2[[#This Row],[WBS_ID]], Table26[WBS CODE],0)), "")) -> E540-30-D245401 | V88: =IF(IFERROR(INDEX(WBS_Dictionary!F$2:F$1212, MATCH(Table2[[#This Row],[WBS_ID]], Table26[WBS CODE],0)), "") = "", "null", IFERROR(INDEX(WBS_Dictionary!F$2:F$1212, MATCH(Table2[[#This Row],[WBS_ID]], Table26[WBS CODE],0)), "")) -> E540-30203-D245401 | W88: =IF(IFERROR(INDEX(WBS_Dictionary!G$2:G$1212, MATCH(Table2[[#This Row],[WBS_ID]], Table26[WBS CODE],0)), "") = "", "null", IFERROR(INDEX(WBS_Dictionary!G$2:G$1212, MATCH(Table2[[#This Row],[WBS_ID]], Table26[WBS CODE],0)), "")) -> E540-3020374-D245401 | X88: =IF(IFERROR(INDEX(WBS_Dictionary!H$2:H$1212, MATCH(Table2[[#This Row],[WBS_ID]], Table26[WBS CODE],0)), "") = "", "null", IFERROR(INDEX(WBS_Dictionary!H$2:H$1212, MATCH(Table2[[#This Row],[WBS_ID]], Table26[WBS CODE],0)), "")) -> E540-302037406-D245401 | Y88: =IF(IFERROR(INDEX(WBS_Dictionary!I$2:I$1212, MATCH(Table2[[#This Row],[WBS_ID]], Table26[WBS CODE],0)), "") = "", "null", IFERROR(INDEX(WBS_Dictionary!I$2:I$1212, MATCH(Table2[[#This Row],[WBS_ID]], Table26[WBS CODE],0)), "")) -> E540-30203740660-D245401 | Z88: =IF(IFERROR(INDEX(WBS_Dictionary!J$2:J$1212, MATCH(Table2[[#This Row],[WBS_ID]], Table26[WBS CODE],0)), "") = "", "null", IFERROR(INDEX(WBS_Dictionary!J$2:J$1212, MATCH(Table2[[#This Row],[WBS_ID]], Table26[WBS CODE],0)), "")) -> Surface Facilities Cost | AA88: =IF(IFERROR(INDEX(WBS_Dictionary!K$2:K$1212, MATCH(Table2[[#This Row],[WBS_ID]], Table26[WBS CODE],0)), "") = "", "null", IFERROR(INDEX(WBS_Dictionary!K$2:K$1212, MATCH(Table2[[#This Row],[WBS_ID]], Table26[WBS CODE],0)), "")) -> Conductor Casing Installation & Material | AB88: =IF(IFERROR(INDEX(WBS_Dictionary!L$2:L$1212, MATCH(Table2[[#This Row],[WBS_ID]], Table26[WBS CODE],0)), "") = "", "null", IFERROR(INDEX(WBS_Dictionary!L$2:L$1212, MATCH(Table2[[#This Row],[WBS_ID]], Table26[WBS CODE],0)), "")) -> Material | ... AE88: =IF(IFERROR(INDEX(WBS_Dictionary!O$2:O$1212, MATCH(Table2[[#This Row],[WBS_ID]], Table26[WBS CODE],0)), "") = "", "null", IFERROR(INDEX(WBS_Dictionary!O$2:O$1212, MATCH(Table2[[#This Row],[WBS_ID]], Table26[WBS CODE],0)), "")) -> null
... A116: 115 | B116: 05 | C116: Drilling Facilities Support | D116: E540-30129146321-D245401 | E116: D245401 | F116: 0 | G116: USD | H116: 0 | I116: USD | J116: 0 | K116: USD | L116: 123275.73 | M116: USD | N116: 475455.58 | O116: USD | Q116: X | R116: STAR ENERGY | S116: Production | T116: REL AVAC SETC // BUDG | U116: =IF(IFERROR(INDEX(WBS_Dictionary!E$2:E$1212, MATCH(Table2[[#This Row],[WBS_ID]], Table26[WBS CODE],0)), "") = "", "null", IFERROR(INDEX(WBS_Dictionary!E$2:E$1212, MATCH(Table2[[#This Row],[WBS_ID]], Table26[WBS CODE],0)), "")) -> E540-30-D245401 | V116: =IF(IFERROR(INDEX(WBS_Dictionary!F$2:F$1212, MATCH(Table2[[#This Row],[WBS_ID]], Table26[WBS CODE],0)), "") = "", "null", IFERROR(INDEX(WBS_Dictionary!F$2:F$1212, MATCH(Table2[[#This Row],[WBS_ID]], Table26[WBS CODE],0)), "")) -> E540-30129-D245401 | W116: =IF(IFERROR(INDEX(WBS_Dictionary!G$2:G$1212, MATCH(Table2[[#This Row],[WBS_ID]], Table26[WBS CODE],0)), "") = "", "null", IFERROR(INDEX(WBS_Dictionary!G$2:G$1212, MATCH(Table2[[#This Row],[WBS_ID]], Table26[WBS CODE],0)), "")) -> E540-3012914-D245401 | X116: =IF(IFERROR(INDEX(WBS_Dictionary!H$2:H$1212, MATCH(Table2[[#This Row],[WBS_ID]], Table26[WBS CODE],0)), "") = "", "null", IFERROR(INDEX(WBS_Dictionary!H$2:H$1212, MATCH(Table2[[#This Row],[WBS_ID]], Table26[WBS CODE],0)), "")) -> E540-301291463-D245401 | Y116: =IF(IFERROR(INDEX(WBS_Dictionary!I$2:I$1212, MATCH(Table2[[#This Row],[WBS_ID]], Table26[WBS CODE],0)), "") = "", "null", IFERROR(INDEX(WBS_Dictionary!I$2:I$1212, MATCH(Table2[[#This Row],[WBS_ID]], Table26[WBS CODE],0)), "")) -> E540-30129146321-D245401 | Z116: =IF(IFERROR(INDEX(WBS_Dictionary!J$2:J$1212, MATCH(Table2[[#This Row],[WBS_ID]], Table26[WBS CODE],0)), "") = "", "null", IFERROR(INDEX(WBS_Dictionary!J$2:J$1212, MATCH(Table2[[#This Row],[WBS_ID]], Table26[WBS CODE],0)), "")) -> Support Cost | AA116: =IF(IFERROR(INDEX(WBS_Dictionary!K$2:K$1212, MATCH(Table2[[#This Row],[WBS_ID]], Table26[WBS CODE],0)), "") = "", "null", IFERROR(INDEX(WBS_Dictionary!K$2:K$1212, MATCH(Table2[[#This Row],[WBS_ID]], Table26[WBS CODE],0)), "")) -> Drilling Facilities Support | AB116: =IF(IFERROR(INDEX(WBS_Dictionary!L$2:L$1212, MATCH(Table2[[#This Row],[WBS_ID]], Table26[WBS CODE],0)), "") = "", "null", IFERROR(INDEX(WBS_Dictionary!L$2:L$1212, MATCH(Table2[[#This Row],[WBS_ID]], Table26[WBS CODE],0)), "")) -> Drilling Facilities Support | ... AE116: =IF(IFERROR(INDEX(WBS_Dictionary!O$2:O$1212, MATCH(Table2[[#This Row],[WBS_ID]], Table26[WBS CODE],0)), "") = "", "null", IFERROR(INDEX(WBS_Dictionary!O$2:O$1212, MATCH(Table2[[#This Row],[WBS_ID]], Table26[WBS CODE],0)), "")) -> null
A117: 116 | B117: 06 | C117: Pemasangan lampu penerangan luar dan pen | D117: 40000007089 | F117: 0 | G117: USD | H117: 0 | I117: USD | J117: 0 | K117: USD | L117: 0 | M117: USD | N117: 3291.41 | O117: USD | T117: REL PCNF CSER GMPS MSPT PRC SETC // RDEX WMTR | U117: =IF(IFERROR(INDEX(WBS_Dictionary!E$2:E$1212, MATCH(Table2[[#This Row],[WBS_ID]], Table26[WBS CODE],0)), "") = "", "null", IFERROR(INDEX(WBS_Dictionary!E$2:E$1212, MATCH(Table2[[#This Row],[WBS_ID]], Table26[WBS CODE],0)), "")) -> null | V117: =IF(IFERROR(INDEX(WBS_Dictionary!F$2:F$1212, MATCH(Table2[[#This Row],[WBS_ID]], Table26[WBS CODE],0)), "") = "", "null", IFERROR(INDEX(WBS_Dictionary!F$2:F$1212, MATCH(Table2[[#This Row],[WBS_ID]], Table26[WBS CODE],0)), "")) -> null | W117: =IF(IFERROR(INDEX(WBS_Dictionary!G$2:G$1212, MATCH(Table2[[#This Row],[WBS_ID]], Table26[WBS CODE],0)), "") = "", "null", IFERROR(INDEX(WBS_Dictionary!G$2:G$1212, MATCH(Table2[[#This Row],[WBS_ID]], Table26[WBS CODE],0)), "")) -> null | X117: =IF(IFERROR(INDEX(WBS_Dictionary!H$2:H$1212, MATCH(Table2[[#This Row],[WBS_ID]], Table26[WBS CODE],0)), "") = "", "null", IFERROR(INDEX(WBS_Dictionary!H$2:H$1212, MATCH(Table2[[#This Row],[WBS_ID]], Table26[WBS CODE],0)), "")) -> null | Y117: =IF(IFERROR(INDEX(WBS_Dictionary!I$2:I$1212, MATCH(Table2[[#This Row],[WBS_ID]], Table26[WBS CODE],0)), "") = "", "null", IFERROR(INDEX(WBS_Dictionary!I$2:I$1212, MATCH(Table2[[#This Row],[WBS_ID]], Table26[WBS CODE],0)), "")) -> null | Z117: =IF(IFERROR(INDEX(WBS_Dictionary!J$2:J$1212, MATCH(Table2[[#This Row],[WBS_ID]], Table26[WBS CODE],0)), "") = "", "null", IFERROR(INDEX(WBS_Dictionary!J$2:J$1212, MATCH(Table2[[#This Row],[WBS_ID]], Table26[WBS CODE],0)), "")) -> null | AA117: =IF(IFERROR(INDEX(WBS_Dictionary!K$2:K$1212, MATCH(Table2[[#This Row],[WBS_ID]], Table26[WBS CODE],0)), "") = "", "null", IFERROR(INDEX(WBS_Dictionary!K$2:K$1212, MATCH(Table2[[#This Row],[WBS_ID]], Table26[WBS CODE],0)), "")) -> null | AB117: =IF(IFERROR(INDEX(WBS_Dictionary!L$2:L$1212, MATCH(Table2[[#This Row],[WBS_ID]], Table26[WBS CODE],0)), "") = "", "null", IFERROR(INDEX(WBS_Dictionary!L$2:L$1212, MATCH(Table2[[#This Row],[WBS_ID]], Table26[WBS CODE],0)), "")) -> null | ... AE117: =IF(IFERROR(INDEX(WBS_Dictionary!O$2:O$1212, MATCH(Table2[[#This Row],[WBS_ID]], Table26[WBS CODE],0)), "") = "", "null", IFERROR(INDEX(WBS_Dictionary!O$2:O$1212, MATCH(Table2[[#This Row],[WBS_ID]], Table26[WBS CODE],0)), "")) -> null
A118: 117 | B118: 07 | C118: Persiapan material | D118: 40000007089 0010 | F118: 0 | G118: USD | H118: 0 | I118: USD | J118: 0 | K118: USD | L118: 0 | M118: USD | N118: 0 | O118: USD | U118: =IF(IFERROR(INDEX(WBS_Dictionary!E$2:E$1212, MATCH(Table2[[#This Row],[WBS_ID]], Table26[WBS CODE],0)), "") = "", "null", IFERROR(INDEX(WBS_Dictionary!E$2:E$1212, MATCH(Table2[[#This Row],[WBS_ID]], Table26[WBS CODE],0)), "")) -> null | V118: =IF(IFERROR(INDEX(WBS_Dictionary!F$2:F$1212, MATCH(Table2[[#This Row],[WBS_ID]], Table26[WBS CODE],0)), "") = "", "null", IFERROR(INDEX(WBS_Dictionary!F$2:F$1212, MATCH(Table2[[#This Row],[WBS_ID]], Table26[WBS CODE],0)), "")) -> null | W118: =IF(IFERROR(INDEX(WBS_Dictionary!G$2:G$1212, MATCH(Table2[[#This Row],[WBS_ID]], Table26[WBS CODE],0)), "") = "", "null", IFERROR(INDEX(WBS_Dictionary!G$2:G$1212, MATCH(Table2[[#This Row],[WBS_ID]], Table26[WBS CODE],0)), "")) -> null | X118: =IF(IFERROR(INDEX(WBS_Dictionary!H$2:H$1212, MATCH(Table2[[#This Row],[WBS_ID]], Table26[WBS CODE],0)), "") = "", "null", IFERROR(INDEX(WBS_Dictionary!H$2:H$1212, MATCH(Table2[[#This Row],[WBS_ID]], Table26[WBS CODE],0)), "")) -> null | Y118: =IF(IFERROR(INDEX(WBS_Dictionary!I$2:I$1212, MATCH(Table2[[#This Row],[WBS_ID]], Table26[WBS CODE],0)), "") = "", "null", IFERROR(INDEX(WBS_Dictionary!I$2:I$1212, MATCH(Table2[[#This Row],[WBS_ID]], Table26[WBS CODE],0)), "")) -> null | Z118: =IF(IFERROR(INDEX(WBS_Dictionary!J$2:J$1212, MATCH(Table2[[#This Row],[WBS_ID]], Table26[WBS CODE],0)), "") = "", "null", IFERROR(INDEX(WBS_Dictionary!J$2:J$1212, MATCH(Table2[[#This Row],[WBS_ID]], Table26[WBS CODE],0)), "")) -> null | AA118: =IF(IFERROR(INDEX(WBS_Dictionary!K$2:K$1212, MATCH(Table2[[#This Row],[WBS_ID]], Table26[WBS CODE],0)), "") = "", "null", IFERROR(INDEX(WBS_Dictionary!K$2:K$1212, MATCH(Table2[[#This Row],[WBS_ID]], Table26[WBS CODE],0)), "")) -> null | AB118: =IF(IFERROR(INDEX(WBS_Dictionary!L$2:L$1212, MATCH(Table2[[#This Row],[WBS_ID]], Table26[WBS CODE],0)), "") = "", "null", IFERROR(INDEX(WBS_Dictionary!L$2:L$1212, MATCH(Table2[[#This Row],[WBS_ID]], Table26[WBS CODE],0)), "")) -> null | ... AE118: =IF(IFERROR(INDEX(WBS_Dictionary!O$2:O$1212, MATCH(Table2[[#This Row],[WBS_ID]], Table26[WBS CODE],0)), "") = "", "null", IFERROR(INDEX(WBS_Dictionary!O$2:O$1212, MATCH(Table2[[#This Row],[WBS_ID]], Table26[WBS CODE],0)), "")) -> null
A119: 118 | B119: 07 | C119: Digging for Pole and cable | D119: 40000007089 0040 | F119: 0 | G119: USD | H119: 0 | I119: USD | J119: 0 | K119: USD | L119: 0 | M119: USD | N119: 0 | O119: USD | U119: =IF(IFERROR(INDEX(WBS_Dictionary!E$2:E$1212, MATCH(Table2[[#This Row],[WBS_ID]], Table26[WBS CODE],0)), "") = "", "null", IFERROR(INDEX(WBS_Dictionary!E$2:E$1212, MATCH(Table2[[#This Row],[WBS_ID]], Table26[WBS CODE],0)), "")) -> null | V119: =IF(IFERROR(INDEX(WBS_Dictionary!F$2:F$1212, MATCH(Table2[[#This Row],[WBS_ID]], Table26[WBS CODE],0)), "") = "", "null", IFERROR(INDEX(WBS_Dictionary!F$2:F$1212, MATCH(Table2[[#This Row],[WBS_ID]], Table26[WBS CODE],0)), "")) -> null | W119: =IF(IFERROR(INDEX(WBS_Dictionary!G$2:G$1212, MATCH(Table2[[#This Row],[WBS_ID]], Table26[WBS CODE],0)), "") = "", "null", IFERROR(INDEX(WBS_Dictionary!G$2:G$1212, MATCH(Table2[[#This Row],[WBS_ID]], Table26[WBS CODE],0)), "")) -> null | X119: =IF(IFERROR(INDEX(WBS_Dictionary!H$2:H$1212, MATCH(Table2[[#This Row],[WBS_ID]], Table26[WBS CODE],0)), "") = "", "null", IFERROR(INDEX(WBS_Dictionary!H$2:H$1212, MATCH(Table2[[#This Row],[WBS_ID]], Table26[WBS CODE],0)), "")) -> null | Y119: =IF(IFERROR(INDEX(WBS_Dictionary!I$2:I$1212, MATCH(Table2[[#This Row],[WBS_ID]], Table26[WBS CODE],0)), "") = "", "null", IFERROR(INDEX(WBS_Dictionary!I$2:I$1212, MATCH(Table2[[#This Row],[WBS_ID]], Table26[WBS CODE],0)), "")) -> null | Z119: =IF(IFERROR(INDEX(WBS_Dictionary!J$2:J$1212, MATCH(Table2[[#This Row],[WBS_ID]], Table26[WBS CODE],0)), "") = "", "null", IFERROR(INDEX(WBS_Dictionary!J$2:J$1212, MATCH(Table2[[#This Row],[WBS_ID]], Table26[WBS CODE],0)), "")) -> null | AA119: =IF(IFERROR(INDEX(WBS_Dictionary!K$2:K$1212, MATCH(Table2[[#This Row],[WBS_ID]], Table26[WBS CODE],0)), "") = "", "null", IFERROR(INDEX(WBS_Dictionary!K$2:K$1212, MATCH(Table2[[#This Row],[WBS_ID]], Table26[WBS CODE],0)), "")) -> null | AB119: =IF(IFERROR(INDEX(WBS_Dictionary!L$2:L$1212, MATCH(Table2[[#This Row],[WBS_ID]], Table26[WBS CODE],0)), "") = "", "null", IFERROR(INDEX(WBS_Dictionary!L$2:L$1212, MATCH(Table2[[#This Row],[WBS_ID]], Table26[WBS CODE],0)), "")) -> null | ... AE119: =IF(IFERROR(INDEX(WBS_Dictionary!O$2:O$1212, MATCH(Table2[[#This Row],[WBS_ID]], Table26[WBS CODE],0)), "") = "", "null", IFERROR(INDEX(WBS_Dictionary!O$2:O$1212, MATCH(Table2[[#This Row],[WBS_ID]], Table26[WBS CODE],0)), "")) -> null
A120: 119 | B120: 07 | C120: Housekeeping | D120: 40000007089 0050 | F120: 0 | G120: USD | H120: 0 | I120: USD | J120: 0 | K120: USD | L120: 0 | M120: USD | N120: 0 | O120: USD | U120: =IF(IFERROR(INDEX(WBS_Dictionary!E$2:E$1212, MATCH(Table2[[#This Row],[WBS_ID]], Table26[WBS CODE],0)), "") = "", "null", IFERROR(INDEX(WBS_Dictionary!E$2:E$1212, MATCH(Table2[[#This Row],[WBS_ID]], Table26[WBS CODE],0)), "")) -> null | V120: =IF(IFERROR(INDEX(WBS_Dictionary!F$2:F$1212, MATCH(Table2[[#This Row],[WBS_ID]], Table26[WBS CODE],0)), "") = "", "null", IFERROR(INDEX(WBS_Dictionary!F$2:F$1212, MATCH(Table2[[#This Row],[WBS_ID]], Table26[WBS CODE],0)), "")) -> null | W120: =IF(IFERROR(INDEX(WBS_Dictionary!G$2:G$1212, MATCH(Table2[[#This Row],[WBS_ID]], Table26[WBS CODE],0)), "") = "", "null", IFERROR(INDEX(WBS_Dictionary!G$2:G$1212, MATCH(Table2[[#This Row],[WBS_ID]], Table26[WBS CODE],0)), "")) -> null | X120: =IF(IFERROR(INDEX(WBS_Dictionary!H$2:H$1212, MATCH(Table2[[#This Row],[WBS_ID]], Table26[WBS CODE],0)), "") = "", "null", IFERROR(INDEX(WBS_Dictionary!H$2:H$1212, MATCH(Table2[[#This Row],[WBS_ID]], Table26[WBS CODE],0)), "")) -> null | Y120: =IF(IFERROR(INDEX(WBS_Dictionary!I$2:I$1212, MATCH(Table2[[#This Row],[WBS_ID]], Table26[WBS CODE],0)), "") = "", "null", IFERROR(INDEX(WBS_Dictionary!I$2:I$1212, MATCH(Table2[[#This Row],[WBS_ID]], Table26[WBS CODE],0)), "")) -> null | Z120: =IF(IFERROR(INDEX(WBS_Dictionary!J$2:J$1212, MATCH(Table2[[#This Row],[WBS_ID]], Table26[WBS CODE],0)), "") = "", "null", IFERROR(INDEX(WBS_Dictionary!J$2:J$1212, MATCH(Table2[[#This Row],[WBS_ID]], Table26[WBS CODE],0)), "")) -> null | AA120: =IF(IFERROR(INDEX(WBS_Dictionary!K$2:K$1212, MATCH(Table2[[#This Row],[WBS_ID]], Table26[WBS CODE],0)), "") = "", "null", IFERROR(INDEX(WBS_Dictionary!K$2:K$1212, MATCH(Table2[[#This Row],[WBS_ID]], Table26[WBS CODE],0)), "")) -> null | AB120: =IF(IFERROR(INDEX(WBS_Dictionary!L$2:L$1212, MATCH(Table2[[#This Row],[WBS_ID]], Table26[WBS CODE],0)), "") = "", "null", IFERROR(INDEX(WBS_Dictionary!L$2:L$1212, MATCH(Table2[[#This Row],[WBS_ID]], Table26[WBS CODE],0)), "")) -> null | ... AE120: =IF(IFERROR(INDEX(WBS_Dictionary!O$2:O$1212, MATCH(Table2[[#This Row],[WBS_ID]], Table26[WBS CODE],0)), "") = "", "null", IFERROR(INDEX(WBS_Dictionary!O$2:O$1212, MATCH(Table2[[#This Row],[WBS_ID]], Table26[WBS CODE],0)), "")) -> null
A121: 120 | B121: 07 | C121: instsll toilet portable awi-21 | D121: 40000007089 0060 | F121: 0 | G121: USD | H121: 0 | I121: USD | J121: 0 | K121: USD | L121: 0 | M121: USD | N121: 0 | O121: USD | U121: =IF(IFERROR(INDEX(WBS_Dictionary!E$2:E$1212, MATCH(Table2[[#This Row],[WBS_ID]], Table26[WBS CODE],0)), "") = "", "null", IFERROR(INDEX(WBS_Dictionary!E$2:E$1212, MATCH(Table2[[#This Row],[WBS_ID]], Table26[WBS CODE],0)), "")) -> null | V121: =IF(IFERROR(INDEX(WBS_Dictionary!F$2:F$1212, MATCH(Table2[[#This Row],[WBS_ID]], Table26[WBS CODE],0)), "") = "", "null", IFERROR(INDEX(WBS_Dictionary!F$2:F$1212, MATCH(Table2[[#This Row],[WBS_ID]], Table26[WBS CODE],0)), "")) -> null | W121: =IF(IFERROR(INDEX(WBS_Dictionary!G$2:G$1212, MATCH(Table2[[#This Row],[WBS_ID]], Table26[WBS CODE],0)), "") = "", "null", IFERROR(INDEX(WBS_Dictionary!G$2:G$1212, MATCH(Table2[[#This Row],[WBS_ID]], Table26[WBS CODE],0)), "")) -> null | X121: =IF(IFERROR(INDEX(WBS_Dictionary!H$2:H$1212, MATCH(Table2[[#This Row],[WBS_ID]], Table26[WBS CODE],0)), "") = "", "null", IFERROR(INDEX(WBS_Dictionary!H$2:H$1212, MATCH(Table2[[#This Row],[WBS_ID]], Table26[WBS CODE],0)), "")) -> null | Y121: =IF(IFERROR(INDEX(WBS_Dictionary!I$2:I$1212, MATCH(Table2[[#This Row],[WBS_ID]], Table26[WBS CODE],0)), "") = "", "null", IFERROR(INDEX(WBS_Dictionary!I$2:I$1212, MATCH(Table2[[#This Row],[WBS_ID]], Table26[WBS CODE],0)), "")) -> null | Z121: =IF(IFERROR(INDEX(WBS_Dictionary!J$2:J$1212, MATCH(Table2[[#This Row],[WBS_ID]], Table26[WBS CODE],0)), "") = "", "null", IFERROR(INDEX(WBS_Dictionary!J$2:J$1212, MATCH(Table2[[#This Row],[WBS_ID]], Table26[WBS CODE],0)), "")) -> null | AA121: =IF(IFERROR(INDEX(WBS_Dictionary!K$2:K$1212, MATCH(Table2[[#This Row],[WBS_ID]], Table26[WBS CODE],0)), "") = "", "null", IFERROR(INDEX(WBS_Dictionary!K$2:K$1212, MATCH(Table2[[#This Row],[WBS_ID]], Table26[WBS CODE],0)), "")) -> null | AB121: =IF(IFERROR(INDEX(WBS_Dictionary!L$2:L$1212, MATCH(Table2[[#This Row],[WBS_ID]], Table26[WBS CODE],0)), "") = "", "null", IFERROR(INDEX(WBS_Dictionary!L$2:L$1212, MATCH(Table2[[#This Row],[WBS_ID]], Table26[WBS CODE],0)), "")) -> null | ... AE121: =IF(IFERROR(INDEX(WBS_Dictionary!O$2:O$1212, MATCH(Table2[[#This Row],[WBS_ID]], Table26[WBS CODE],0)), "") = "", "null", IFERROR(INDEX(WBS_Dictionary!O$2:O$1212, MATCH(Table2[[#This Row],[WBS_ID]], Table26[WBS CODE],0)), "")) -> null
A122: 121 | B122: 07 | C122: Assist boom truck | D122: 40000007089 0070 | F122: 0 | G122: USD | H122: 0 | I122: USD | J122: 0 | K122: USD | L122: 0 | M122: USD | N122: 0 | O122: USD | U122: =IF(IFERROR(INDEX(WBS_Dictionary!E$2:E$1212, MATCH(Table2[[#This Row],[WBS_ID]], Table26[WBS CODE],0)), "") = "", "null", IFERROR(INDEX(WBS_Dictionary!E$2:E$1212, MATCH(Table2[[#This Row],[WBS_ID]], Table26[WBS CODE],0)), "")) -> null | V122: =IF(IFERROR(INDEX(WBS_Dictionary!F$2:F$1212, MATCH(Table2[[#This Row],[WBS_ID]], Table26[WBS CODE],0)), "") = "", "null", IFERROR(INDEX(WBS_Dictionary!F$2:F$1212, MATCH(Table2[[#This Row],[WBS_ID]], Table26[WBS CODE],0)), "")) -> null | W122: =IF(IFERROR(INDEX(WBS_Dictionary!G$2:G$1212, MATCH(Table2[[#This Row],[WBS_ID]], Table26[WBS CODE],0)), "") = "", "null", IFERROR(INDEX(WBS_Dictionary!G$2:G$1212, MATCH(Table2[[#This Row],[WBS_ID]], Table26[WBS CODE],0)), "")) -> null | X122: =IF(IFERROR(INDEX(WBS_Dictionary!H$2:H$1212, MATCH(Table2[[#This Row],[WBS_ID]], Table26[WBS CODE],0)), "") = "", "null", IFERROR(INDEX(WBS_Dictionary!H$2:H$1212, MATCH(Table2[[#This Row],[WBS_ID]], Table26[WBS CODE],0)), "")) -> null | Y122: =IF(IFERROR(INDEX(WBS_Dictionary!I$2:I$1212, MATCH(Table2[[#This Row],[WBS_ID]], Table26[WBS CODE],0)), "") = "", "null", IFERROR(INDEX(WBS_Dictionary!I$2:I$1212, MATCH(Table2[[#This Row],[WBS_ID]], Table26[WBS CODE],0)), "")) -> null | Z122: =IF(IFERROR(INDEX(WBS_Dictionary!J$2:J$1212, MATCH(Table2[[#This Row],[WBS_ID]], Table26[WBS CODE],0)), "") = "", "null", IFERROR(INDEX(WBS_Dictionary!J$2:J$1212, MATCH(Table2[[#This Row],[WBS_ID]], Table26[WBS CODE],0)), "")) -> null | AA122: =IF(IFERROR(INDEX(WBS_Dictionary!K$2:K$1212, MATCH(Table2[[#This Row],[WBS_ID]], Table26[WBS CODE],0)), "") = "", "null", IFERROR(INDEX(WBS_Dictionary!K$2:K$1212, MATCH(Table2[[#This Row],[WBS_ID]], Table26[WBS CODE],0)), "")) -> null | AB122: =IF(IFERROR(INDEX(WBS_Dictionary!L$2:L$1212, MATCH(Table2[[#This Row],[WBS_ID]], Table26[WBS CODE],0)), "") = "", "null", IFERROR(INDEX(WBS_Dictionary!L$2:L$1212, MATCH(Table2[[#This Row],[WBS_ID]], Table26[WBS CODE],0)), "")) -> null | ... AE122: =IF(IFERROR(INDEX(WBS_Dictionary!O$2:O$1212, MATCH(Table2[[#This Row],[WBS_ID]], Table26[WBS CODE],0)), "") = "", "null", IFERROR(INDEX(WBS_Dictionary!O$2:O$1212, MATCH(Table2[[#This Row],[WBS_ID]], Table26[WBS CODE],0)), "")) -> null
A123: 122 | B123: 07 | C123: Assist welder | D123: 40000007089 0080 | F123: 0 | G123: USD | H123: 0 | I123: USD | J123: 0 | K123: USD | L123: 0 | M123: USD | N123: 0 | O123: USD | U123: =IF(IFERROR(INDEX(WBS_Dictionary!E$2:E$1212, MATCH(Table2[[#This Row],[WBS_ID]], Table26[WBS CODE],0)), "") = "", "null", IFERROR(INDEX(WBS_Dictionary!E$2:E$1212, MATCH(Table2[[#This Row],[WBS_ID]], Table26[WBS CODE],0)), "")) -> null | V123: =IF(IFERROR(INDEX(WBS_Dictionary!F$2:F$1212, MATCH(Table2[[#This Row],[WBS_ID]], Table26[WBS CODE],0)), "") = "", "null", IFERROR(INDEX(WBS_Dictionary!F$2:F$1212, MATCH(Table2[[#This Row],[WBS_ID]], Table26[WBS CODE],0)), "")) -> null | W123: =IF(IFERROR(INDEX(WBS_Dictionary!G$2:G$1212, MATCH(Table2[[#This Row],[WBS_ID]], Table26[WBS CODE],0)), "") = "", "null", IFERROR(INDEX(WBS_Dictionary!G$2:G$1212, MATCH(Table2[[#This Row],[WBS_ID]], Table26[WBS CODE],0)), "")) -> null | X123: =IF(IFERROR(INDEX(WBS_Dictionary!H$2:H$1212, MATCH(Table2[[#This Row],[WBS_ID]], Table26[WBS CODE],0)), "") = "", "null", IFERROR(INDEX(WBS_Dictionary!H$2:H$1212, MATCH(Table2[[#This Row],[WBS_ID]], Table26[WBS CODE],0)), "")) -> null | Y123: =IF(IFERROR(INDEX(WBS_Dictionary!I$2:I$1212, MATCH(Table2[[#This Row],[WBS_ID]], Table26[WBS CODE],0)), "") = "", "null", IFERROR(INDEX(WBS_Dictionary!I$2:I$1212, MATCH(Table2[[#This Row],[WBS_ID]], Table26[WBS CODE],0)), "")) -> null | Z123: =IF(IFERROR(INDEX(WBS_Dictionary!J$2:J$1212, MATCH(Table2[[#This Row],[WBS_ID]], Table26[WBS CODE],0)), "") = "", "null", IFERROR(INDEX(WBS_Dictionary!J$2:J$1212, MATCH(Table2[[#This Row],[WBS_ID]], Table26[WBS CODE],0)), "")) -> null | AA123: =IF(IFERROR(INDEX(WBS_Dictionary!K$2:K$1212, MATCH(Table2[[#This Row],[WBS_ID]], Table26[WBS CODE],0)), "") = "", "null", IFERROR(INDEX(WBS_Dictionary!K$2:K$1212, MATCH(Table2[[#This Row],[WBS_ID]], Table26[WBS CODE],0)), "")) -> null | AB123: =IF(IFERROR(INDEX(WBS_Dictionary!L$2:L$1212, MATCH(Table2[[#This Row],[WBS_ID]], Table26[WBS CODE],0)), "") = "", "null", IFERROR(INDEX(WBS_Dictionary!L$2:L$1212, MATCH(Table2[[#This Row],[WBS_ID]], Table26[WBS CODE],0)), "")) -> null | ... AE123: =IF(IFERROR(INDEX(WBS_Dictionary!O$2:O$1212, MATCH(Table2[[#This Row],[WBS_ID]], Table26[WBS CODE],0)), "") = "", "null", IFERROR(INDEX(WBS_Dictionary!O$2:O$1212, MATCH(Table2[[#This Row],[WBS_ID]], Table26[WBS CODE],0)), "")) -> null
A124: 123 | B124: 07 | C124: Spv penggalian sumber jalur Listrik Utam | D124: 40000007089 0090 | F124: 0 | G124: USD | H124: 0 | I124: USD | J124: 0 | K124: USD | L124: 0 | M124: USD | N124: 0 | O124: USD | U124: =IF(IFERROR(INDEX(WBS_Dictionary!E$2:E$1212, MATCH(Table2[[#This Row],[WBS_ID]], Table26[WBS CODE],0)), "") = "", "null", IFERROR(INDEX(WBS_Dictionary!E$2:E$1212, MATCH(Table2[[#This Row],[WBS_ID]], Table26[WBS CODE],0)), "")) -> null | V124: =IF(IFERROR(INDEX(WBS_Dictionary!F$2:F$1212, MATCH(Table2[[#This Row],[WBS_ID]], Table26[WBS CODE],0)), "") = "", "null", IFERROR(INDEX(WBS_Dictionary!F$2:F$1212, MATCH(Table2[[#This Row],[WBS_ID]], Table26[WBS CODE],0)), "")) -> null | W124: =IF(IFERROR(INDEX(WBS_Dictionary!G$2:G$1212, MATCH(Table2[[#This Row],[WBS_ID]], Table26[WBS CODE],0)), "") = "", "null", IFERROR(INDEX(WBS_Dictionary!G$2:G$1212, MATCH(Table2[[#This Row],[WBS_ID]], Table26[WBS CODE],0)), "")) -> null | X124: =IF(IFERROR(INDEX(WBS_Dictionary!H$2:H$1212, MATCH(Table2[[#This Row],[WBS_ID]], Table26[WBS CODE],0)), "") = "", "null", IFERROR(INDEX(WBS_Dictionary!H$2:H$1212, MATCH(Table2[[#This Row],[WBS_ID]], Table26[WBS CODE],0)), "")) -> null | Y124: =IF(IFERROR(INDEX(WBS_Dictionary!I$2:I$1212, MATCH(Table2[[#This Row],[WBS_ID]], Table26[WBS CODE],0)), "") = "", "null", IFERROR(INDEX(WBS_Dictionary!I$2:I$1212, MATCH(Table2[[#This Row],[WBS_ID]], Table26[WBS CODE],0)), "")) -> null | Z124: =IF(IFERROR(INDEX(WBS_Dictionary!J$2:J$1212, MATCH(Table2[[#This Row],[WBS_ID]], Table26[WBS CODE],0)), "") = "", "null", IFERROR(INDEX(WBS_Dictionary!J$2:J$1212, MATCH(Table2[[#This Row],[WBS_ID]], Table26[WBS CODE],0)), "")) -> null | AA124: =IF(IFERROR(INDEX(WBS_Dictionary!K$2:K$1212, MATCH(Table2[[#This Row],[WBS_ID]], Table26[WBS CODE],0)), "") = "", "null", IFERROR(INDEX(WBS_Dictionary!K$2:K$1212, MATCH(Table2[[#This Row],[WBS_ID]], Table26[WBS CODE],0)), "")) -> null | AB124: =IF(IFERROR(INDEX(WBS_Dictionary!L$2:L$1212, MATCH(Table2[[#This Row],[WBS_ID]], Table26[WBS CODE],0)), "") = "", "null", IFERROR(INDEX(WBS_Dictionary!L$2:L$1212, MATCH(Table2[[#This Row],[WBS_ID]], Table26[WBS CODE],0)), "")) -> null | ... AE124: =IF(IFERROR(INDEX(WBS_Dictionary!O$2:O$1212, MATCH(Table2[[#This Row],[WBS_ID]], Table26[WBS CODE],0)), "") = "", "null", IFERROR(INDEX(WBS_Dictionary!O$2:O$1212, MATCH(Table2[[#This Row],[WBS_ID]], Table26[WBS CODE],0)), "")) -> null
A125: 124 | B125: 07 | C125: Check underground cable AWI-21 | D125: 40000007089 0100 | F125: 0 | G125: USD | H125: 0 | I125: USD | J125: 0 | K125: USD | L125: 0 | M125: USD | N125: 0 | O125: USD | U125: =IF(IFERROR(INDEX(WBS_Dictionary!E$2:E$1212, MATCH(Table2[[#This Row],[WBS_ID]], Table26[WBS CODE],0)), "") = "", "null", IFERROR(INDEX(WBS_Dictionary!E$2:E$1212, MATCH(Table2[[#This Row],[WBS_ID]], Table26[WBS CODE],0)), "")) -> null | V125: =IF(IFERROR(INDEX(WBS_Dictionary!F$2:F$1212, MATCH(Table2[[#This Row],[WBS_ID]], Table26[WBS CODE],0)), "") = "", "null", IFERROR(INDEX(WBS_Dictionary!F$2:F$1212, MATCH(Table2[[#This Row],[WBS_ID]], Table26[WBS CODE],0)), "")) -> null | W125: =IF(IFERROR(INDEX(WBS_Dictionary!G$2:G$1212, MATCH(Table2[[#This Row],[WBS_ID]], Table26[WBS CODE],0)), "") = "", "null", IFERROR(INDEX(WBS_Dictionary!G$2:G$1212, MATCH(Table2[[#This Row],[WBS_ID]], Table26[WBS CODE],0)), "")) -> null | X125: =IF(IFERROR(INDEX(WBS_Dictionary!H$2:H$1212, MATCH(Table2[[#This Row],[WBS_ID]], Table26[WBS CODE],0)), "") = "", "null", IFERROR(INDEX(WBS_Dictionary!H$2:H$1212, MATCH(Table2[[#This Row],[WBS_ID]], Table26[WBS CODE],0)), "")) -> null | Y125: =IF(IFERROR(INDEX(WBS_Dictionary!I$2:I$1212, MATCH(Table2[[#This Row],[WBS_ID]], Table26[WBS CODE],0)), "") = "", "null", IFERROR(INDEX(WBS_Dictionary!I$2:I$1212, MATCH(Table2[[#This Row],[WBS_ID]], Table26[WBS CODE],0)), "")) -> null | Z125: =IF(IFERROR(INDEX(WBS_Dictionary!J$2:J$1212, MATCH(Table2[[#This Row],[WBS_ID]], Table26[WBS CODE],0)), "") = "", "null", IFERROR(INDEX(WBS_Dictionary!J$2:J$1212, MATCH(Table2[[#This Row],[WBS_ID]], Table26[WBS CODE],0)), "")) -> null | AA125: =IF(IFERROR(INDEX(WBS_Dictionary!K$2:K$1212, MATCH(Table2[[#This Row],[WBS_ID]], Table26[WBS CODE],0)), "") = "", "null", IFERROR(INDEX(WBS_Dictionary!K$2:K$1212, MATCH(Table2[[#This Row],[WBS_ID]], Table26[WBS CODE],0)), "")) -> null | AB125: =IF(IFERROR(INDEX(WBS_Dictionary!L$2:L$1212, MATCH(Table2[[#This Row],[WBS_ID]], Table26[WBS CODE],0)), "") = "", "null", IFERROR(INDEX(WBS_Dictionary!L$2:L$1212, MATCH(Table2[[#This Row],[WBS_ID]], Table26[WBS CODE],0)), "")) -> null | ... AE125: =IF(IFERROR(INDEX(WBS_Dictionary!O$2:O$1212, MATCH(Table2[[#This Row],[WBS_ID]], Table26[WBS CODE],0)), "") = "", "null", IFERROR(INDEX(WBS_Dictionary!O$2:O$1212, MATCH(Table2[[#This Row],[WBS_ID]], Table26[WBS CODE],0)), "")) -> null
A126: 125 | B126: 03 | C126: Drilling Operation water support | D126: E540-3012981-D245401 | E126: D245401 | F126: 346328 | G126: USD | H126: 346328 | I126: USD | J126: 0 | K126: USD | L126: 33045.4 | M126: USD | N126: 320332 | O126: USD | Q126: X | R126: STAR ENERGY | S126: Production | T126: REL BUDG AVAC // BUDG | U126: =IF(IFERROR(INDEX(WBS_Dictionary!E$2:E$1212, MATCH(Table2[[#This Row],[WBS_ID]], Table26[WBS CODE],0)), "") = "", "null", IFERROR(INDEX(WBS_Dictionary!E$2:E$1212, MATCH(Table2[[#This Row],[WBS_ID]], Table26[WBS CODE],0)), "")) -> E540-30-D245401 | V126: =IF(IFERROR(INDEX(WBS_Dictionary!F$2:F$1212, MATCH(Table2[[#This Row],[WBS_ID]], Table26[WBS CODE],0)), "") = "", "null", IFERROR(INDEX(WBS_Dictionary!F$2:F$1212, MATCH(Table2[[#This Row],[WBS_ID]], Table26[WBS CODE],0)), "")) -> E540-30129-D245401 | W126: =IF(IFERROR(INDEX(WBS_Dictionary!G$2:G$1212, MATCH(Table2[[#This Row],[WBS_ID]], Table26[WBS CODE],0)), "") = "", "null", IFERROR(INDEX(WBS_Dictionary!G$2:G$1212, MATCH(Table2[[#This Row],[WBS_ID]], Table26[WBS CODE],0)), "")) -> E540-3012981-D245401 | X126: =IF(IFERROR(INDEX(WBS_Dictionary!H$2:H$1212, MATCH(Table2[[#This Row],[WBS_ID]], Table26[WBS CODE],0)), "") = "", "null", IFERROR(INDEX(WBS_Dictionary!H$2:H$1212, MATCH(Table2[[#This Row],[WBS_ID]], Table26[WBS CODE],0)), "")) -> null | Y126: =IF(IFERROR(INDEX(WBS_Dictionary!I$2:I$1212, MATCH(Table2[[#This Row],[WBS_ID]], Table26[WBS CODE],0)), "") = "", "null", IFERROR(INDEX(WBS_Dictionary!I$2:I$1212, MATCH(Table2[[#This Row],[WBS_ID]], Table26[WBS CODE],0)), "")) -> null | Z126: =IF(IFERROR(INDEX(WBS_Dictionary!J$2:J$1212, MATCH(Table2[[#This Row],[WBS_ID]], Table26[WBS CODE],0)), "") = "", "null", IFERROR(INDEX(WBS_Dictionary!J$2:J$1212, MATCH(Table2[[#This Row],[WBS_ID]], Table26[WBS CODE],0)), "")) -> Support Cost | AA126: =IF(IFERROR(INDEX(WBS_Dictionary!K$2:K$1212, MATCH(Table2[[#This Row],[WBS_ID]], Table26[WBS CODE],0)), "") = "", "null", IFERROR(INDEX(WBS_Dictionary!K$2:K$1212, MATCH(Table2[[#This Row],[WBS_ID]], Table26[WBS CODE],0)), "")) -> Drilling Operation Water Support | AB126: =IF(IFERROR(INDEX(WBS_Dictionary!L$2:L$1212, MATCH(Table2[[#This Row],[WBS_ID]], Table26[WBS CODE],0)), "") = "", "null", IFERROR(INDEX(WBS_Dictionary!L$2:L$1212, MATCH(Table2[[#This Row],[WBS_ID]], Table26[WBS CODE],0)), "")) -> null | ... AE126: =IF(IFERROR(INDEX(WBS_Dictionary!O$2:O$1212, MATCH(Table2[[#This Row],[WBS_ID]], Table26[WBS CODE],0)), "") = "", "null", IFERROR(INDEX(WBS_Dictionary!O$2:O$1212, MATCH(Table2[[#This Row],[WBS_ID]], Table26[WBS CODE],0)), "")) -> null
A127: 126 | B127: 04 | C127: Drilling Operation water support | D127: E540-301298160-D245401 | E127: D245401 | F127: 346328 | G127: USD | H127: 346328 | I127: USD | J127: 0 | K127: USD | L127: 33045.4 | M127: USD | N127: 320332 | O127: USD | Q127: X | R127: STAR ENERGY | S127: Production | T127: REL BUDG ISBD AVAC // BUDG | U127: =IF(IFERROR(INDEX(WBS_Dictionary!E$2:E$1212, MATCH(Table2[[#This Row],[WBS_ID]], Table26[WBS CODE],0)), "") = "", "null", IFERROR(INDEX(WBS_Dictionary!E$2:E$1212, MATCH(Table2[[#This Row],[WBS_ID]], Table26[WBS CODE],0)), "")) -> E540-30-D245401 | V127: =IF(IFERROR(INDEX(WBS_Dictionary!F$2:F$1212, MATCH(Table2[[#This Row],[WBS_ID]], Table26[WBS CODE],0)), "") = "", "null", IFERROR(INDEX(WBS_Dictionary!F$2:F$1212, MATCH(Table2[[#This Row],[WBS_ID]], Table26[WBS CODE],0)), "")) -> E540-30129-D245401 | W127: =IF(IFERROR(INDEX(WBS_Dictionary!G$2:G$1212, MATCH(Table2[[#This Row],[WBS_ID]], Table26[WBS CODE],0)), "") = "", "null", IFERROR(INDEX(WBS_Dictionary!G$2:G$1212, MATCH(Table2[[#This Row],[WBS_ID]], Table26[WBS CODE],0)), "")) -> E540-3012981-D245401 | X127: =IF(IFERROR(INDEX(WBS_Dictionary!H$2:H$1212, MATCH(Table2[[#This Row],[WBS_ID]], Table26[WBS CODE],0)), "") = "", "null", IFERROR(INDEX(WBS_Dictionary!H$2:H$1212, MATCH(Table2[[#This Row],[WBS_ID]], Table26[WBS CODE],0)), "")) -> E540-301298160-D245401 | Y127: =IF(IFERROR(INDEX(WBS_Dictionary!I$2:I$1212, MATCH(Table2[[#This Row],[WBS_ID]], Table26[WBS CODE],0)), "") = "", "null", IFERROR(INDEX(WBS_Dictionary!I$2:I$1212, MATCH(Table2[[#This Row],[WBS_ID]], Table26[WBS CODE],0)), "")) -> null | Z127: =IF(IFERROR(INDEX(WBS_Dictionary!J$2:J$1212, MATCH(Table2[[#This Row],[WBS_ID]], Table26[WBS CODE],0)), "") = "", "null", IFERROR(INDEX(WBS_Dictionary!J$2:J$1212, MATCH(Table2[[#This Row],[WBS_ID]], Table26[WBS CODE],0)), "")) -> Support Cost | AA127: =IF(IFERROR(INDEX(WBS_Dictionary!K$2:K$1212, MATCH(Table2[[#This Row],[WBS_ID]], Table26[WBS CODE],0)), "") = "", "null", IFERROR(INDEX(WBS_Dictionary!K$2:K$1212, MATCH(Table2[[#This Row],[WBS_ID]], Table26[WBS CODE],0)), "")) -> Drilling Operation Water Support | AB127: =IF(IFERROR(INDEX(WBS_Dictionary!L$2:L$1212, MATCH(Table2[[#This Row],[WBS_ID]], Table26[WBS CODE],0)), "") = "", "null", IFERROR(INDEX(WBS_Dictionary!L$2:L$1212, MATCH(Table2[[#This Row],[WBS_ID]], Table26[WBS CODE],0)), "")) -> Drilling Operation Water Support | ... AE127: =IF(IFERROR(INDEX(WBS_Dictionary!O$2:O$1212, MATCH(Table2[[#This Row],[WBS_ID]], Table26[WBS CODE],0)), "") = "", "null", IFERROR(INDEX(WBS_Dictionary!O$2:O$1212, MATCH(Table2[[#This Row],[WBS_ID]], Table26[WBS CODE],0)), "")) -> null
A128: 127 | B128: 05 | C128: Drilling Operation water support | D128: E540-30129816043-D245401 | E128: D245401 | F128: 0 | G128: USD | H128: 0 | I128: USD | J128: 0 | K128: USD | L128: 33045.4 | M128: USD | N128: 320332 | O128: USD | Q128: X | R128: STAR ENERGY | S128: Production | T128: REL AVAC SETC // BUDG | U128: =IF(IFERROR(INDEX(WBS_Dictionary!E$2:E$1212, MATCH(Table2[[#This Row],[WBS_ID]], Table26[WBS CODE],0)), "") = "", "null", IFERROR(INDEX(WBS_Dictionary!E$2:E$1212, MATCH(Table2[[#This Row],[WBS_ID]], Table26[WBS CODE],0)), "")) -> E540-30-D245401 | V128: =IF(IFERROR(INDEX(WBS_Dictionary!F$2:F$1212, MATCH(Table2[[#This Row],[WBS_ID]], Table26[WBS CODE],0)), "") = "", "null", IFERROR(INDEX(WBS_Dictionary!F$2:F$1212, MATCH(Table2[[#This Row],[WBS_ID]], Table26[WBS CODE],0)), "")) -> E540-30129-D245401 | W128: =IF(IFERROR(INDEX(WBS_Dictionary!G$2:G$1212, MATCH(Table2[[#This Row],[WBS_ID]], Table26[WBS CODE],0)), "") = "", "null", IFERROR(INDEX(WBS_Dictionary!G$2:G$1212, MATCH(Table2[[#This Row],[WBS_ID]], Table26[WBS CODE],0)), "")) -> E540-3012981-D245401 | X128: =IF(IFERROR(INDEX(WBS_Dictionary!H$2:H$1212, MATCH(Table2[[#This Row],[WBS_ID]], Table26[WBS CODE],0)), "") = "", "null", IFERROR(INDEX(WBS_Dictionary!H$2:H$1212, MATCH(Table2[[#This Row],[WBS_ID]], Table26[WBS CODE],0)), "")) -> E540-301298160-D245401 | Y128: =IF(IFERROR(INDEX(WBS_Dictionary!I$2:I$1212, MATCH(Table2[[#This Row],[WBS_ID]], Table26[WBS CODE],0)), "") = "", "null", IFERROR(INDEX(WBS_Dictionary!I$2:I$1212, MATCH(Table2[[#This Row],[WBS_ID]], Table26[WBS CODE],0)), "")) -> E540-30129816043-D245401 | Z128: =IF(IFERROR(INDEX(WBS_Dictionary!J$2:J$1212, MATCH(Table2[[#This Row],[WBS_ID]], Table26[WBS CODE],0)), "") = "", "null", IFERROR(INDEX(WBS_Dictionary!J$2:J$1212, MATCH(Table2[[#This Row],[WBS_ID]], Table26[WBS CODE],0)), "")) -> Support Cost | AA128: =IF(IFERROR(INDEX(WBS_Dictionary!K$2:K$1212, MATCH(Table2[[#This Row],[WBS_ID]], Table26[WBS CODE],0)), "") = "", "null", IFERROR(INDEX(WBS_Dictionary!K$2:K$1212, MATCH(Table2[[#This Row],[WBS_ID]], Table26[WBS CODE],0)), "")) -> Drilling Operation Water Support | AB128: =IF(IFERROR(INDEX(WBS_Dictionary!L$2:L$1212, MATCH(Table2[[#This Row],[WBS_ID]], Table26[WBS CODE],0)), "") = "", "null", IFERROR(INDEX(WBS_Dictionary!L$2:L$1212, MATCH(Table2[[#This Row],[WBS_ID]], Table26[WBS CODE],0)), "")) -> Drilling Operation Water Support | ... AE128: =IF(IFERROR(INDEX(WBS_Dictionary!O$2:O$1212, MATCH(Table2[[#This Row],[WBS_ID]], Table26[WBS CODE],0)), "") = "", "null", IFERROR(INDEX(WBS_Dictionary!O$2:O$1212, MATCH(Table2[[#This Row],[WBS_ID]], Table26[WBS CODE],0)), "")) -> null
A129: 128 | B129: 03 | C129: Well Insurance | D129: E540-3012979-D245401 | E129: D245401 | F129: 562531.16 | G129: USD | H129: 562530.5 | I129: USD | J129: 0 | K129: USD | L129: 0 | M129: USD | N129: 131647.73 | O129: USD | Q129: X | R129: STAR ENERGY | S129: Production | T129: REL BUDG AVAC // BUDG | U129: =IF(IFERROR(INDEX(WBS_Dictionary!E$2:E$1212, MATCH(Table2[[#This Row],[WBS_ID]], Table26[WBS CODE],0)), "") = "", "null", IFERROR(INDEX(WBS_Dictionary!E$2:E$1212, MATCH(Table2[[#This Row],[WBS_ID]], Table26[WBS CODE],0)), "")) -> E540-30-D245401 | V129: =IF(IFERROR(INDEX(WBS_Dictionary!F$2:F$1212, MATCH(Table2[[#This Row],[WBS_ID]], Table26[WBS CODE],0)), "") = "", "null", IFERROR(INDEX(WBS_Dictionary!F$2:F$1212, MATCH(Table2[[#This Row],[WBS_ID]], Table26[WBS CODE],0)), "")) -> E540-30129-D245401 | W129: =IF(IFERROR(INDEX(WBS_Dictionary!G$2:G$1212, MATCH(Table2[[#This Row],[WBS_ID]], Table26[WBS CODE],0)), "") = "", "null", IFERROR(INDEX(WBS_Dictionary!G$2:G$1212, MATCH(Table2[[#This Row],[WBS_ID]], Table26[WBS CODE],0)), "")) -> E540-3012979-D245401 | X129: =IF(IFERROR(INDEX(WBS_Dictionary!H$2:H$1212, MATCH(Table2[[#This Row],[WBS_ID]], Table26[WBS CODE],0)), "") = "", "null", IFERROR(INDEX(WBS_Dictionary!H$2:H$1212, MATCH(Table2[[#This Row],[WBS_ID]], Table26[WBS CODE],0)), "")) -> null | Y129: =IF(IFERROR(INDEX(WBS_Dictionary!I$2:I$1212, MATCH(Table2[[#This Row],[WBS_ID]], Table26[WBS CODE],0)), "") = "", "null", IFERROR(INDEX(WBS_Dictionary!I$2:I$1212, MATCH(Table2[[#This Row],[WBS_ID]], Table26[WBS CODE],0)), "")) -> null | Z129: =IF(IFERROR(INDEX(WBS_Dictionary!J$2:J$1212, MATCH(Table2[[#This Row],[WBS_ID]], Table26[WBS CODE],0)), "") = "", "null", IFERROR(INDEX(WBS_Dictionary!J$2:J$1212, MATCH(Table2[[#This Row],[WBS_ID]], Table26[WBS CODE],0)), "")) -> Support Cost | AA129: =IF(IFERROR(INDEX(WBS_Dictionary!K$2:K$1212, MATCH(Table2[[#This Row],[WBS_ID]], Table26[WBS CODE],0)), "") = "", "null", IFERROR(INDEX(WBS_Dictionary!K$2:K$1212, MATCH(Table2[[#This Row],[WBS_ID]], Table26[WBS CODE],0)), "")) -> Well Insurance | AB129: =IF(IFERROR(INDEX(WBS_Dictionary!L$2:L$1212, MATCH(Table2[[#This Row],[WBS_ID]], Table26[WBS CODE],0)), "") = "", "null", IFERROR(INDEX(WBS_Dictionary!L$2:L$1212, MATCH(Table2[[#This Row],[WBS_ID]], Table26[WBS CODE],0)), "")) -> null | ... AE129: =IF(IFERROR(INDEX(WBS_Dictionary!O$2:O$1212, MATCH(Table2[[#This Row],[WBS_ID]], Table26[WBS CODE],0)), "") = "", "null", IFERROR(INDEX(WBS_Dictionary!O$2:O$1212, MATCH(Table2[[#This Row],[WBS_ID]], Table26[WBS CODE],0)), "")) -> null
A130: 129 | B130: 04 | C130: Insurance AWI 9-10RD | D130: E540-301297909-D245401 | E130: D245401 | F130: 82932 | G130: USD | H130: 82932 | I130: USD | J130: 0 | K130: USD | L130: 0 | M130: USD | N130: 0 | O130: USD | Q130: X | R130: STAR ENERGY | S130: Production | T130: REL BUDG AVAC // BUDG | U130: =IF(IFERROR(INDEX(WBS_Dictionary!E$2:E$1212, MATCH(Table2[[#This Row],[WBS_ID]], Table26[WBS CODE],0)), "") = "", "null", IFERROR(INDEX(WBS_Dictionary!E$2:E$1212, MATCH(Table2[[#This Row],[WBS_ID]], Table26[WBS CODE],0)), "")) -> E540-30-D245401 | V130: =IF(IFERROR(INDEX(WBS_Dictionary!F$2:F$1212, MATCH(Table2[[#This Row],[WBS_ID]], Table26[WBS CODE],0)), "") = "", "null", IFERROR(INDEX(WBS_Dictionary!F$2:F$1212, MATCH(Table2[[#This Row],[WBS_ID]], Table26[WBS CODE],0)), "")) -> E540-30129-D245401 | W130: =IF(IFERROR(INDEX(WBS_Dictionary!G$2:G$1212, MATCH(Table2[[#This Row],[WBS_ID]], Table26[WBS CODE],0)), "") = "", "null", IFERROR(INDEX(WBS_Dictionary!G$2:G$1212, MATCH(Table2[[#This Row],[WBS_ID]], Table26[WBS CODE],0)), "")) -> E540-3012979-D245401 | X130: =IF(IFERROR(INDEX(WBS_Dictionary!H$2:H$1212, MATCH(Table2[[#This Row],[WBS_ID]], Table26[WBS CODE],0)), "") = "", "null", IFERROR(INDEX(WBS_Dictionary!H$2:H$1212, MATCH(Table2[[#This Row],[WBS_ID]], Table26[WBS CODE],0)), "")) -> E540-301297909-D245401 | Y130: =IF(IFERROR(INDEX(WBS_Dictionary!I$2:I$1212, MATCH(Table2[[#This Row],[WBS_ID]], Table26[WBS CODE],0)), "") = "", "null", IFERROR(INDEX(WBS_Dictionary!I$2:I$1212, MATCH(Table2[[#This Row],[WBS_ID]], Table26[WBS CODE],0)), "")) -> null | Z130: =IF(IFERROR(INDEX(WBS_Dictionary!J$2:J$1212, MATCH(Table2[[#This Row],[WBS_ID]], Table26[WBS CODE],0)), "") = "", "null", IFERROR(INDEX(WBS_Dictionary!J$2:J$1212, MATCH(Table2[[#This Row],[WBS_ID]], Table26[WBS CODE],0)), "")) -> Support Cost | AA130: =IF(IFERROR(INDEX(WBS_Dictionary!K$2:K$1212, MATCH(Table2[[#This Row],[WBS_ID]], Table26[WBS CODE],0)), "") = "", "null", IFERROR(INDEX(WBS_Dictionary!K$2:K$1212, MATCH(Table2[[#This Row],[WBS_ID]], Table26[WBS CODE],0)), "")) -> Well Insurance | AB130: =IF(IFERROR(INDEX(WBS_Dictionary!L$2:L$1212, MATCH(Table2[[#This Row],[WBS_ID]], Table26[WBS CODE],0)), "") = "", "null", IFERROR(INDEX(WBS_Dictionary!L$2:L$1212, MATCH(Table2[[#This Row],[WBS_ID]], Table26[WBS CODE],0)), "")) -> Well Insurance | ... AE130: =IF(IFERROR(INDEX(WBS_Dictionary!O$2:O$1212, MATCH(Table2[[#This Row],[WBS_ID]], Table26[WBS CODE],0)), "") = "", "null", IFERROR(INDEX(WBS_Dictionary!O$2:O$1212, MATCH(Table2[[#This Row],[WBS_ID]], Table26[WBS CODE],0)), "")) -> Well
A131: 130 | B131: 05 | C131: Insurance AWI 9-10RD | D131: E540-30129790909-D245401 | E131: D245401 | F131: 0 | G131: USD | H131: 0 | I131: USD | J131: 0 | K131: USD | L131: 0 | M131: USD | N131: 0 | O131: USD | Q131: X | R131: STAR ENERGY | S131: Production | T131: REL AVAC SETC // BUDG | U131: =IF(IFERROR(INDEX(WBS_Dictionary!E$2:E$1212, MATCH(Table2[[#This Row],[WBS_ID]], Table26[WBS CODE],0)), "") = "", "null", IFERROR(INDEX(WBS_Dictionary!E$2:E$1212, MATCH(Table2[[#This Row],[WBS_ID]], Table26[WBS CODE],0)), "")) -> E540-30-D245401 | V131: =IF(IFERROR(INDEX(WBS_Dictionary!F$2:F$1212, MATCH(Table2[[#This Row],[WBS_ID]], Table26[WBS CODE],0)), "") = "", "null", IFERROR(INDEX(WBS_Dictionary!F$2:F$1212, MATCH(Table2[[#This Row],[WBS_ID]], Table26[WBS CODE],0)), "")) -> E540-30129-D245401 | W131: =IF(IFERROR(INDEX(WBS_Dictionary!G$2:G$1212, MATCH(Table2[[#This Row],[WBS_ID]], Table26[WBS CODE],0)), "") = "", "null", IFERROR(INDEX(WBS_Dictionary!G$2:G$1212, MATCH(Table2[[#This Row],[WBS_ID]], Table26[WBS CODE],0)), "")) -> E540-3012979-D245401 | X131: =IF(IFERROR(INDEX(WBS_Dictionary!H$2:H$1212, MATCH(Table2[[#This Row],[WBS_ID]], Table26[WBS CODE],0)), "") = "", "null", IFERROR(INDEX(WBS_Dictionary!H$2:H$1212, MATCH(Table2[[#This Row],[WBS_ID]], Table26[WBS CODE],0)), "")) -> E540-301297909-D245401 | Y131: =IF(IFERROR(INDEX(WBS_Dictionary!I$2:I$1212, MATCH(Table2[[#This Row],[WBS_ID]], Table26[WBS CODE],0)), "") = "", "null", IFERROR(INDEX(WBS_Dictionary!I$2:I$1212, MATCH(Table2[[#This Row],[WBS_ID]], Table26[WBS CODE],0)), "")) -> E540-30129790909-D245401 | Z131: =IF(IFERROR(INDEX(WBS_Dictionary!J$2:J$1212, MATCH(Table2[[#This Row],[WBS_ID]], Table26[WBS CODE],0)), "") = "", "null", IFERROR(INDEX(WBS_Dictionary!J$2:J$1212, MATCH(Table2[[#This Row],[WBS_ID]], Table26[WBS CODE],0)), "")) -> Support Cost | AA131: =IF(IFERROR(INDEX(WBS_Dictionary!K$2:K$1212, MATCH(Table2[[#This Row],[WBS_ID]], Table26[WBS CODE],0)), "") = "", "null", IFERROR(INDEX(WBS_Dictionary!K$2:K$1212, MATCH(Table2[[#This Row],[WBS_ID]], Table26[WBS CODE],0)), "")) -> Well Insurance | AB131: =IF(IFERROR(INDEX(WBS_Dictionary!L$2:L$1212, MATCH(Table2[[#This Row],[WBS_ID]], Table26[WBS CODE],0)), "") = "", "null", IFERROR(INDEX(WBS_Dictionary!L$2:L$1212, MATCH(Table2[[#This Row],[WBS_ID]], Table26[WBS CODE],0)), "")) -> Well Insurance | ... AE131: =IF(IFERROR(INDEX(WBS_Dictionary!O$2:O$1212, MATCH(Table2[[#This Row],[WBS_ID]], Table26[WBS CODE],0)), "") = "", "null", IFERROR(INDEX(WBS_Dictionary!O$2:O$1212, MATCH(Table2[[#This Row],[WBS_ID]], Table26[WBS CODE],0)), "")) -> Well
A132: 131 | B132: 04 | C132: Insurance AWI 23-2 | D132: E540-301297908-D245401 | E132: D245401 | F132: 82932 | G132: USD | H132: 82932 | I132: USD | J132: 0 | K132: USD | L132: 0 | M132: USD | N132: 37796.48 | O132: USD | Q132: X | R132: STAR ENERGY | S132: Production | T132: REL BUDG AVAC // BUDG | U132: =IF(IFERROR(INDEX(WBS_Dictionary!E$2:E$1212, MATCH(Table2[[#This Row],[WBS_ID]], Table26[WBS CODE],0)), "") = "", "null", IFERROR(INDEX(WBS_Dictionary!E$2:E$1212, MATCH(Table2[[#This Row],[WBS_ID]], Table26[WBS CODE],0)), "")) -> E540-30-D245401 | V132: =IF(IFERROR(INDEX(WBS_Dictionary!F$2:F$1212, MATCH(Table2[[#This Row],[WBS_ID]], Table26[WBS CODE],0)), "") = "", "null", IFERROR(INDEX(WBS_Dictionary!F$2:F$1212, MATCH(Table2[[#This Row],[WBS_ID]], Table26[WBS CODE],0)), "")) -> E540-30129-D245401 | W132: =IF(IFERROR(INDEX(WBS_Dictionary!G$2:G$1212, MATCH(Table2[[#This Row],[WBS_ID]], Table26[WBS CODE],0)), "") = "", "null", IFERROR(INDEX(WBS_Dictionary!G$2:G$1212, MATCH(Table2[[#This Row],[WBS_ID]], Table26[WBS CODE],0)), "")) -> E540-3012979-D245401 | X132: =IF(IFERROR(INDEX(WBS_Dictionary!H$2:H$1212, MATCH(Table2[[#This Row],[WBS_ID]], Table26[WBS CODE],0)), "") = "", "null", IFERROR(INDEX(WBS_Dictionary!H$2:H$1212, MATCH(Table2[[#This Row],[WBS_ID]], Table26[WBS CODE],0)), "")) -> E540-301297908-D245401 | Y132: =IF(IFERROR(INDEX(WBS_Dictionary!I$2:I$1212, MATCH(Table2[[#This Row],[WBS_ID]], Table26[WBS CODE],0)), "") = "", "null", IFERROR(INDEX(WBS_Dictionary!I$2:I$1212, MATCH(Table2[[#This Row],[WBS_ID]], Table26[WBS CODE],0)), "")) -> null | Z132: =IF(IFERROR(INDEX(WBS_Dictionary!J$2:J$1212, MATCH(Table2[[#This Row],[WBS_ID]], Table26[WBS CODE],0)), "") = "", "null", IFERROR(INDEX(WBS_Dictionary!J$2:J$1212, MATCH(Table2[[#This Row],[WBS_ID]], Table26[WBS CODE],0)), "")) -> Support Cost | AA132: =IF(IFERROR(INDEX(WBS_Dictionary!K$2:K$1212, MATCH(Table2[[#This Row],[WBS_ID]], Table26[WBS CODE],0)), "") = "", "null", IFERROR(INDEX(WBS_Dictionary!K$2:K$1212, MATCH(Table2[[#This Row],[WBS_ID]], Table26[WBS CODE],0)), "")) -> Well Insurance | AB132: =IF(IFERROR(INDEX(WBS_Dictionary!L$2:L$1212, MATCH(Table2[[#This Row],[WBS_ID]], Table26[WBS CODE],0)), "") = "", "null", IFERROR(INDEX(WBS_Dictionary!L$2:L$1212, MATCH(Table2[[#This Row],[WBS_ID]], Table26[WBS CODE],0)), "")) -> Well Insurance | ... AE132: =IF(IFERROR(INDEX(WBS_Dictionary!O$2:O$1212, MATCH(Table2[[#This Row],[WBS_ID]], Table26[WBS CODE],0)), "") = "", "null", IFERROR(INDEX(WBS_Dictionary!O$2:O$1212, MATCH(Table2[[#This Row],[WBS_ID]], Table26[WBS CODE],0)), "")) -> Well
A133: 132 | B133: 05 | C133: Insurance AWI 23-2 | D133: E540-30129790808-D245401 | E133: D245401 | F133: 0 | G133: USD | H133: 0 | I133: USD | J133: 0 | K133: USD | L133: 0 | M133: USD | N133: 37796.48 | O133: USD | Q133: X | R133: STAR ENERGY | S133: Production | T133: REL AVAC SETC // BUDG | U133: =IF(IFERROR(INDEX(WBS_Dictionary!E$2:E$1212, MATCH(Table2[[#This Row],[WBS_ID]], Table26[WBS CODE],0)), "") = "", "null", IFERROR(INDEX(WBS_Dictionary!E$2:E$1212, MATCH(Table2[[#This Row],[WBS_ID]], Table26[WBS CODE],0)), "")) -> E540-30-D245401 | V133: =IF(IFERROR(INDEX(WBS_Dictionary!F$2:F$1212, MATCH(Table2[[#This Row],[WBS_ID]], Table26[WBS CODE],0)), "") = "", "null", IFERROR(INDEX(WBS_Dictionary!F$2:F$1212, MATCH(Table2[[#This Row],[WBS_ID]], Table26[WBS CODE],0)), "")) -> E540-30129-D245401 | W133: =IF(IFERROR(INDEX(WBS_Dictionary!G$2:G$1212, MATCH(Table2[[#This Row],[WBS_ID]], Table26[WBS CODE],0)), "") = "", "null", IFERROR(INDEX(WBS_Dictionary!G$2:G$1212, MATCH(Table2[[#This Row],[WBS_ID]], Table26[WBS CODE],0)), "")) -> E540-3012979-D245401 | X133: =IF(IFERROR(INDEX(WBS_Dictionary!H$2:H$1212, MATCH(Table2[[#This Row],[WBS_ID]], Table26[WBS CODE],0)), "") = "", "null", IFERROR(INDEX(WBS_Dictionary!H$2:H$1212, MATCH(Table2[[#This Row],[WBS_ID]], Table26[WBS CODE],0)), "")) -> E540-301297908-D245401 | Y133: =IF(IFERROR(INDEX(WBS_Dictionary!I$2:I$1212, MATCH(Table2[[#This Row],[WBS_ID]], Table26[WBS CODE],0)), "") = "", "null", IFERROR(INDEX(WBS_Dictionary!I$2:I$1212, MATCH(Table2[[#This Row],[WBS_ID]], Table26[WBS CODE],0)), "")) -> E540-30129790808-D245401 | Z133: =IF(IFERROR(INDEX(WBS_Dictionary!J$2:J$1212, MATCH(Table2[[#This Row],[WBS_ID]], Table26[WBS CODE],0)), "") = "", "null", IFERROR(INDEX(WBS_Dictionary!J$2:J$1212, MATCH(Table2[[#This Row],[WBS_ID]], Table26[WBS CODE],0)), "")) -> Support Cost | AA133: =IF(IFERROR(INDEX(WBS_Dictionary!K$2:K$1212, MATCH(Table2[[#This Row],[WBS_ID]], Table26[WBS CODE],0)), "") = "", "null", IFERROR(INDEX(WBS_Dictionary!K$2:K$1212, MATCH(Table2[[#This Row],[WBS_ID]], Table26[WBS CODE],0)), "")) -> Well Insurance | AB133: =IF(IFERROR(INDEX(WBS_Dictionary!L$2:L$1212, MATCH(Table2[[#This Row],[WBS_ID]], Table26[WBS CODE],0)), "") = "", "null", IFERROR(INDEX(WBS_Dictionary!L$2:L$1212, MATCH(Table2[[#This Row],[WBS_ID]], Table26[WBS CODE],0)), "")) -> Well Insurance | ... AE133: =IF(IFERROR(INDEX(WBS_Dictionary!O$2:O$1212, MATCH(Table2[[#This Row],[WBS_ID]], Table26[WBS CODE],0)), "") = "", "null", IFERROR(INDEX(WBS_Dictionary!O$2:O$1212, MATCH(Table2[[#This Row],[WBS_ID]], Table26[WBS CODE],0)), "")) -> Well
A134: 133 | B134: 04 | C134: Insurance AWI 21-8 | D134: E540-301297907-D245401 | E134: D245401 | F134: 38467 | G134: USD | H134: 38467 | I134: USD | J134: 0 | K134: USD | L134: 0 | M134: USD | N134: 14315.08 | O134: USD | Q134: X | R134: STAR ENERGY | S134: Production | T134: REL BUDG AVAC // BUDG | U134: =IF(IFERROR(INDEX(WBS_Dictionary!E$2:E$1212, MATCH(Table2[[#This Row],[WBS_ID]], Table26[WBS CODE],0)), "") = "", "null", IFERROR(INDEX(WBS_Dictionary!E$2:E$1212, MATCH(Table2[[#This Row],[WBS_ID]], Table26[WBS CODE],0)), "")) -> E540-30-D245401 | V134: =IF(IFERROR(INDEX(WBS_Dictionary!F$2:F$1212, MATCH(Table2[[#This Row],[WBS_ID]], Table26[WBS CODE],0)), "") = "", "null", IFERROR(INDEX(WBS_Dictionary!F$2:F$1212, MATCH(Table2[[#This Row],[WBS_ID]], Table26[WBS CODE],0)), "")) -> E540-30129-D245401 | W134: =IF(IFERROR(INDEX(WBS_Dictionary!G$2:G$1212, MATCH(Table2[[#This Row],[WBS_ID]], Table26[WBS CODE],0)), "") = "", "null", IFERROR(INDEX(WBS_Dictionary!G$2:G$1212, MATCH(Table2[[#This Row],[WBS_ID]], Table26[WBS CODE],0)), "")) -> E540-3012979-D245401 | X134: =IF(IFERROR(INDEX(WBS_Dictionary!H$2:H$1212, MATCH(Table2[[#This Row],[WBS_ID]], Table26[WBS CODE],0)), "") = "", "null", IFERROR(INDEX(WBS_Dictionary!H$2:H$1212, MATCH(Table2[[#This Row],[WBS_ID]], Table26[WBS CODE],0)), "")) -> E540-301297907-D245401 | Y134: =IF(IFERROR(INDEX(WBS_Dictionary!I$2:I$1212, MATCH(Table2[[#This Row],[WBS_ID]], Table26[WBS CODE],0)), "") = "", "null", IFERROR(INDEX(WBS_Dictionary!I$2:I$1212, MATCH(Table2[[#This Row],[WBS_ID]], Table26[WBS CODE],0)), "")) -> null | Z134: =IF(IFERROR(INDEX(WBS_Dictionary!J$2:J$1212, MATCH(Table2[[#This Row],[WBS_ID]], Table26[WBS CODE],0)), "") = "", "null", IFERROR(INDEX(WBS_Dictionary!J$2:J$1212, MATCH(Table2[[#This Row],[WBS_ID]], Table26[WBS CODE],0)), "")) -> Support Cost | AA134: =IF(IFERROR(INDEX(WBS_Dictionary!K$2:K$1212, MATCH(Table2[[#This Row],[WBS_ID]], Table26[WBS CODE],0)), "") = "", "null", IFERROR(INDEX(WBS_Dictionary!K$2:K$1212, MATCH(Table2[[#This Row],[WBS_ID]], Table26[WBS CODE],0)), "")) -> Well Insurance | AB134: =IF(IFERROR(INDEX(WBS_Dictionary!L$2:L$1212, MATCH(Table2[[#This Row],[WBS_ID]], Table26[WBS CODE],0)), "") = "", "null", IFERROR(INDEX(WBS_Dictionary!L$2:L$1212, MATCH(Table2[[#This Row],[WBS_ID]], Table26[WBS CODE],0)), "")) -> Well Insurance | ... AE134: =IF(IFERROR(INDEX(WBS_Dictionary!O$2:O$1212, MATCH(Table2[[#This Row],[WBS_ID]], Table26[WBS CODE],0)), "") = "", "null", IFERROR(INDEX(WBS_Dictionary!O$2:O$1212, MATCH(Table2[[#This Row],[WBS_ID]], Table26[WBS CODE],0)), "")) -> Well
A135: 134 | B135: 05 | C135: Insurance AWI 21-8 | D135: E540-30129790707-D245401 | E135: D245401 | F135: 0 | G135: USD | H135: 0 | I135: USD | J135: 0 | K135: USD | L135: 0 | M135: USD | N135: 14315.08 | O135: USD | Q135: X | R135: STAR ENERGY | S135: Production | T135: REL AVAC SETC // BUDG | U135: =IF(IFERROR(INDEX(WBS_Dictionary!E$2:E$1212, MATCH(Table2[[#This Row],[WBS_ID]], Table26[WBS CODE],0)), "") = "", "null", IFERROR(INDEX(WBS_Dictionary!E$2:E$1212, MATCH(Table2[[#This Row],[WBS_ID]], Table26[WBS CODE],0)), "")) -> E540-30-D245401 | V135: =IF(IFERROR(INDEX(WBS_Dictionary!F$2:F$1212, MATCH(Table2[[#This Row],[WBS_ID]], Table26[WBS CODE],0)), "") = "", "null", IFERROR(INDEX(WBS_Dictionary!F$2:F$1212, MATCH(Table2[[#This Row],[WBS_ID]], Table26[WBS CODE],0)), "")) -> E540-30129-D245401 | W135: =IF(IFERROR(INDEX(WBS_Dictionary!G$2:G$1212, MATCH(Table2[[#This Row],[WBS_ID]], Table26[WBS CODE],0)), "") = "", "null", IFERROR(INDEX(WBS_Dictionary!G$2:G$1212, MATCH(Table2[[#This Row],[WBS_ID]], Table26[WBS CODE],0)), "")) -> E540-3012979-D245401 | X135: =IF(IFERROR(INDEX(WBS_Dictionary!H$2:H$1212, MATCH(Table2[[#This Row],[WBS_ID]], Table26[WBS CODE],0)), "") = "", "null", IFERROR(INDEX(WBS_Dictionary!H$2:H$1212, MATCH(Table2[[#This Row],[WBS_ID]], Table26[WBS CODE],0)), "")) -> E540-301297907-D245401 | Y135: =IF(IFERROR(INDEX(WBS_Dictionary!I$2:I$1212, MATCH(Table2[[#This Row],[WBS_ID]], Table26[WBS CODE],0)), "") = "", "null", IFERROR(INDEX(WBS_Dictionary!I$2:I$1212, MATCH(Table2[[#This Row],[WBS_ID]], Table26[WBS CODE],0)), "")) -> E540-30129790707-D245401 | Z135: =IF(IFERROR(INDEX(WBS_Dictionary!J$2:J$1212, MATCH(Table2[[#This Row],[WBS_ID]], Table26[WBS CODE],0)), "") = "", "null", IFERROR(INDEX(WBS_Dictionary!J$2:J$1212, MATCH(Table2[[#This Row],[WBS_ID]], Table26[WBS CODE],0)), "")) -> Support Cost | AA135: =IF(IFERROR(INDEX(WBS_Dictionary!K$2:K$1212, MATCH(Table2[[#This Row],[WBS_ID]], Table26[WBS CODE],0)), "") = "", "null", IFERROR(INDEX(WBS_Dictionary!K$2:K$1212, MATCH(Table2[[#This Row],[WBS_ID]], Table26[WBS CODE],0)), "")) -> Well Insurance | AB135: =IF(IFERROR(INDEX(WBS_Dictionary!L$2:L$1212, MATCH(Table2[[#This Row],[WBS_ID]], Table26[WBS CODE],0)), "") = "", "null", IFERROR(INDEX(WBS_Dictionary!L$2:L$1212, MATCH(Table2[[#This Row],[WBS_ID]], Table26[WBS CODE],0)), "")) -> Well Insurance | ... AE135: =IF(IFERROR(INDEX(WBS_Dictionary!O$2:O$1212, MATCH(Table2[[#This Row],[WBS_ID]], Table26[WBS CODE],0)), "") = "", "null", IFERROR(INDEX(WBS_Dictionary!O$2:O$1212, MATCH(Table2[[#This Row],[WBS_ID]], Table26[WBS CODE],0)), "")) -> Well
A136: 135 | B136: 04 | C136: Insurance AWI 3-9 | D136: E540-301297906-D245401 | E136: D245401 | F136: 38467 | G136: USD | H136: 38467 | I136: USD | J136: 0 | K136: USD | L136: 0 | M136: USD | N136: 19416.27 | O136: USD | Q136: X | R136: STAR ENERGY | S136: Production | T136: REL BUDG AVAC // BUDG | U136: =IF(IFERROR(INDEX(WBS_Dictionary!E$2:E$1212, MATCH(Table2[[#This Row],[WBS_ID]], Table26[WBS CODE],0)), "") = "", "null", IFERROR(INDEX(WBS_Dictionary!E$2:E$1212, MATCH(Table2[[#This Row],[WBS_ID]], Table26[WBS CODE],0)), "")) -> E540-30-D245401 | V136: =IF(IFERROR(INDEX(WBS_Dictionary!F$2:F$1212, MATCH(Table2[[#This Row],[WBS_ID]], Table26[WBS CODE],0)), "") = "", "null", IFERROR(INDEX(WBS_Dictionary!F$2:F$1212, MATCH(Table2[[#This Row],[WBS_ID]], Table26[WBS CODE],0)), "")) -> E540-30129-D245401 | W136: =IF(IFERROR(INDEX(WBS_Dictionary!G$2:G$1212, MATCH(Table2[[#This Row],[WBS_ID]], Table26[WBS CODE],0)), "") = "", "null", IFERROR(INDEX(WBS_Dictionary!G$2:G$1212, MATCH(Table2[[#This Row],[WBS_ID]], Table26[WBS CODE],0)), "")) -> E540-3012979-D245401 | X136: =IF(IFERROR(INDEX(WBS_Dictionary!H$2:H$1212, MATCH(Table2[[#This Row],[WBS_ID]], Table26[WBS CODE],0)), "") = "", "null", IFERROR(INDEX(WBS_Dictionary!H$2:H$1212, MATCH(Table2[[#This Row],[WBS_ID]], Table26[WBS CODE],0)), "")) -> E540-301297906-D245401 | Y136: =IF(IFERROR(INDEX(WBS_Dictionary!I$2:I$1212, MATCH(Table2[[#This Row],[WBS_ID]], Table26[WBS CODE],0)), "") = "", "null", IFERROR(INDEX(WBS_Dictionary!I$2:I$1212, MATCH(Table2[[#This Row],[WBS_ID]], Table26[WBS CODE],0)), "")) -> null | Z136: =IF(IFERROR(INDEX(WBS_Dictionary!J$2:J$1212, MATCH(Table2[[#This Row],[WBS_ID]], Table26[WBS CODE],0)), "") = "", "null", IFERROR(INDEX(WBS_Dictionary!J$2:J$1212, MATCH(Table2[[#This Row],[WBS_ID]], Table26[WBS CODE],0)), "")) -> Support Cost | AA136: =IF(IFERROR(INDEX(WBS_Dictionary!K$2:K$1212, MATCH(Table2[[#This Row],[WBS_ID]], Table26[WBS CODE],0)), "") = "", "null", IFERROR(INDEX(WBS_Dictionary!K$2:K$1212, MATCH(Table2[[#This Row],[WBS_ID]], Table26[WBS CODE],0)), "")) -> Well Insurance | AB136: =IF(IFERROR(INDEX(WBS_Dictionary!L$2:L$1212, MATCH(Table2[[#This Row],[WBS_ID]], Table26[WBS CODE],0)), "") = "", "null", IFERROR(INDEX(WBS_Dictionary!L$2:L$1212, MATCH(Table2[[#This Row],[WBS_ID]], Table26[WBS CODE],0)), "")) -> Well Insurance | ... AE136: =IF(IFERROR(INDEX(WBS_Dictionary!O$2:O$1212, MATCH(Table2[[#This Row],[WBS_ID]], Table26[WBS CODE],0)), "") = "", "null", IFERROR(INDEX(WBS_Dictionary!O$2:O$1212, MATCH(Table2[[#This Row],[WBS_ID]], Table26[WBS CODE],0)), "")) -> Well
A137: 136 | B137: 05 | C137: Insurance AWI 3-9 | D137: E540-30129790606-D245401 | E137: D245401 | F137: 0 | G137: USD | H137: 0 | I137: USD | J137: 0 | K137: USD | L137: 0 | M137: USD | N137: 19416.27 | O137: USD | Q137: X | R137: STAR ENERGY | S137: Production | T137: REL AVAC SETC // BUDG | U137: =IF(IFERROR(INDEX(WBS_Dictionary!E$2:E$1212, MATCH(Table2[[#This Row],[WBS_ID]], Table26[WBS CODE],0)), "") = "", "null", IFERROR(INDEX(WBS_Dictionary!E$2:E$1212, MATCH(Table2[[#This Row],[WBS_ID]], Table26[WBS CODE],0)), "")) -> E540-30-D245401 | V137: =IF(IFERROR(INDEX(WBS_Dictionary!F$2:F$1212, MATCH(Table2[[#This Row],[WBS_ID]], Table26[WBS CODE],0)), "") = "", "null", IFERROR(INDEX(WBS_Dictionary!F$2:F$1212, MATCH(Table2[[#This Row],[WBS_ID]], Table26[WBS CODE],0)), "")) -> E540-30129-D245401 | W137: =IF(IFERROR(INDEX(WBS_Dictionary!G$2:G$1212, MATCH(Table2[[#This Row],[WBS_ID]], Table26[WBS CODE],0)), "") = "", "null", IFERROR(INDEX(WBS_Dictionary!G$2:G$1212, MATCH(Table2[[#This Row],[WBS_ID]], Table26[WBS CODE],0)), "")) -> E540-3012979-D245401 | X137: =IF(IFERROR(INDEX(WBS_Dictionary!H$2:H$1212, MATCH(Table2[[#This Row],[WBS_ID]], Table26[WBS CODE],0)), "") = "", "null", IFERROR(INDEX(WBS_Dictionary!H$2:H$1212, MATCH(Table2[[#This Row],[WBS_ID]], Table26[WBS CODE],0)), "")) -> E540-301297906-D245401 | Y137: =IF(IFERROR(INDEX(WBS_Dictionary!I$2:I$1212, MATCH(Table2[[#This Row],[WBS_ID]], Table26[WBS CODE],0)), "") = "", "null", IFERROR(INDEX(WBS_Dictionary!I$2:I$1212, MATCH(Table2[[#This Row],[WBS_ID]], Table26[WBS CODE],0)), "")) -> E540-30129790606-D245401 | Z137: =IF(IFERROR(INDEX(WBS_Dictionary!J$2:J$1212, MATCH(Table2[[#This Row],[WBS_ID]], Table26[WBS CODE],0)), "") = "", "null", IFERROR(INDEX(WBS_Dictionary!J$2:J$1212, MATCH(Table2[[#This Row],[WBS_ID]], Table26[WBS CODE],0)), "")) -> Support Cost | AA137: =IF(IFERROR(INDEX(WBS_Dictionary!K$2:K$1212, MATCH(Table2[[#This Row],[WBS_ID]], Table26[WBS CODE],0)), "") = "", "null", IFERROR(INDEX(WBS_Dictionary!K$2:K$1212, MATCH(Table2[[#This Row],[WBS_ID]], Table26[WBS CODE],0)), "")) -> Well Insurance | AB137: =IF(IFERROR(INDEX(WBS_Dictionary!L$2:L$1212, MATCH(Table2[[#This Row],[WBS_ID]], Table26[WBS CODE],0)), "") = "", "null", IFERROR(INDEX(WBS_Dictionary!L$2:L$1212, MATCH(Table2[[#This Row],[WBS_ID]], Table26[WBS CODE],0)), "")) -> Well Insurance | ... AE137: =IF(IFERROR(INDEX(WBS_Dictionary!O$2:O$1212, MATCH(Table2[[#This Row],[WBS_ID]], Table26[WBS CODE],0)), "") = "", "null", IFERROR(INDEX(WBS_Dictionary!O$2:O$1212, MATCH(Table2[[#This Row],[WBS_ID]], Table26[WBS CODE],0)), "")) -> Well
... A525: 524 | B525: 05 | C525: Casing AWI 2-7 ML | D525: E540-30101026101-D245401 | E525: D245401 | F525: 0 | G525: USD | H525: 0 | I525: USD | J525: 0 | K525: USD | L525: 3153.96 | M525: USD | N525: 725447.72 | O525: USD | Q525: X | R525: STAR ENERGY | S525: Production | T525: REL AVAC SETC // BUDG | U525: =IF(IFERROR(INDEX(WBS_Dictionary!E$2:E$1212, MATCH(Table2[[#This Row],[WBS_ID]], Table26[WBS CODE],0)), "") = "", "null", IFERROR(INDEX(WBS_Dictionary!E$2:E$1212, MATCH(Table2[[#This Row],[WBS_ID]], Table26[WBS CODE],0)), "")) -> E540-30-D245401 | V525: =IF(IFERROR(INDEX(WBS_Dictionary!F$2:F$1212, MATCH(Table2[[#This Row],[WBS_ID]], Table26[WBS CODE],0)), "") = "", "null", IFERROR(INDEX(WBS_Dictionary!F$2:F$1212, MATCH(Table2[[#This Row],[WBS_ID]], Table26[WBS CODE],0)), "")) -> E540-30101-D245401 | W525: =IF(IFERROR(INDEX(WBS_Dictionary!G$2:G$1212, MATCH(Table2[[#This Row],[WBS_ID]], Table26[WBS CODE],0)), "") = "", "null", IFERROR(INDEX(WBS_Dictionary!G$2:G$1212, MATCH(Table2[[#This Row],[WBS_ID]], Table26[WBS CODE],0)), "")) -> E540-3010102-D245401 | X525: =IF(IFERROR(INDEX(WBS_Dictionary!H$2:H$1212, MATCH(Table2[[#This Row],[WBS_ID]], Table26[WBS CODE],0)), "") = "", "null", IFERROR(INDEX(WBS_Dictionary!H$2:H$1212, MATCH(Table2[[#This Row],[WBS_ID]], Table26[WBS CODE],0)), "")) -> E540-301010261-D245401 | Y525: =IF(IFERROR(INDEX(WBS_Dictionary!I$2:I$1212, MATCH(Table2[[#This Row],[WBS_ID]], Table26[WBS CODE],0)), "") = "", "null", IFERROR(INDEX(WBS_Dictionary!I$2:I$1212, MATCH(Table2[[#This Row],[WBS_ID]], Table26[WBS CODE],0)), "")) -> E540-30101026101-D245401 | Z525: =IF(IFERROR(INDEX(WBS_Dictionary!J$2:J$1212, MATCH(Table2[[#This Row],[WBS_ID]], Table26[WBS CODE],0)), "") = "", "null", IFERROR(INDEX(WBS_Dictionary!J$2:J$1212, MATCH(Table2[[#This Row],[WBS_ID]], Table26[WBS CODE],0)), "")) -> Drilling Cost | AA525: =IF(IFERROR(INDEX(WBS_Dictionary!K$2:K$1212, MATCH(Table2[[#This Row],[WBS_ID]], Table26[WBS CODE],0)), "") = "", "null", IFERROR(INDEX(WBS_Dictionary!K$2:K$1212, MATCH(Table2[[#This Row],[WBS_ID]], Table26[WBS CODE],0)), "")) -> Well Cost | AB525: =IF(IFERROR(INDEX(WBS_Dictionary!L$2:L$1212, MATCH(Table2[[#This Row],[WBS_ID]], Table26[WBS CODE],0)), "") = "", "null", IFERROR(INDEX(WBS_Dictionary!L$2:L$1212, MATCH(Table2[[#This Row],[WBS_ID]], Table26[WBS CODE],0)), "")) -> Material - LL | ... AE525: =IF(IFERROR(INDEX(WBS_Dictionary!O$2:O$1212, MATCH(Table2[[#This Row],[WBS_ID]], Table26[WBS CODE],0)), "") = "", "null", IFERROR(INDEX(WBS_Dictionary!O$2:O$1212, MATCH(Table2[[#This Row],[WBS_ID]], Table26[WBS CODE],0)), "")) -> Well
A526: 1 | B526: 00 | C526: Darajat Projects 2022 | D526: 1E53022 | F526: 35164286 | G526: USD | H526: 33472052 | I526: USD | J526: 0 | K526: USD | L526: 34172.87 | M526: USD | N526: 30669525 | O526: USD | R526: STAR ENERGY | T526: PREL | U526: =IF(IFERROR(INDEX(WBS_Dictionary!E$2:E$1212, MATCH(Table2[[#This Row],[WBS_ID]], Table26[WBS CODE],0)), "") = "", "null", IFERROR(INDEX(WBS_Dictionary!E$2:E$1212, MATCH(Table2[[#This Row],[WBS_ID]], Table26[WBS CODE],0)), "")) -> null | V526: =IF(IFERROR(INDEX(WBS_Dictionary!F$2:F$1212, MATCH(Table2[[#This Row],[WBS_ID]], Table26[WBS CODE],0)), "") = "", "null", IFERROR(INDEX(WBS_Dictionary!F$2:F$1212, MATCH(Table2[[#This Row],[WBS_ID]], Table26[WBS CODE],0)), "")) -> null | W526: =IF(IFERROR(INDEX(WBS_Dictionary!G$2:G$1212, MATCH(Table2[[#This Row],[WBS_ID]], Table26[WBS CODE],0)), "") = "", "null", IFERROR(INDEX(WBS_Dictionary!G$2:G$1212, MATCH(Table2[[#This Row],[WBS_ID]], Table26[WBS CODE],0)), "")) -> null | X526: =IF(IFERROR(INDEX(WBS_Dictionary!H$2:H$1212, MATCH(Table2[[#This Row],[WBS_ID]], Table26[WBS CODE],0)), "") = "", "null", IFERROR(INDEX(WBS_Dictionary!H$2:H$1212, MATCH(Table2[[#This Row],[WBS_ID]], Table26[WBS CODE],0)), "")) -> null | Y526: =IF(IFERROR(INDEX(WBS_Dictionary!I$2:I$1212, MATCH(Table2[[#This Row],[WBS_ID]], Table26[WBS CODE],0)), "") = "", "null", IFERROR(INDEX(WBS_Dictionary!I$2:I$1212, MATCH(Table2[[#This Row],[WBS_ID]], Table26[WBS CODE],0)), "")) -> null | Z526: =IF(IFERROR(INDEX(WBS_Dictionary!J$2:J$1212, MATCH(Table2[[#This Row],[WBS_ID]], Table26[WBS CODE],0)), "") = "", "null", IFERROR(INDEX(WBS_Dictionary!J$2:J$1212, MATCH(Table2[[#This Row],[WBS_ID]], Table26[WBS CODE],0)), "")) -> null | AA526: =IF(IFERROR(INDEX(WBS_Dictionary!K$2:K$1212, MATCH(Table2[[#This Row],[WBS_ID]], Table26[WBS CODE],0)), "") = "", "null", IFERROR(INDEX(WBS_Dictionary!K$2:K$1212, MATCH(Table2[[#This Row],[WBS_ID]], Table26[WBS CODE],0)), "")) -> null | AB526: =IF(IFERROR(INDEX(WBS_Dictionary!L$2:L$1212, MATCH(Table2[[#This Row],[WBS_ID]], Table26[WBS CODE],0)), "") = "", "null", IFERROR(INDEX(WBS_Dictionary!L$2:L$1212, MATCH(Table2[[#This Row],[WBS_ID]], Table26[WBS CODE],0)), "")) -> null | ... AE526: =IF(IFERROR(INDEX(WBS_Dictionary!O$2:O$1212, MATCH(Table2[[#This Row],[WBS_ID]], Table26[WBS CODE],0)), "") = "", "null", IFERROR(INDEX(WBS_Dictionary!O$2:O$1212, MATCH(Table2[[#This Row],[WBS_ID]], Table26[WBS CODE],0)), "")) -> null
A527: 2 | B527: 01 | C527: DRJ Drilling MUW 2022 | D527: E530-30-D225301 | E527: D225301 | F527: 35164286 | G527: USD | H527: 33472052 | I527: USD | J527: 0 | K527: USD | L527: 34172.87 | M527: USD | N527: 30669525 | O527: USD | Q527: X | R527: STAR ENERGY | S527: PRODUCTION | T527: REL LKD BUDG AVAC // REL | U527: =IF(IFERROR(INDEX(WBS_Dictionary!E$2:E$1212, MATCH(Table2[[#This Row],[WBS_ID]], Table26[WBS CODE],0)), "") = "", "null", IFERROR(INDEX(WBS_Dictionary!E$2:E$1212, MATCH(Table2[[#This Row],[WBS_ID]], Table26[WBS CODE],0)), "")) -> E530-30-D225301 | V527: =IF(IFERROR(INDEX(WBS_Dictionary!F$2:F$1212, MATCH(Table2[[#This Row],[WBS_ID]], Table26[WBS CODE],0)), "") = "", "null", IFERROR(INDEX(WBS_Dictionary!F$2:F$1212, MATCH(Table2[[#This Row],[WBS_ID]], Table26[WBS CODE],0)), "")) -> null | W527: =IF(IFERROR(INDEX(WBS_Dictionary!G$2:G$1212, MATCH(Table2[[#This Row],[WBS_ID]], Table26[WBS CODE],0)), "") = "", "null", IFERROR(INDEX(WBS_Dictionary!G$2:G$1212, MATCH(Table2[[#This Row],[WBS_ID]], Table26[WBS CODE],0)), "")) -> null | X527: =IF(IFERROR(INDEX(WBS_Dictionary!H$2:H$1212, MATCH(Table2[[#This Row],[WBS_ID]], Table26[WBS CODE],0)), "") = "", "null", IFERROR(INDEX(WBS_Dictionary!H$2:H$1212, MATCH(Table2[[#This Row],[WBS_ID]], Table26[WBS CODE],0)), "")) -> null | Y527: =IF(IFERROR(INDEX(WBS_Dictionary!I$2:I$1212, MATCH(Table2[[#This Row],[WBS_ID]], Table26[WBS CODE],0)), "") = "", "null", IFERROR(INDEX(WBS_Dictionary!I$2:I$1212, MATCH(Table2[[#This Row],[WBS_ID]], Table26[WBS CODE],0)), "")) -> null | Z527: =IF(IFERROR(INDEX(WBS_Dictionary!J$2:J$1212, MATCH(Table2[[#This Row],[WBS_ID]], Table26[WBS CODE],0)), "") = "", "null", IFERROR(INDEX(WBS_Dictionary!J$2:J$1212, MATCH(Table2[[#This Row],[WBS_ID]], Table26[WBS CODE],0)), "")) -> null | AA527: =IF(IFERROR(INDEX(WBS_Dictionary!K$2:K$1212, MATCH(Table2[[#This Row],[WBS_ID]], Table26[WBS CODE],0)), "") = "", "null", IFERROR(INDEX(WBS_Dictionary!K$2:K$1212, MATCH(Table2[[#This Row],[WBS_ID]], Table26[WBS CODE],0)), "")) -> null | AB527: =IF(IFERROR(INDEX(WBS_Dictionary!L$2:L$1212, MATCH(Table2[[#This Row],[WBS_ID]], Table26[WBS CODE],0)), "") = "", "null", IFERROR(INDEX(WBS_Dictionary!L$2:L$1212, MATCH(Table2[[#This Row],[WBS_ID]], Table26[WBS CODE],0)), "")) -> null | ... AE527: =IF(IFERROR(INDEX(WBS_Dictionary!O$2:O$1212, MATCH(Table2[[#This Row],[WBS_ID]], Table26[WBS CODE],0)), "") = "", "null", IFERROR(INDEX(WBS_Dictionary!O$2:O$1212, MATCH(Table2[[#This Row],[WBS_ID]], Table26[WBS CODE],0)), "")) -> null
A528: 3 | B528: 02 | C528: Support Cost | D528: E530-30129-D225301 | E528: D225301 | F528: 2245889.2 | G528: USD | H528: 2245888.8 | I528: USD | J528: 0 | K528: USD | L528: 0 | M528: USD | N528: 1945666.6 | O528: USD | Q528: X | R528: STAR ENERGY | S528: Production | T528: REL LKD BUDG AVAC // REL | U528: =IF(IFERROR(INDEX(WBS_Dictionary!E$2:E$1212, MATCH(Table2[[#This Row],[WBS_ID]], Table26[WBS CODE],0)), "") = "", "null", IFERROR(INDEX(WBS_Dictionary!E$2:E$1212, MATCH(Table2[[#This Row],[WBS_ID]], Table26[WBS CODE],0)), "")) -> E530-30-D225301 | V528: =IF(IFERROR(INDEX(WBS_Dictionary!F$2:F$1212, MATCH(Table2[[#This Row],[WBS_ID]], Table26[WBS CODE],0)), "") = "", "null", IFERROR(INDEX(WBS_Dictionary!F$2:F$1212, MATCH(Table2[[#This Row],[WBS_ID]], Table26[WBS CODE],0)), "")) -> E530-30129-D225301 | W528: =IF(IFERROR(INDEX(WBS_Dictionary!G$2:G$1212, MATCH(Table2[[#This Row],[WBS_ID]], Table26[WBS CODE],0)), "") = "", "null", IFERROR(INDEX(WBS_Dictionary!G$2:G$1212, MATCH(Table2[[#This Row],[WBS_ID]], Table26[WBS CODE],0)), "")) -> null | X528: =IF(IFERROR(INDEX(WBS_Dictionary!H$2:H$1212, MATCH(Table2[[#This Row],[WBS_ID]], Table26[WBS CODE],0)), "") = "", "null", IFERROR(INDEX(WBS_Dictionary!H$2:H$1212, MATCH(Table2[[#This Row],[WBS_ID]], Table26[WBS CODE],0)), "")) -> null | Y528: =IF(IFERROR(INDEX(WBS_Dictionary!I$2:I$1212, MATCH(Table2[[#This Row],[WBS_ID]], Table26[WBS CODE],0)), "") = "", "null", IFERROR(INDEX(WBS_Dictionary!I$2:I$1212, MATCH(Table2[[#This Row],[WBS_ID]], Table26[WBS CODE],0)), "")) -> null | Z528: =IF(IFERROR(INDEX(WBS_Dictionary!J$2:J$1212, MATCH(Table2[[#This Row],[WBS_ID]], Table26[WBS CODE],0)), "") = "", "null", IFERROR(INDEX(WBS_Dictionary!J$2:J$1212, MATCH(Table2[[#This Row],[WBS_ID]], Table26[WBS CODE],0)), "")) -> Support Cost | AA528: =IF(IFERROR(INDEX(WBS_Dictionary!K$2:K$1212, MATCH(Table2[[#This Row],[WBS_ID]], Table26[WBS CODE],0)), "") = "", "null", IFERROR(INDEX(WBS_Dictionary!K$2:K$1212, MATCH(Table2[[#This Row],[WBS_ID]], Table26[WBS CODE],0)), "")) -> null | AB528: =IF(IFERROR(INDEX(WBS_Dictionary!L$2:L$1212, MATCH(Table2[[#This Row],[WBS_ID]], Table26[WBS CODE],0)), "") = "", "null", IFERROR(INDEX(WBS_Dictionary!L$2:L$1212, MATCH(Table2[[#This Row],[WBS_ID]], Table26[WBS CODE],0)), "")) -> null | ... AE528: =IF(IFERROR(INDEX(WBS_Dictionary!O$2:O$1212, MATCH(Table2[[#This Row],[WBS_ID]], Table26[WBS CODE],0)), "") = "", "null", IFERROR(INDEX(WBS_Dictionary!O$2:O$1212, MATCH(Table2[[#This Row],[WBS_ID]], Table26[WBS CODE],0)), "")) -> null
A529: 4 | B529: 03 | C529: IT+ Communication | D529: E530-3012982-D225301 | E529: D225301 | F529: 15604 | G529: USD | H529: 15604 | I529: USD | J529: 0 | K529: USD | L529: 0 | M529: USD | N529: 5049.74 | O529: USD | Q529: X | R529: STAR ENERGY | S529: Production | T529: REL LKD BUDG AVAC // BUDG | U529: =IF(IFERROR(INDEX(WBS_Dictionary!E$2:E$1212, MATCH(Table2[[#This Row],[WBS_ID]], Table26[WBS CODE],0)), "") = "", "null", IFERROR(INDEX(WBS_Dictionary!E$2:E$1212, MATCH(Table2[[#This Row],[WBS_ID]], Table26[WBS CODE],0)), "")) -> E530-30-D225301 | V529: =IF(IFERROR(INDEX(WBS_Dictionary!F$2:F$1212, MATCH(Table2[[#This Row],[WBS_ID]], Table26[WBS CODE],0)), "") = "", "null", IFERROR(INDEX(WBS_Dictionary!F$2:F$1212, MATCH(Table2[[#This Row],[WBS_ID]], Table26[WBS CODE],0)), "")) -> E530-30129-D225301 | W529: =IF(IFERROR(INDEX(WBS_Dictionary!G$2:G$1212, MATCH(Table2[[#This Row],[WBS_ID]], Table26[WBS CODE],0)), "") = "", "null", IFERROR(INDEX(WBS_Dictionary!G$2:G$1212, MATCH(Table2[[#This Row],[WBS_ID]], Table26[WBS CODE],0)), "")) -> E530-3012982-D225301 | X529: =IF(IFERROR(INDEX(WBS_Dictionary!H$2:H$1212, MATCH(Table2[[#This Row],[WBS_ID]], Table26[WBS CODE],0)), "") = "", "null", IFERROR(INDEX(WBS_Dictionary!H$2:H$1212, MATCH(Table2[[#This Row],[WBS_ID]], Table26[WBS CODE],0)), "")) -> null | Y529: =IF(IFERROR(INDEX(WBS_Dictionary!I$2:I$1212, MATCH(Table2[[#This Row],[WBS_ID]], Table26[WBS CODE],0)), "") = "", "null", IFERROR(INDEX(WBS_Dictionary!I$2:I$1212, MATCH(Table2[[#This Row],[WBS_ID]], Table26[WBS CODE],0)), "")) -> null | Z529: =IF(IFERROR(INDEX(WBS_Dictionary!J$2:J$1212, MATCH(Table2[[#This Row],[WBS_ID]], Table26[WBS CODE],0)), "") = "", "null", IFERROR(INDEX(WBS_Dictionary!J$2:J$1212, MATCH(Table2[[#This Row],[WBS_ID]], Table26[WBS CODE],0)), "")) -> Support Cost | AA529: =IF(IFERROR(INDEX(WBS_Dictionary!K$2:K$1212, MATCH(Table2[[#This Row],[WBS_ID]], Table26[WBS CODE],0)), "") = "", "null", IFERROR(INDEX(WBS_Dictionary!K$2:K$1212, MATCH(Table2[[#This Row],[WBS_ID]], Table26[WBS CODE],0)), "")) -> IT & Communication | AB529: =IF(IFERROR(INDEX(WBS_Dictionary!L$2:L$1212, MATCH(Table2[[#This Row],[WBS_ID]], Table26[WBS CODE],0)), "") = "", "null", IFERROR(INDEX(WBS_Dictionary!L$2:L$1212, MATCH(Table2[[#This Row],[WBS_ID]], Table26[WBS CODE],0)), "")) -> null | ... AE529: =IF(IFERROR(INDEX(WBS_Dictionary!O$2:O$1212, MATCH(Table2[[#This Row],[WBS_ID]], Table26[WBS CODE],0)), "") = "", "null", IFERROR(INDEX(WBS_Dictionary!O$2:O$1212, MATCH(Table2[[#This Row],[WBS_ID]], Table26[WBS CODE],0)), "")) -> null
A530: 5 | B530: 04 | C530: Internet and IT Support Service | D530: E530-301298265-D225301 | E530: D225301 | F530: 7925 | G530: USD | H530: 7925 | I530: USD | J530: 0 | K530: USD | L530: 0 | M530: USD | N530: 0 | O530: USD | Q530: X | R530: STAR ENERGY | S530: Production | T530: REL LKD BUDG AVAC // BUDG | U530: =IF(IFERROR(INDEX(WBS_Dictionary!E$2:E$1212, MATCH(Table2[[#This Row],[WBS_ID]], Table26[WBS CODE],0)), "") = "", "null", IFERROR(INDEX(WBS_Dictionary!E$2:E$1212, MATCH(Table2[[#This Row],[WBS_ID]], Table26[WBS CODE],0)), "")) -> E530-30-D225301 | V530: =IF(IFERROR(INDEX(WBS_Dictionary!F$2:F$1212, MATCH(Table2[[#This Row],[WBS_ID]], Table26[WBS CODE],0)), "") = "", "null", IFERROR(INDEX(WBS_Dictionary!F$2:F$1212, MATCH(Table2[[#This Row],[WBS_ID]], Table26[WBS CODE],0)), "")) -> E530-30129-D225301 | W530: =IF(IFERROR(INDEX(WBS_Dictionary!G$2:G$1212, MATCH(Table2[[#This Row],[WBS_ID]], Table26[WBS CODE],0)), "") = "", "null", IFERROR(INDEX(WBS_Dictionary!G$2:G$1212, MATCH(Table2[[#This Row],[WBS_ID]], Table26[WBS CODE],0)), "")) -> E530-3012982-D225301 | X530: =IF(IFERROR(INDEX(WBS_Dictionary!H$2:H$1212, MATCH(Table2[[#This Row],[WBS_ID]], Table26[WBS CODE],0)), "") = "", "null", IFERROR(INDEX(WBS_Dictionary!H$2:H$1212, MATCH(Table2[[#This Row],[WBS_ID]], Table26[WBS CODE],0)), "")) -> E530-301298265-D225301 | Y530: =IF(IFERROR(INDEX(WBS_Dictionary!I$2:I$1212, MATCH(Table2[[#This Row],[WBS_ID]], Table26[WBS CODE],0)), "") = "", "null", IFERROR(INDEX(WBS_Dictionary!I$2:I$1212, MATCH(Table2[[#This Row],[WBS_ID]], Table26[WBS CODE],0)), "")) -> null | Z530: =IF(IFERROR(INDEX(WBS_Dictionary!J$2:J$1212, MATCH(Table2[[#This Row],[WBS_ID]], Table26[WBS CODE],0)), "") = "", "null", IFERROR(INDEX(WBS_Dictionary!J$2:J$1212, MATCH(Table2[[#This Row],[WBS_ID]], Table26[WBS CODE],0)), "")) -> Support Cost | AA530: =IF(IFERROR(INDEX(WBS_Dictionary!K$2:K$1212, MATCH(Table2[[#This Row],[WBS_ID]], Table26[WBS CODE],0)), "") = "", "null", IFERROR(INDEX(WBS_Dictionary!K$2:K$1212, MATCH(Table2[[#This Row],[WBS_ID]], Table26[WBS CODE],0)), "")) -> IT & Communication | AB530: =IF(IFERROR(INDEX(WBS_Dictionary!L$2:L$1212, MATCH(Table2[[#This Row],[WBS_ID]], Table26[WBS CODE],0)), "") = "", "null", IFERROR(INDEX(WBS_Dictionary!L$2:L$1212, MATCH(Table2[[#This Row],[WBS_ID]], Table26[WBS CODE],0)), "")) -> Internet and IT Support Service | ... AE530: =IF(IFERROR(INDEX(WBS_Dictionary!O$2:O$1212, MATCH(Table2[[#This Row],[WBS_ID]], Table26[WBS CODE],0)), "") = "", "null", IFERROR(INDEX(WBS_Dictionary!O$2:O$1212, MATCH(Table2[[#This Row],[WBS_ID]], Table26[WBS CODE],0)), "")) -> null
A531: 6 | B531: 05 | C531: Internet and IT Support Service | D531: E530-30129826504-D225301 | E531: D225301 | F531: 0 | G531: USD | H531: 0 | I531: USD | J531: 0 | K531: USD | L531: 0 | M531: USD | N531: 0 | O531: USD | Q531: X | R531: STAR ENERGY | S531: Production | T531: REL LKD AVAC SETC // BUDG | U531: =IF(IFERROR(INDEX(WBS_Dictionary!E$2:E$1212, MATCH(Table2[[#This Row],[WBS_ID]], Table26[WBS CODE],0)), "") = "", "null", IFERROR(INDEX(WBS_Dictionary!E$2:E$1212, MATCH(Table2[[#This Row],[WBS_ID]], Table26[WBS CODE],0)), "")) -> E530-30-D225301 | V531: =IF(IFERROR(INDEX(WBS_Dictionary!F$2:F$1212, MATCH(Table2[[#This Row],[WBS_ID]], Table26[WBS CODE],0)), "") = "", "null", IFERROR(INDEX(WBS_Dictionary!F$2:F$1212, MATCH(Table2[[#This Row],[WBS_ID]], Table26[WBS CODE],0)), "")) -> E530-30129-D225301 | W531: =IF(IFERROR(INDEX(WBS_Dictionary!G$2:G$1212, MATCH(Table2[[#This Row],[WBS_ID]], Table26[WBS CODE],0)), "") = "", "null", IFERROR(INDEX(WBS_Dictionary!G$2:G$1212, MATCH(Table2[[#This Row],[WBS_ID]], Table26[WBS CODE],0)), "")) -> E530-3012982-D225301 | X531: =IF(IFERROR(INDEX(WBS_Dictionary!H$2:H$1212, MATCH(Table2[[#This Row],[WBS_ID]], Table26[WBS CODE],0)), "") = "", "null", IFERROR(INDEX(WBS_Dictionary!H$2:H$1212, MATCH(Table2[[#This Row],[WBS_ID]], Table26[WBS CODE],0)), "")) -> E530-301298265-D225301 | Y531: =IF(IFERROR(INDEX(WBS_Dictionary!I$2:I$1212, MATCH(Table2[[#This Row],[WBS_ID]], Table26[WBS CODE],0)), "") = "", "null", IFERROR(INDEX(WBS_Dictionary!I$2:I$1212, MATCH(Table2[[#This Row],[WBS_ID]], Table26[WBS CODE],0)), "")) -> E530-30129826504-D225301 | Z531: =IF(IFERROR(INDEX(WBS_Dictionary!J$2:J$1212, MATCH(Table2[[#This Row],[WBS_ID]], Table26[WBS CODE],0)), "") = "", "null", IFERROR(INDEX(WBS_Dictionary!J$2:J$1212, MATCH(Table2[[#This Row],[WBS_ID]], Table26[WBS CODE],0)), "")) -> Support Cost | AA531: =IF(IFERROR(INDEX(WBS_Dictionary!K$2:K$1212, MATCH(Table2[[#This Row],[WBS_ID]], Table26[WBS CODE],0)), "") = "", "null", IFERROR(INDEX(WBS_Dictionary!K$2:K$1212, MATCH(Table2[[#This Row],[WBS_ID]], Table26[WBS CODE],0)), "")) -> IT & Communication | AB531: =IF(IFERROR(INDEX(WBS_Dictionary!L$2:L$1212, MATCH(Table2[[#This Row],[WBS_ID]], Table26[WBS CODE],0)), "") = "", "null", IFERROR(INDEX(WBS_Dictionary!L$2:L$1212, MATCH(Table2[[#This Row],[WBS_ID]], Table26[WBS CODE],0)), "")) -> Internet and IT Support Service | ... AE531: =IF(IFERROR(INDEX(WBS_Dictionary!O$2:O$1212, MATCH(Table2[[#This Row],[WBS_ID]], Table26[WBS CODE],0)), "") = "", "null", IFERROR(INDEX(WBS_Dictionary!O$2:O$1212, MATCH(Table2[[#This Row],[WBS_ID]], Table26[WBS CODE],0)), "")) -> null
A532: 7 | B532: 04 | C532: Hardware Supply | D532: E530-301298264-D225301 | E532: D225301 | F532: 7679 | G532: USD | H532: 7679 | I532: USD | J532: 0 | K532: USD | L532: 0 | M532: USD | N532: 5049.74 | O532: USD | Q532: X | R532: STAR ENERGY | S532: Production | T532: REL LKD BUDG AVAC // BUDG | U532: =IF(IFERROR(INDEX(WBS_Dictionary!E$2:E$1212, MATCH(Table2[[#This Row],[WBS_ID]], Table26[WBS CODE],0)), "") = "", "null", IFERROR(INDEX(WBS_Dictionary!E$2:E$1212, MATCH(Table2[[#This Row],[WBS_ID]], Table26[WBS CODE],0)), "")) -> E530-30-D225301 | V532: =IF(IFERROR(INDEX(WBS_Dictionary!F$2:F$1212, MATCH(Table2[[#This Row],[WBS_ID]], Table26[WBS CODE],0)), "") = "", "null", IFERROR(INDEX(WBS_Dictionary!F$2:F$1212, MATCH(Table2[[#This Row],[WBS_ID]], Table26[WBS CODE],0)), "")) -> E530-30129-D225301 | W532: =IF(IFERROR(INDEX(WBS_Dictionary!G$2:G$1212, MATCH(Table2[[#This Row],[WBS_ID]], Table26[WBS CODE],0)), "") = "", "null", IFERROR(INDEX(WBS_Dictionary!G$2:G$1212, MATCH(Table2[[#This Row],[WBS_ID]], Table26[WBS CODE],0)), "")) -> E530-3012982-D225301 | X532: =IF(IFERROR(INDEX(WBS_Dictionary!H$2:H$1212, MATCH(Table2[[#This Row],[WBS_ID]], Table26[WBS CODE],0)), "") = "", "null", IFERROR(INDEX(WBS_Dictionary!H$2:H$1212, MATCH(Table2[[#This Row],[WBS_ID]], Table26[WBS CODE],0)), "")) -> E530-301298264-D225301 | Y532: =IF(IFERROR(INDEX(WBS_Dictionary!I$2:I$1212, MATCH(Table2[[#This Row],[WBS_ID]], Table26[WBS CODE],0)), "") = "", "null", IFERROR(INDEX(WBS_Dictionary!I$2:I$1212, MATCH(Table2[[#This Row],[WBS_ID]], Table26[WBS CODE],0)), "")) -> null | Z532: =IF(IFERROR(INDEX(WBS_Dictionary!J$2:J$1212, MATCH(Table2[[#This Row],[WBS_ID]], Table26[WBS CODE],0)), "") = "", "null", IFERROR(INDEX(WBS_Dictionary!J$2:J$1212, MATCH(Table2[[#This Row],[WBS_ID]], Table26[WBS CODE],0)), "")) -> Support Cost | AA532: =IF(IFERROR(INDEX(WBS_Dictionary!K$2:K$1212, MATCH(Table2[[#This Row],[WBS_ID]], Table26[WBS CODE],0)), "") = "", "null", IFERROR(INDEX(WBS_Dictionary!K$2:K$1212, MATCH(Table2[[#This Row],[WBS_ID]], Table26[WBS CODE],0)), "")) -> IT & Communication | AB532: =IF(IFERROR(INDEX(WBS_Dictionary!L$2:L$1212, MATCH(Table2[[#This Row],[WBS_ID]], Table26[WBS CODE],0)), "") = "", "null", IFERROR(INDEX(WBS_Dictionary!L$2:L$1212, MATCH(Table2[[#This Row],[WBS_ID]], Table26[WBS CODE],0)), "")) -> Hardware Supply | ... AE532: =IF(IFERROR(INDEX(WBS_Dictionary!O$2:O$1212, MATCH(Table2[[#This Row],[WBS_ID]], Table26[WBS CODE],0)), "") = "", "null", IFERROR(INDEX(WBS_Dictionary!O$2:O$1212, MATCH(Table2[[#This Row],[WBS_ID]], Table26[WBS CODE],0)), "")) -> null
A533: 8 | B533: 05 | C533: Hardware Supply | D533: E530-30129826460-D225301 | E533: D225301 | F533: 0 | G533: USD | H533: 0 | I533: USD | J533: 0 | K533: USD | L533: 0 | M533: USD | N533: 5049.74 | O533: USD | Q533: X | R533: STAR ENERGY | S533: Production | T533: REL LKD AVAC SETC // BUDG | U533: =IF(IFERROR(INDEX(WBS_Dictionary!E$2:E$1212, MATCH(Table2[[#This Row],[WBS_ID]], Table26[WBS CODE],0)), "") = "", "null", IFERROR(INDEX(WBS_Dictionary!E$2:E$1212, MATCH(Table2[[#This Row],[WBS_ID]], Table26[WBS CODE],0)), "")) -> E530-30-D225301 | V533: =IF(IFERROR(INDEX(WBS_Dictionary!F$2:F$1212, MATCH(Table2[[#This Row],[WBS_ID]], Table26[WBS CODE],0)), "") = "", "null", IFERROR(INDEX(WBS_Dictionary!F$2:F$1212, MATCH(Table2[[#This Row],[WBS_ID]], Table26[WBS CODE],0)), "")) -> E530-30129-D225301 | W533: =IF(IFERROR(INDEX(WBS_Dictionary!G$2:G$1212, MATCH(Table2[[#This Row],[WBS_ID]], Table26[WBS CODE],0)), "") = "", "null", IFERROR(INDEX(WBS_Dictionary!G$2:G$1212, MATCH(Table2[[#This Row],[WBS_ID]], Table26[WBS CODE],0)), "")) -> E530-3012982-D225301 | X533: =IF(IFERROR(INDEX(WBS_Dictionary!H$2:H$1212, MATCH(Table2[[#This Row],[WBS_ID]], Table26[WBS CODE],0)), "") = "", "null", IFERROR(INDEX(WBS_Dictionary!H$2:H$1212, MATCH(Table2[[#This Row],[WBS_ID]], Table26[WBS CODE],0)), "")) -> E530-301298264-D225301 | Y533: =IF(IFERROR(INDEX(WBS_Dictionary!I$2:I$1212, MATCH(Table2[[#This Row],[WBS_ID]], Table26[WBS CODE],0)), "") = "", "null", IFERROR(INDEX(WBS_Dictionary!I$2:I$1212, MATCH(Table2[[#This Row],[WBS_ID]], Table26[WBS CODE],0)), "")) -> E530-30129826460-D225301 | Z533: =IF(IFERROR(INDEX(WBS_Dictionary!J$2:J$1212, MATCH(Table2[[#This Row],[WBS_ID]], Table26[WBS CODE],0)), "") = "", "null", IFERROR(INDEX(WBS_Dictionary!J$2:J$1212, MATCH(Table2[[#This Row],[WBS_ID]], Table26[WBS CODE],0)), "")) -> Support Cost | AA533: =IF(IFERROR(INDEX(WBS_Dictionary!K$2:K$1212, MATCH(Table2[[#This Row],[WBS_ID]], Table26[WBS CODE],0)), "") = "", "null", IFERROR(INDEX(WBS_Dictionary!K$2:K$1212, MATCH(Table2[[#This Row],[WBS_ID]], Table26[WBS CODE],0)), "")) -> IT & Communication | AB533: =IF(IFERROR(INDEX(WBS_Dictionary!L$2:L$1212, MATCH(Table2[[#This Row],[WBS_ID]], Table26[WBS CODE],0)), "") = "", "null", IFERROR(INDEX(WBS_Dictionary!L$2:L$1212, MATCH(Table2[[#This Row],[WBS_ID]], Table26[WBS CODE],0)), "")) -> Hardware Supply | ... AE533: =IF(IFERROR(INDEX(WBS_Dictionary!O$2:O$1212, MATCH(Table2[[#This Row],[WBS_ID]], Table26[WBS CODE],0)), "") = "", "null", IFERROR(INDEX(WBS_Dictionary!O$2:O$1212, MATCH(Table2[[#This Row],[WBS_ID]], Table26[WBS CODE],0)), "")) -> null
A534: 9 | B534: 03 | C534: Drilling Facilities Support | D534: E530-3012914-D225301 | E534: D225301 | F534: 141559 | G534: USD | H534: 141559 | I534: USD | J534: 0 | K534: USD | L534: 0 | M534: USD | N534: 111242.84 | O534: USD | Q534: X | R534: STAR ENERGY | S534: Production | T534: REL LKD BUDG AVAC // BUDG | U534: =IF(IFERROR(INDEX(WBS_Dictionary!E$2:E$1212, MATCH(Table2[[#This Row],[WBS_ID]], Table26[WBS CODE],0)), "") = "", "null", IFERROR(INDEX(WBS_Dictionary!E$2:E$1212, MATCH(Table2[[#This Row],[WBS_ID]], Table26[WBS CODE],0)), "")) -> E530-30-D225301 | V534: =IF(IFERROR(INDEX(WBS_Dictionary!F$2:F$1212, MATCH(Table2[[#This Row],[WBS_ID]], Table26[WBS CODE],0)), "") = "", "null", IFERROR(INDEX(WBS_Dictionary!F$2:F$1212, MATCH(Table2[[#This Row],[WBS_ID]], Table26[WBS CODE],0)), "")) -> E530-30129-D225301 | W534: =IF(IFERROR(INDEX(WBS_Dictionary!G$2:G$1212, MATCH(Table2[[#This Row],[WBS_ID]], Table26[WBS CODE],0)), "") = "", "null", IFERROR(INDEX(WBS_Dictionary!G$2:G$1212, MATCH(Table2[[#This Row],[WBS_ID]], Table26[WBS CODE],0)), "")) -> E530-3012914-D225301 | X534: =IF(IFERROR(INDEX(WBS_Dictionary!H$2:H$1212, MATCH(Table2[[#This Row],[WBS_ID]], Table26[WBS CODE],0)), "") = "", "null", IFERROR(INDEX(WBS_Dictionary!H$2:H$1212, MATCH(Table2[[#This Row],[WBS_ID]], Table26[WBS CODE],0)), "")) -> null | Y534: =IF(IFERROR(INDEX(WBS_Dictionary!I$2:I$1212, MATCH(Table2[[#This Row],[WBS_ID]], Table26[WBS CODE],0)), "") = "", "null", IFERROR(INDEX(WBS_Dictionary!I$2:I$1212, MATCH(Table2[[#This Row],[WBS_ID]], Table26[WBS CODE],0)), "")) -> null | Z534: =IF(IFERROR(INDEX(WBS_Dictionary!J$2:J$1212, MATCH(Table2[[#This Row],[WBS_ID]], Table26[WBS CODE],0)), "") = "", "null", IFERROR(INDEX(WBS_Dictionary!J$2:J$1212, MATCH(Table2[[#This Row],[WBS_ID]], Table26[WBS CODE],0)), "")) -> Support Cost | AA534: =IF(IFERROR(INDEX(WBS_Dictionary!K$2:K$1212, MATCH(Table2[[#This Row],[WBS_ID]], Table26[WBS CODE],0)), "") = "", "null", IFERROR(INDEX(WBS_Dictionary!K$2:K$1212, MATCH(Table2[[#This Row],[WBS_ID]], Table26[WBS CODE],0)), "")) -> Drilling Facilities Support | AB534: =IF(IFERROR(INDEX(WBS_Dictionary!L$2:L$1212, MATCH(Table2[[#This Row],[WBS_ID]], Table26[WBS CODE],0)), "") = "", "null", IFERROR(INDEX(WBS_Dictionary!L$2:L$1212, MATCH(Table2[[#This Row],[WBS_ID]], Table26[WBS CODE],0)), "")) -> null | ... AE534: =IF(IFERROR(INDEX(WBS_Dictionary!O$2:O$1212, MATCH(Table2[[#This Row],[WBS_ID]], Table26[WBS CODE],0)), "") = "", "null", IFERROR(INDEX(WBS_Dictionary!O$2:O$1212, MATCH(Table2[[#This Row],[WBS_ID]], Table26[WBS CODE],0)), "")) -> null
A535: 10 | B535: 04 | C535: Drilling Facilities Support | D535: E530-301291463-D225301 | E535: D225301 | F535: 141559 | G535: USD | H535: 141559 | I535: USD | J535: 0 | K535: USD | L535: 0 | M535: USD | N535: 111242.84 | O535: USD | Q535: X | R535: STAR ENERGY | S535: Production | T535: REL LKD BUDG AVAC // BUDG | U535: =IF(IFERROR(INDEX(WBS_Dictionary!E$2:E$1212, MATCH(Table2[[#This Row],[WBS_ID]], Table26[WBS CODE],0)), "") = "", "null", IFERROR(INDEX(WBS_Dictionary!E$2:E$1212, MATCH(Table2[[#This Row],[WBS_ID]], Table26[WBS CODE],0)), "")) -> E530-30-D225301 | V535: =IF(IFERROR(INDEX(WBS_Dictionary!F$2:F$1212, MATCH(Table2[[#This Row],[WBS_ID]], Table26[WBS CODE],0)), "") = "", "null", IFERROR(INDEX(WBS_Dictionary!F$2:F$1212, MATCH(Table2[[#This Row],[WBS_ID]], Table26[WBS CODE],0)), "")) -> E530-30129-D225301 | W535: =IF(IFERROR(INDEX(WBS_Dictionary!G$2:G$1212, MATCH(Table2[[#This Row],[WBS_ID]], Table26[WBS CODE],0)), "") = "", "null", IFERROR(INDEX(WBS_Dictionary!G$2:G$1212, MATCH(Table2[[#This Row],[WBS_ID]], Table26[WBS CODE],0)), "")) -> E530-3012914-D225301 | X535: =IF(IFERROR(INDEX(WBS_Dictionary!H$2:H$1212, MATCH(Table2[[#This Row],[WBS_ID]], Table26[WBS CODE],0)), "") = "", "null", IFERROR(INDEX(WBS_Dictionary!H$2:H$1212, MATCH(Table2[[#This Row],[WBS_ID]], Table26[WBS CODE],0)), "")) -> E530-301291463-D225301 | Y535: =IF(IFERROR(INDEX(WBS_Dictionary!I$2:I$1212, MATCH(Table2[[#This Row],[WBS_ID]], Table26[WBS CODE],0)), "") = "", "null", IFERROR(INDEX(WBS_Dictionary!I$2:I$1212, MATCH(Table2[[#This Row],[WBS_ID]], Table26[WBS CODE],0)), "")) -> null | Z535: =IF(IFERROR(INDEX(WBS_Dictionary!J$2:J$1212, MATCH(Table2[[#This Row],[WBS_ID]], Table26[WBS CODE],0)), "") = "", "null", IFERROR(INDEX(WBS_Dictionary!J$2:J$1212, MATCH(Table2[[#This Row],[WBS_ID]], Table26[WBS CODE],0)), "")) -> Support Cost | AA535: =IF(IFERROR(INDEX(WBS_Dictionary!K$2:K$1212, MATCH(Table2[[#This Row],[WBS_ID]], Table26[WBS CODE],0)), "") = "", "null", IFERROR(INDEX(WBS_Dictionary!K$2:K$1212, MATCH(Table2[[#This Row],[WBS_ID]], Table26[WBS CODE],0)), "")) -> Drilling Facilities Support | AB535: =IF(IFERROR(INDEX(WBS_Dictionary!L$2:L$1212, MATCH(Table2[[#This Row],[WBS_ID]], Table26[WBS CODE],0)), "") = "", "null", IFERROR(INDEX(WBS_Dictionary!L$2:L$1212, MATCH(Table2[[#This Row],[WBS_ID]], Table26[WBS CODE],0)), "")) -> Drilling Facilities Support | ... AE535: =IF(IFERROR(INDEX(WBS_Dictionary!O$2:O$1212, MATCH(Table2[[#This Row],[WBS_ID]], Table26[WBS CODE],0)), "") = "", "null", IFERROR(INDEX(WBS_Dictionary!O$2:O$1212, MATCH(Table2[[#This Row],[WBS_ID]], Table26[WBS CODE],0)), "")) -> null
A536: 11 | B536: 05 | C536: Drilling Facilities Support | D536: E530-30129146321-D225301 | E536: D225301 | F536: 0 | G536: USD | H536: 0 | I536: USD | J536: 0 | K536: USD | L536: 0 | M536: USD | N536: 111242.84 | O536: USD | Q536: X | R536: STAR ENERGY | S536: Production | T536: REL LKD AVAC SETC // BUDG | U536: =IF(IFERROR(INDEX(WBS_Dictionary!E$2:E$1212, MATCH(Table2[[#This Row],[WBS_ID]], Table26[WBS CODE],0)), "") = "", "null", IFERROR(INDEX(WBS_Dictionary!E$2:E$1212, MATCH(Table2[[#This Row],[WBS_ID]], Table26[WBS CODE],0)), "")) -> E530-30-D225301 | V536: =IF(IFERROR(INDEX(WBS_Dictionary!F$2:F$1212, MATCH(Table2[[#This Row],[WBS_ID]], Table26[WBS CODE],0)), "") = "", "null", IFERROR(INDEX(WBS_Dictionary!F$2:F$1212, MATCH(Table2[[#This Row],[WBS_ID]], Table26[WBS CODE],0)), "")) -> E530-30129-D225301 | W536: =IF(IFERROR(INDEX(WBS_Dictionary!G$2:G$1212, MATCH(Table2[[#This Row],[WBS_ID]], Table26[WBS CODE],0)), "") = "", "null", IFERROR(INDEX(WBS_Dictionary!G$2:G$1212, MATCH(Table2[[#This Row],[WBS_ID]], Table26[WBS CODE],0)), "")) -> E530-3012914-D225301 | X536: =IF(IFERROR(INDEX(WBS_Dictionary!H$2:H$1212, MATCH(Table2[[#This Row],[WBS_ID]], Table26[WBS CODE],0)), "") = "", "null", IFERROR(INDEX(WBS_Dictionary!H$2:H$1212, MATCH(Table2[[#This Row],[WBS_ID]], Table26[WBS CODE],0)), "")) -> E530-301291463-D225301 | Y536: =IF(IFERROR(INDEX(WBS_Dictionary!I$2:I$1212, MATCH(Table2[[#This Row],[WBS_ID]], Table26[WBS CODE],0)), "") = "", "null", IFERROR(INDEX(WBS_Dictionary!I$2:I$1212, MATCH(Table2[[#This Row],[WBS_ID]], Table26[WBS CODE],0)), "")) -> E530-30129146321-D225301 | Z536: =IF(IFERROR(INDEX(WBS_Dictionary!J$2:J$1212, MATCH(Table2[[#This Row],[WBS_ID]], Table26[WBS CODE],0)), "") = "", "null", IFERROR(INDEX(WBS_Dictionary!J$2:J$1212, MATCH(Table2[[#This Row],[WBS_ID]], Table26[WBS CODE],0)), "")) -> Support Cost | AA536: =IF(IFERROR(INDEX(WBS_Dictionary!K$2:K$1212, MATCH(Table2[[#This Row],[WBS_ID]], Table26[WBS CODE],0)), "") = "", "null", IFERROR(INDEX(WBS_Dictionary!K$2:K$1212, MATCH(Table2[[#This Row],[WBS_ID]], Table26[WBS CODE],0)), "")) -> Drilling Facilities Support | AB536: =IF(IFERROR(INDEX(WBS_Dictionary!L$2:L$1212, MATCH(Table2[[#This Row],[WBS_ID]], Table26[WBS CODE],0)), "") = "", "null", IFERROR(INDEX(WBS_Dictionary!L$2:L$1212, MATCH(Table2[[#This Row],[WBS_ID]], Table26[WBS CODE],0)), "")) -> Drilling Facilities Support | ... AE536: =IF(IFERROR(INDEX(WBS_Dictionary!O$2:O$1212, MATCH(Table2[[#This Row],[WBS_ID]], Table26[WBS CODE],0)), "") = "", "null", IFERROR(INDEX(WBS_Dictionary!O$2:O$1212, MATCH(Table2[[#This Row],[WBS_ID]], Table26[WBS CODE],0)), "")) -> null
